{
  "birthplace": null, 
  "weight": "127", 
  "firstname": "Alex", 
  "club": null, 
  "lastname": "Rose", 
  "results": [
    {
      "competition_ID": "12795197", 
      "compName": null, 
      "roundstage": "Final", 
      "venue": "Raleigh NC", 
      "IndoorOutdoor": "Outdoor", 
      "agegroup": null, 
      "venueCountry": "USA", 
      "rank": "4", 
      "event": "DT", 
      "result": "51.05", 
      "date": "2010-03-26", 
      "round": null, 
      "wind": null
    }, 
    {
      "competition_ID": "12795519", 
      "compName": null, 
      "roundstage": "Final", 
      "venue": "Big Rapids MI", 
      "IndoorOutdoor": "Outdoor", 
      "agegroup": null, 
      "venueCountry": "USA", 
      "rank": "2", 
      "event": "DT", 
      "result": "52.10", 
      "date": "2010-04-10", 
      "round": null, 
      "wind": null
    }, 
    {
      "competition_ID": "12795961", 
      "compName": null, 
      "roundstage": "Final", 
      "venue": "Louisville KY", 
      "IndoorOutdoor": "Outdoor", 
      "agegroup": null, 
      "venueCountry": "USA", 
      "rank": "1", 
      "event": "DT", 
      "result": "54.76", 
      "date": "2010-04-16", 
      "round": null, 
      "wind": null
    }, 
    {
      "competition_ID": "12796095", 
      "compName": null, 
      "roundstage": "Final", 
      "venue": "Norman OK", 
      "IndoorOutdoor": "Outdoor", 
      "agegroup": null, 
      "venueCountry": "USA", 
      "rank": "5", 
      "event": "DT", 
      "result": "53.73", 
      "date": "2010-04-24", 
      "round": null, 
      "wind": null
    }, 
    {
      "competition_ID": "12796519", 
      "compName": null, 
      "roundstage": "Final", 
      "venue": "Ann Arbor MI", 
      "IndoorOutdoor": "Outdoor", 
      "agegroup": null, 
      "venueCountry": "USA", 
      "rank": "1", 
      "event": "DT", 
      "result": "55.24", 
      "date": "2010-05-08", 
      "round": null, 
      "wind": null
    }, 
    {
      "competition_ID": "12796781", 
      "compName": null, 
      "roundstage": "Final", 
      "venue": "Amherst NY", 
      "IndoorOutdoor": "Outdoor", 
      "agegroup": null, 
      "venueCountry": "USA", 
      "rank": "8", 
      "event": "SP", 
      "result": "16.42", 
      "date": "2010-05-14", 
      "round": null, 
      "wind": null
    }, 
    {
      "competition_ID": "12797570", 
      "compName": null, 
      "roundstage": "Prelim", 
      "venue": "Greensboro NC", 
      "IndoorOutdoor": "Outdoor", 
      "agegroup": null, 
      "venueCountry": "USA", 
      "rank": "7", 
      "event": "DT", 
      "result": "54.69", 
      "date": "2010-05-29", 
      "round": "q", 
      "wind": null
    }, 
    {
      "competition_ID": "12798019", 
      "compName": null, 
      "roundstage": "Final", 
      "venue": "Eugene OR", 
      "IndoorOutdoor": "Outdoor", 
      "agegroup": null, 
      "venueCountry": "USA", 
      "rank": "13", 
      "event": "DT", 
      "result": "54.01", 
      "date": "2010-06-09", 
      "round": null, 
      "wind": null
    }, 
    {
      "competition_ID": "12798896", 
      "compName": null, 
      "roundstage": "Final", 
      "venue": "Des Moines IA", 
      "IndoorOutdoor": "Outdoor", 
      "agegroup": "Under 20", 
      "venueCountry": "USA", 
      "rank": "2", 
      "event": "DT1.75", 
      "result": "57.51", 
      "date": "2010-06-24", 
      "round": "-19", 
      "wind": null
    }, 
    {
      "competition_ID": "12800024", 
      "compName": null, 
      "roundstage": "Prelim", 
      "venue": "Moncton", 
      "IndoorOutdoor": "Outdoor", 
      "agegroup": null, 
      "venueCountry": "CAN", 
      "rank": "22", 
      "event": "DT1.75", 
      "result": "53.46", 
      "date": "2010-07-23", 
      "round": "q-19", 
      "wind": null
    }, 
    {
      "competition_ID": "12805035", 
      "compName": "CMU Chippewa Invite", 
      "roundstage": "Final", 
      "venue": "East Lansing MI", 
      "IndoorOutdoor": "Indoor", 
      "agegroup": null, 
      "venueCountry": "USA", 
      "rank": "1", 
      "event": "SP", 
      "result": "16.78", 
      "date": "2011-01-14", 
      "round": null, 
      "wind": null
    }, 
    {
      "competition_ID": "12805610", 
      "compName": "Simmons-Harvey Invitational, U of M Indoor Track", 
      "roundstage": "Final", 
      "venue": "Ann Arbor MI", 
      "IndoorOutdoor": "Indoor", 
      "agegroup": null, 
      "venueCountry": "USA", 
      "rank": "4", 
      "event": "SP", 
      "result": "16.70", 
      "date": "2011-01-22", 
      "round": null, 
      "wind": null
    }, 
    {
      "competition_ID": "12805876", 
      "compName": null, 
      "roundstage": "Final", 
      "venue": "Saginaw MI", 
      "IndoorOutdoor": "Indoor", 
      "agegroup": null, 
      "venueCountry": "USA", 
      "rank": "1", 
      "event": "SP", 
      "result": "17.13", 
      "date": "2011-01-28", 
      "round": null, 
      "wind": null
    }, 
    {
      "competition_ID": "12806478", 
      "compName": null, 
      "roundstage": "Final", 
      "venue": "Akron OH", 
      "IndoorOutdoor": "Indoor", 
      "agegroup": null, 
      "venueCountry": "USA", 
      "rank": "2", 
      "event": "DT", 
      "result": "54.13", 
      "date": "2011-02-12", 
      "round": null, 
      "wind": null
    }, 
    {
      "competition_ID": "12806478", 
      "compName": null, 
      "roundstage": "Final", 
      "venue": "Akron OH", 
      "IndoorOutdoor": "Indoor", 
      "agegroup": null, 
      "venueCountry": "USA", 
      "rank": "8", 
      "event": "SP", 
      "result": "16.57", 
      "date": "2011-02-12", 
      "round": null, 
      "wind": null
    }, 
    {
      "competition_ID": "12807795", 
      "compName": "Defiance Dick Small Invitational", 
      "roundstage": "Final", 
      "venue": "Defiance OH", 
      "IndoorOutdoor": "Outdoor", 
      "agegroup": null, 
      "venueCountry": "USA", 
      "rank": "1", 
      "event": "DT", 
      "result": "56.14", 
      "date": "2011-03-19", 
      "round": null, 
      "wind": null
    }, 
    {
      "competition_ID": "12807795", 
      "compName": "Defiance Dick Small Invitational", 
      "roundstage": "Final", 
      "venue": "Defiance OH", 
      "IndoorOutdoor": "Outdoor", 
      "agegroup": null, 
      "venueCountry": "USA", 
      "rank": "1", 
      "event": "SP", 
      "result": "16.67", 
      "date": "2011-03-19", 
      "round": null, 
      "wind": null
    }, 
    {
      "competition_ID": "12808174", 
      "compName": "Toledo Collegiate Challenge", 
      "roundstage": "Final", 
      "venue": "Toledo OH", 
      "IndoorOutdoor": "Outdoor", 
      "agegroup": null, 
      "venueCountry": "USA", 
      "rank": "1", 
      "event": "DT", 
      "result": "57.86", 
      "date": "2011-04-02", 
      "round": null, 
      "wind": null
    }, 
    {
      "competition_ID": "12808336", 
      "compName": "Ed Adams Invitational", 
      "roundstage": "Final", 
      "venue": "Salinas CA", 
      "IndoorOutdoor": "Outdoor", 
      "agegroup": null, 
      "venueCountry": "USA", 
      "rank": "1", 
      "event": "DT", 
      "result": "58.70", 
      "date": "2011-04-09", 
      "round": null, 
      "wind": null
    }, 
    {
      "competition_ID": "12808324", 
      "compName": "Sacramento State MONDO Mid-Major Challenge", 
      "roundstage": "Final", 
      "venue": "Sacramento CA", 
      "IndoorOutdoor": "Outdoor", 
      "agegroup": null, 
      "venueCountry": "USA", 
      "rank": "1", 
      "event": "DT", 
      "result": "54.52", 
      "date": "2011-04-09", 
      "round": null, 
      "wind": null
    }, 
    {
      "competition_ID": "12808568", 
      "compName": "John Jacobs Collegiate Invitational", 
      "roundstage": "Prelim", 
      "venue": "Norman OK", 
      "IndoorOutdoor": "Outdoor", 
      "agegroup": null, 
      "venueCountry": "USA", 
      "rank": "3", 
      "event": "DT", 
      "result": "53.52", 
      "date": "2011-04-16", 
      "round": "cB", 
      "wind": null
    }, 
    {
      "competition_ID": "12809025", 
      "compName": "Lyle Bennett Open", 
      "roundstage": "Final", 
      "venue": "Mount Pleasant MI", 
      "IndoorOutdoor": "Outdoor", 
      "agegroup": null, 
      "venueCountry": "USA", 
      "rank": "1", 
      "event": "DT", 
      "result": "54.89", 
      "date": "2011-04-30", 
      "round": null, 
      "wind": null
    }, 
    {
      "competition_ID": "12809227", 
      "compName": "Len Paddock Invitational", 
      "roundstage": "Final", 
      "venue": "Ann Arbor MI", 
      "IndoorOutdoor": "Outdoor", 
      "agegroup": null, 
      "venueCountry": "USA", 
      "rank": "2", 
      "event": "DT", 
      "result": "54.53", 
      "date": "2011-05-07", 
      "round": null, 
      "wind": null
    }, 
    {
      "competition_ID": "12810645", 
      "compName": null, 
      "roundstage": "Prelim", 
      "venue": "Bloomington IN", 
      "IndoorOutdoor": "Outdoor", 
      "agegroup": null, 
      "venueCountry": "USA", 
      "rank": "3", 
      "event": "DT", 
      "result": "56.69", 
      "date": "2011-05-28", 
      "round": "q", 
      "wind": null
    }, 
    {
      "competition_ID": "12811335", 
      "compName": "NCAA Championships, Drake Stadium", 
      "roundstage": "Final", 
      "venue": "Des Moines IA", 
      "IndoorOutdoor": "Outdoor", 
      "agegroup": null, 
      "venueCountry": "USA", 
      "rank": "5", 
      "event": "DT", 
      "result": "56.64", 
      "date": "2011-06-08", 
      "round": null, 
      "wind": null
    }, 
    {
      "competition_ID": "12820355", 
      "compName": "Akron Invitational", 
      "roundstage": "Final", 
      "venue": "Akron OH", 
      "IndoorOutdoor": "Indoor", 
      "agegroup": null, 
      "venueCountry": "USA", 
      "rank": "2", 
      "event": "DT", 
      "result": "53.86", 
      "date": "2012-02-10", 
      "round": null, 
      "wind": null
    }, 
    {
      "competition_ID": "12821477", 
      "compName": null, 
      "roundstage": "Final", 
      "venue": "Baton Rouge LA", 
      "IndoorOutdoor": "Outdoor", 
      "agegroup": null, 
      "venueCountry": "USA", 
      "rank": "2", 
      "event": "DT", 
      "result": "53.66", 
      "date": "2012-03-24", 
      "round": null, 
      "wind": null
    }, 
    {
      "competition_ID": "12821643", 
      "compName": "Toledo Collegiate Challenge", 
      "roundstage": "Final", 
      "venue": "Toledo OH", 
      "IndoorOutdoor": "Outdoor", 
      "agegroup": null, 
      "venueCountry": "USA", 
      "rank": "3", 
      "event": "SP", 
      "result": "17.12", 
      "date": "2012-03-31", 
      "round": null, 
      "wind": null
    }, 
    {
      "competition_ID": "12822001", 
      "compName": "Northwood Open", 
      "roundstage": "Final", 
      "venue": "Midland MI", 
      "IndoorOutdoor": "Outdoor", 
      "agegroup": null, 
      "venueCountry": "USA", 
      "rank": "1", 
      "event": "DT", 
      "result": "52.32", 
      "date": "2012-04-14", 
      "round": null, 
      "wind": null
    }, 
    {
      "competition_ID": "12822001", 
      "compName": "Northwood Open", 
      "roundstage": "Final", 
      "venue": "Midland MI", 
      "IndoorOutdoor": "Outdoor", 
      "agegroup": null, 
      "venueCountry": "USA", 
      "rank": "1", 
      "event": "SP", 
      "result": "17.04", 
      "date": "2012-04-14", 
      "round": null, 
      "wind": null
    }, 
    {
      "competition_ID": "12822081", 
      "compName": "Cal St. Los Angeles Twilight Open", 
      "roundstage": "Final", 
      "venue": "Los Angeles CA", 
      "IndoorOutdoor": "Outdoor", 
      "agegroup": null, 
      "venueCountry": "USA", 
      "rank": "1", 
      "event": "DT", 
      "result": "54.55", 
      "date": "2012-04-19", 
      "round": null, 
      "wind": null
    }, 
    {
      "competition_ID": "12822073", 
      "compName": null, 
      "roundstage": "Final", 
      "venue": "Walnut CA", 
      "IndoorOutdoor": "Outdoor", 
      "agegroup": null, 
      "venueCountry": "USA", 
      "rank": "27", 
      "event": "DT", 
      "result": "51.62", 
      "date": "2012-04-20", 
      "round": null, 
      "wind": null
    }, 
    {
      "competition_ID": "12826563", 
      "compName": null, 
      "roundstage": "Final", 
      "venue": "Norwalk CA", 
      "IndoorOutdoor": "Outdoor", 
      "agegroup": null, 
      "venueCountry": "USA", 
      "rank": "5", 
      "event": "DT", 
      "result": "54.85", 
      "date": "2012-04-21", 
      "round": null, 
      "wind": null
    }, 
    {
      "competition_ID": "12822341", 
      "compName": "Central Michigan Lyle Bennett Open", 
      "roundstage": "Final", 
      "venue": "East Lansing MI", 
      "IndoorOutdoor": "Outdoor", 
      "agegroup": null, 
      "venueCountry": "USA", 
      "rank": "1", 
      "event": "DT", 
      "result": "55.04", 
      "date": "2012-04-28", 
      "round": null, 
      "wind": null
    }, 
    {
      "competition_ID": "12822505", 
      "compName": "Len Paddock Invitational", 
      "roundstage": "Final", 
      "venue": "Ann Arbor MI", 
      "IndoorOutdoor": "Outdoor", 
      "agegroup": null, 
      "venueCountry": "USA", 
      "rank": "1", 
      "event": "DT", 
      "result": "56.33", 
      "date": "2012-05-04", 
      "round": null, 
      "wind": null
    }, 
    {
      "competition_ID": "12822741", 
      "compName": "Mid-American Conference Championships", 
      "roundstage": "Final", 
      "venue": "Mount Pleasant MI", 
      "IndoorOutdoor": "Outdoor", 
      "agegroup": null, 
      "venueCountry": "USA", 
      "rank": "3", 
      "event": "SP", 
      "result": "16.98", 
      "date": "2012-05-11", 
      "round": null, 
      "wind": null
    }, 
    {
      "competition_ID": "12822741", 
      "compName": null, 
      "roundstage": "Final", 
      "venue": "Mount Pleasant MI", 
      "IndoorOutdoor": "Outdoor", 
      "agegroup": null, 
      "venueCountry": "USA", 
      "rank": "1", 
      "event": "DT", 
      "result": "55.11", 
      "date": "2012-05-12", 
      "round": null, 
      "wind": null
    }, 
    {
      "competition_ID": "12823080", 
      "compName": "NCAA East Preliminary Round, Hodges Stadium", 
      "roundstage": "Prelim", 
      "venue": "Jacksonville FL", 
      "IndoorOutdoor": "Outdoor", 
      "agegroup": null, 
      "venueCountry": "USA", 
      "rank": "21", 
      "event": "DT", 
      "result": "51.79", 
      "date": "2012-05-24", 
      "round": "q", 
      "wind": null
    }, 
    {
      "competition_ID": "12824355", 
      "compName": "National Championships & Olympic Trials, National Stadium", 
      "roundstage": "Final", 
      "venue": "Cairns", 
      "IndoorOutdoor": "Outdoor", 
      "agegroup": null, 
      "venueCountry": "AUS", 
      "rank": "1", 
      "event": "DT", 
      "result": "56.29", 
      "date": "2012-06-27", 
      "round": null, 
      "wind": null
    }, 
    {
      "competition_ID": "12828372", 
      "compName": null, 
      "roundstage": "Final", 
      "venue": "Allendale MI", 
      "IndoorOutdoor": "Indoor", 
      "agegroup": null, 
      "venueCountry": "USA", 
      "rank": "2", 
      "event": "SP", 
      "result": "16.99", 
      "date": "2013-01-26", 
      "round": null, 
      "wind": null
    }, 
    {
      "competition_ID": "12839402", 
      "compName": "Mid-American Indoor Championships", 
      "roundstage": "Final", 
      "venue": "Ypsilanti MI", 
      "IndoorOutdoor": "Indoor", 
      "agegroup": null, 
      "venueCountry": "USA", 
      "rank": "5", 
      "event": "SP", 
      "result": "17.11", 
      "date": "2013-02-22", 
      "round": null, 
      "wind": null
    }, 
    {
      "competition_ID": "12840294", 
      "compName": "Grand Rapids Open", 
      "roundstage": "Final", 
      "venue": "Grand Rapids MI", 
      "IndoorOutdoor": "Outdoor", 
      "agegroup": null, 
      "venueCountry": "USA", 
      "rank": "1", 
      "event": "DT", 
      "result": "56.04", 
      "date": "2013-03-30", 
      "round": null, 
      "wind": null
    }, 
    {
      "competition_ID": "12840459", 
      "compName": "Michigan State Spartan Invitational", 
      "roundstage": "Final", 
      "venue": "East Lansing MI", 
      "IndoorOutdoor": "Outdoor", 
      "agegroup": null, 
      "venueCountry": "USA", 
      "rank": "1", 
      "event": "DT", 
      "result": "55.30", 
      "date": "2013-04-06", 
      "round": null, 
      "wind": null
    }, 
    {
      "competition_ID": "12840988", 
      "compName": "Lyle Bennett Open", 
      "roundstage": "Final", 
      "venue": "Mount Pleasant MI", 
      "IndoorOutdoor": "Outdoor", 
      "agegroup": null, 
      "venueCountry": "USA", 
      "rank": "1", 
      "event": "DT", 
      "result": "57.03", 
      "date": "2013-04-27", 
      "round": null, 
      "wind": null
    }, 
    {
      "competition_ID": "12841218", 
      "compName": "28th Annual Toledo Invitational", 
      "roundstage": "Final", 
      "venue": "Toledo OH", 
      "IndoorOutdoor": "Outdoor", 
      "agegroup": null, 
      "venueCountry": "USA", 
      "rank": "1", 
      "event": "DT", 
      "result": "57.44", 
      "date": "2013-05-02", 
      "round": null, 
      "wind": null
    }, 
    {
      "competition_ID": "12843478", 
      "compName": null, 
      "roundstage": "Prelim", 
      "venue": "Kazan", 
      "IndoorOutdoor": "Outdoor", 
      "agegroup": null, 
      "venueCountry": "RUS", 
      "rank": "9", 
      "event": "DT", 
      "result": "57.14", 
      "date": "2013-07-10", 
      "round": "q", 
      "wind": null
    }, 
    {
      "competition_ID": "12843478", 
      "compName": null, 
      "roundstage": "Final", 
      "venue": "Kazan", 
      "IndoorOutdoor": "Outdoor", 
      "agegroup": null, 
      "venueCountry": "RUS", 
      "rank": "6", 
      "event": "DT", 
      "result": "58.64", 
      "date": "2013-07-12", 
      "round": null, 
      "wind": null
    }, 
    {
      "competition_ID": "12844203", 
      "compName": null, 
      "roundstage": "Prelim", 
      "venue": "Moskva", 
      "IndoorOutdoor": "Outdoor", 
      "agegroup": null, 
      "venueCountry": "RUS", 
      "rank": "29", 
      "event": "DT", 
      "result": "56.19", 
      "date": "2013-08-12", 
      "round": "q", 
      "wind": null
    }, 
    {
      "competition_ID": "12847741", 
      "compName": "Akron Invitational", 
      "roundstage": "Final", 
      "venue": "Akron OH", 
      "IndoorOutdoor": "Indoor", 
      "agegroup": null, 
      "venueCountry": "USA", 
      "rank": "1", 
      "event": "DT", 
      "result": "54.63", 
      "date": "2014-02-08", 
      "round": null, 
      "wind": null
    }, 
    {
      "competition_ID": "12847741", 
      "compName": "Akron Invitational", 
      "roundstage": "Final", 
      "venue": "Akron OH", 
      "IndoorOutdoor": "Indoor", 
      "agegroup": null, 
      "venueCountry": "USA", 
      "rank": "5", 
      "event": "SP", 
      "result": "17.40", 
      "date": "2014-02-08", 
      "round": null, 
      "wind": null
    }, 
    {
      "competition_ID": "12848353", 
      "compName": "Mid-American Indoor Track & Field Championships", 
      "roundstage": "Final", 
      "venue": "Kent OH", 
      "IndoorOutdoor": "Indoor", 
      "agegroup": null, 
      "venueCountry": "USA", 
      "rank": "3", 
      "event": "SP", 
      "result": "17.69", 
      "date": "2014-03-01", 
      "round": null, 
      "wind": null
    }, 
    {
      "competition_ID": "12850224", 
      "compName": "Lenny Lyles-Clark Wood Invitational, Louisville", 
      "roundstage": "Final", 
      "venue": "Louisville KY", 
      "IndoorOutdoor": "Outdoor", 
      "agegroup": null, 
      "venueCountry": "USA", 
      "rank": "1", 
      "event": "DT", 
      "result": "56.42", 
      "date": "2014-03-28", 
      "round": null, 
      "wind": null
    }, 
    {
      "competition_ID": "12849059", 
      "compName": "Spartan Invitational, Michigan State", 
      "roundstage": "Final", 
      "venue": "East Lansing MI", 
      "IndoorOutdoor": "Outdoor", 
      "agegroup": null, 
      "venueCountry": "USA", 
      "rank": "2", 
      "event": "DT", 
      "result": "57.29", 
      "date": "2014-04-05", 
      "round": null, 
      "wind": null
    }, 
    {
      "competition_ID": "12849157", 
      "compName": "WKU Hilltopper Relays, Western Kentucky ", 
      "roundstage": "Final", 
      "venue": "Bowling Green KY", 
      "IndoorOutdoor": "Outdoor", 
      "agegroup": null, 
      "venueCountry": "USA", 
      "rank": "1", 
      "event": "DT", 
      "result": "55.69", 
      "date": "2014-04-12", 
      "round": null, 
      "wind": null
    }, 
    {
      "competition_ID": "12859087", 
      "compName": "Alma College Charlie Gray Invitational", 
      "roundstage": "Final", 
      "venue": "Alma MI", 
      "IndoorOutdoor": "Outdoor", 
      "agegroup": null, 
      "venueCountry": "USA", 
      "rank": "1", 
      "event": "DT", 
      "result": "54.68", 
      "date": "2015-04-03", 
      "round": null, 
      "wind": null
    }, 
    {
      "competition_ID": "12859391", 
      "compName": "Al Owens Open, Grand Valley State", 
      "roundstage": "Final", 
      "venue": "Allendale MI", 
      "IndoorOutdoor": "Outdoor", 
      "agegroup": null, 
      "venueCountry": "USA", 
      "rank": "1", 
      "event": "DT", 
      "result": "57.75", 
      "date": "2015-04-18", 
      "round": null, 
      "wind": null
    }, 
    {
      "competition_ID": "12859564", 
      "compName": "Ernie Mousseau Track & Field Classic, Houseman Field", 
      "roundstage": "Final", 
      "venue": "Grand Rapids MI", 
      "IndoorOutdoor": "Outdoor", 
      "agegroup": null, 
      "venueCountry": "USA", 
      "rank": "1", 
      "event": "DT", 
      "result": "59.16", 
      "date": "2015-04-25", 
      "round": null, 
      "wind": null
    }, 
    {
      "competition_ID": "12860078", 
      "compName": "Oceania Area Championships, Barlow Park", 
      "roundstage": "Final", 
      "venue": "Cairns", 
      "IndoorOutdoor": "Outdoor", 
      "agegroup": null, 
      "venueCountry": "AUS", 
      "rank": "1", 
      "event": "DT", 
      "result": "60.95", 
      "date": "2015-05-08", 
      "round": null, 
      "wind": null
    }, 
    {
      "competition_ID": "12860078", 
      "compName": "Oceania Area Championships, Barlow Park", 
      "roundstage": "Final", 
      "venue": "Cairns", 
      "IndoorOutdoor": "Outdoor", 
      "agegroup": null, 
      "venueCountry": "AUS", 
      "rank": "1", 
      "event": "SP", 
      "result": "16.89", 
      "date": "2015-05-09", 
      "round": null, 
      "wind": null
    }, 
    {
      "competition_ID": "12860753", 
      "compName": "Running Factory Windsor Open", 
      "roundstage": "Final", 
      "venue": "Windsor", 
      "IndoorOutdoor": "Outdoor", 
      "agegroup": null, 
      "venueCountry": "CAN", 
      "rank": "1", 
      "event": "DT", 
      "result": "59.31", 
      "date": "2015-05-23", 
      "round": null, 
      "wind": null
    }, 
    {
      "competition_ID": "12861331", 
      "compName": "Field of Dreams, Claremont College", 
      "roundstage": "Final", 
      "venue": "Claremont CA", 
      "IndoorOutdoor": "Outdoor", 
      "agegroup": null, 
      "venueCountry": "USA", 
      "rank": "2", 
      "event": "DT", 
      "result": "60.41", 
      "date": "2015-06-06", 
      "round": null, 
      "wind": null
    }, 
    {
      "competition_ID": "12861667", 
      "compName": "Field of Dreams, Claremont College", 
      "roundstage": "Final", 
      "venue": "Claremont CA", 
      "IndoorOutdoor": "Outdoor", 
      "agegroup": null, 
      "venueCountry": "USA", 
      "rank": "2", 
      "event": "DT", 
      "result": "61.35", 
      "date": "2015-06-07", 
      "round": null, 
      "wind": null
    }, 
    {
      "competition_ID": "12863535", 
      "compName": " Pacific Games, John Guise Stadium", 
      "roundstage": "Final", 
      "venue": "Port Moresby", 
      "IndoorOutdoor": "Outdoor", 
      "agegroup": null, 
      "venueCountry": "PNG", 
      "rank": "2", 
      "event": "HT", 
      "result": "58.66", 
      "date": "2015-07-15", 
      "round": null, 
      "wind": null
    }, 
    {
      "competition_ID": "12863535", 
      "compName": " Pacific Games, John Guise Stadium", 
      "roundstage": "Final", 
      "venue": "Port Moresby", 
      "IndoorOutdoor": "Outdoor", 
      "agegroup": null, 
      "venueCountry": "PNG", 
      "rank": "1", 
      "event": "DT", 
      "result": "56.40", 
      "date": "2015-07-16", 
      "round": null, 
      "wind": null
    }, 
    {
      "competition_ID": "12863535", 
      "compName": " Pacific Games, John Guise Stadium", 
      "roundstage": "Final", 
      "venue": "Port Moresby", 
      "IndoorOutdoor": "Outdoor", 
      "agegroup": null, 
      "venueCountry": "PNG", 
      "rank": "2", 
      "event": "SP", 
      "result": "16.58", 
      "date": "2015-07-17", 
      "round": null, 
      "wind": null
    }, 
    {
      "competition_ID": "12863607", 
      "compName": "Tilastopajacup, Paavo Nurmi Stadium", 
      "roundstage": "Prelim", 
      "venue": "Beijing", 
      "IndoorOutdoor": "Outdoor", 
      "agegroup": null, 
      "venueCountry": "CHN", 
      "rank": "25", 
      "event": "DT", 
      "result": "59.07", 
      "date": "2015-08-27", 
      "round": "q", 
      "wind": null
    }, 
    {
      "competition_ID": "12870160", 
      "compName": "Margaret Bradley Invitational, Henry Crown Fieldhouse", 
      "roundstage": "Final", 
      "venue": "Chicago IL", 
      "IndoorOutdoor": "Indoor", 
      "agegroup": null, 
      "venueCountry": "USA", 
      "rank": "11", 
      "event": "SP", 
      "result": "16.70", 
      "date": "2016-02-20", 
      "round": null, 
      "wind": null
    }, 
    {
      "competition_ID": "12871521", 
      "compName": null, 
      "roundstage": "Final", 
      "venue": "Sydney", 
      "IndoorOutdoor": "Outdoor", 
      "agegroup": null, 
      "venueCountry": "AUS", 
      "rank": "2", 
      "event": "DT", 
      "result": "60.24", 
      "date": "2016-04-02", 
      "round": null, 
      "wind": null
    }, 
    {
      "competition_ID": "12871955", 
      "compName": "Millikin University Big Blue Invitational", 
      "roundstage": "Final", 
      "venue": "Decatur IL", 
      "IndoorOutdoor": "Outdoor", 
      "agegroup": null, 
      "venueCountry": "USA", 
      "rank": "2", 
      "event": "DT", 
      "result": "58.40", 
      "date": "2016-04-09", 
      "round": null, 
      "wind": null
    }, 
    {
      "competition_ID": "12872193", 
      "compName": "Wheaton Don Church Twilight", 
      "roundstage": "Final", 
      "venue": "Wheaton IL", 
      "IndoorOutdoor": "Outdoor", 
      "agegroup": null, 
      "venueCountry": "USA", 
      "rank": "10", 
      "event": "DT", 
      "result": "62.55", 
      "date": "2016-04-16", 
      "round": null, 
      "wind": null
    }, 
    {
      "competition_ID": "12872494", 
      "compName": "Augustana College Meet of Champions", 
      "roundstage": "Final", 
      "venue": "Rock Island IL", 
      "IndoorOutdoor": "Outdoor", 
      "agegroup": null, 
      "venueCountry": "USA", 
      "rank": "1", 
      "event": "DT", 
      "result": "63.06", 
      "date": "2016-04-23", 
      "round": null, 
      "wind": null
    }, 
    {
      "competition_ID": "12872647", 
      "compName": "2016 Drake Relays Presented By Hy-Vee, Drake Stadium ", 
      "roundstage": "Final", 
      "venue": "Des Moines IA", 
      "IndoorOutdoor": "Outdoor", 
      "agegroup": null, 
      "venueCountry": "USA", 
      "rank": "2", 
      "event": "DT", 
      "result": "58.98", 
      "date": "2016-04-30", 
      "round": null, 
      "wind": null
    }, 
    {
      "competition_ID": "12873298", 
      "compName": "Dr. Keeler Track & Field Meet", 
      "roundstage": "Final", 
      "venue": "Naperville IL", 
      "IndoorOutdoor": "Outdoor", 
      "agegroup": null, 
      "venueCountry": "USA", 
      "rank": "1", 
      "event": "DT", 
      "result": "63.23", 
      "date": "2016-05-12", 
      "round": null, 
      "wind": null
    }, 
    {
      "competition_ID": "12873358", 
      "compName": "All On The Line Nationals Qualifier and Harry Marra Multis", 
      "roundstage": "Final", 
      "venue": "Santa Barbara CA", 
      "IndoorOutdoor": "Outdoor", 
      "agegroup": null, 
      "venueCountry": "USA", 
      "rank": "1", 
      "event": "DT", 
      "result": "60.59", 
      "date": "2016-05-14", 
      "round": null, 
      "wind": null
    }, 
    {
      "competition_ID": "12873487", 
      "compName": "Field of Dreams", 
      "roundstage": "Final", 
      "venue": "Claremont CA", 
      "IndoorOutdoor": "Outdoor", 
      "agegroup": null, 
      "venueCountry": "USA", 
      "rank": "1", 
      "event": "DT", 
      "result": "65.74", 
      "date": "2016-05-15", 
      "round": null, 
      "wind": null
    }, 
    {
      "competition_ID": "12873735", 
      "compName": "Augustana Midwest Twilight Qualifier", 
      "roundstage": "Final", 
      "venue": "Rock Island IL", 
      "IndoorOutdoor": "Outdoor", 
      "agegroup": null, 
      "venueCountry": "USA", 
      "rank": "1", 
      "event": "DT", 
      "result": "62.91", 
      "date": "2016-05-19", 
      "round": null, 
      "wind": null
    }, 
    {
      "competition_ID": "12875257", 
      "compName": "JN Racers Grand Prix, National Stadium", 
      "roundstage": "Final", 
      "venue": "Kingston", 
      "IndoorOutdoor": "Outdoor", 
      "agegroup": null, 
      "venueCountry": "JAM", 
      "rank": "6", 
      "event": "DT", 
      "result": "60.10", 
      "date": "2016-06-11", 
      "round": null, 
      "wind": null
    }, 
    {
      "competition_ID": "12875879", 
      "compName": "34th Meeting Madrid, Centro Deportivo Municipal Moratalaz", 
      "roundstage": "Final", 
      "venue": "Madrid", 
      "IndoorOutdoor": "Outdoor", 
      "agegroup": null, 
      "venueCountry": "ESP", 
      "rank": "7", 
      "event": "DT", 
      "result": "58.72", 
      "date": "2016-06-23", 
      "round": null, 
      "wind": null
    }, 
    {
      "competition_ID": "12876040", 
      "compName": null, 
      "roundstage": "Final", 
      "venue": "Sollentuna", 
      "IndoorOutdoor": "Outdoor", 
      "agegroup": null, 
      "venueCountry": "SWE", 
      "rank": "5", 
      "event": "DT", 
      "result": "60.56", 
      "date": "2016-06-28", 
      "round": null, 
      "wind": null
    }, 
    {
      "competition_ID": "12877460", 
      "compName": "31st Olympic Games, Olympic Stadium", 
      "roundstage": "Prelim", 
      "venue": "R\u00c3\u00ado de Janeiro", 
      "IndoorOutdoor": "Outdoor", 
      "agegroup": null, 
      "venueCountry": "BRA", 
      "rank": "29", 
      "event": "DT", 
      "result": "57.24", 
      "date": "2016-08-12", 
      "round": "q", 
      "wind": null
    }
  ], 
  "athlete_id": "122371", 
  "birthdate": "17.11.1991", 
  "height": "188", 
  "birthyear": "1991", 
  "accomplishments": "\n", 
  "gender": "M", 
  "nationality": "SAM"
}