﻿<?xml version="1.0" encoding="utf-8" ?>
<results>
<result>
<athlete_id>140163</athlete_id>
<gender>M</gender>
<personalBest>
<IndoorOutdoor>Outdoor</IndoorOutdoor>
<event>SP6</event>
<result>16.83</result>
<wind></wind>
<rank>5</rank>
<round>-19</round>
<roundstage>Final</roundstage>
<agegroup>Under 20</agegroup>
<competition_ID>12853729</competition_ID>
<compName>Nordic Junior Match</compName>
<date>2014-08-16</date>
<venue>Kristiansand</venue>
<venueCountry>NOR</venueCountry>
</personalBest>
<personalBest>
<IndoorOutdoor>Outdoor</IndoorOutdoor>
<event>DT1.75</event>
<result>52.87</result>
<wind></wind>
<rank>5</rank>
<round>-19</round>
<roundstage>Final</roundstage>
<agegroup>Under 20</agegroup>
<competition_ID>12853729</competition_ID>
<compName>Nordic Junior Match</compName>
<date>2014-08-17</date>
<venue>Kristiansand</venue>
<venueCountry>NOR</venueCountry>
</personalBest>
<personalBest>
<IndoorOutdoor>Outdoor</IndoorOutdoor>
<event>DT</event>
<result>63.50</result>
<wind></wind>
<rank>1</rank>
<round></round>
<roundstage>Final</roundstage>
<agegroup></agegroup>
<competition_ID>12864312</competition_ID>
<compName></compName>
<date>2015-09-10</date>
<venue>Hafnarfjördur</venue>
<venueCountry>ISL</venueCountry>
</personalBest>
<personalBest>
<IndoorOutdoor>Indoor</IndoorOutdoor>
<event>SP</event>
<result>17.17</result>
<wind></wind>
<rank>4</rank>
<round></round>
<roundstage>Final</roundstage>
<agegroup></agegroup>
<competition_ID>12869529</competition_ID>
<compName>Botnia Games, Botniahalli, 400m oversized track</compName>
<date>2016-02-06</date>
<venue>Mustasaari</venue>
<venueCountry>FIN</venueCountry>
</personalBest>
<personalBest>
<IndoorOutdoor>Indoor</IndoorOutdoor>
<event>DT</event>
<result>58.59</result>
<wind></wind>
<rank>2</rank>
<round></round>
<roundstage>Final</roundstage>
<agegroup></agegroup>
<competition_ID>12869529</competition_ID>
<compName>Botnia Games, Botniahalli, 400m oversized track</compName>
<date>2016-02-06</date>
<venue>Mustasaari</venue>
<venueCountry>FIN</venueCountry>
</personalBest>
<personalBest>
<IndoorOutdoor>Outdoor</IndoorOutdoor>
<event>SP</event>
<result>16.68</result>
<wind></wind>
<rank>1</rank>
<round>-22</round>
<roundstage>Final</roundstage>
<agegroup>Under 23</agegroup>
<competition_ID>12877731</competition_ID>
<compName>Meistaramót Íslands 15-22 ára</compName>
<date>2016-08-27</date>
<venue>Hafnarfjördur</venue>
<venueCountry>ISL</venueCountry>
</personalBest>
<seasonalBest>
<IndoorOutdoor>Indoor</IndoorOutdoor>
<event>SP</event>
<result>17.17</result>
<wind></wind>
<rank>4</rank>
<round></round>
<roundstage>Final</roundstage>
<agegroup></agegroup>
<competition_ID>12869529</competition_ID>
<compName>Botnia Games, Botniahalli, 400m oversized track</compName>
<date>2016-02-06</date>
<venue>Mustasaari</venue>
<venueCountry>FIN</venueCountry>
</seasonalBest>
<seasonalBest>
<IndoorOutdoor>Indoor</IndoorOutdoor>
<event>DT</event>
<result>58.59</result>
<wind></wind>
<rank>2</rank>
<round></round>
<roundstage>Final</roundstage>
<agegroup></agegroup>
<competition_ID>12869529</competition_ID>
<compName>Botnia Games, Botniahalli, 400m oversized track</compName>
<date>2016-02-06</date>
<venue>Mustasaari</venue>
<venueCountry>FIN</venueCountry>
</seasonalBest>
<seasonalBest>
<IndoorOutdoor>Outdoor</IndoorOutdoor>
<event>DT</event>
<result>61.85</result>
<wind></wind>
<rank>3</rank>
<round></round>
<roundstage>Final</roundstage>
<agegroup></agegroup>
<competition_ID>12876442</competition_ID>
<compName>Leonardo Trainni Memorial</compName>
<date>2016-07-01</date>
<venue>Heerhugowaard</venue>
<venueCountry>NED</venueCountry>
</seasonalBest>
<seasonalBest>
<IndoorOutdoor>Outdoor</IndoorOutdoor>
<event>SP</event>
<result>16.68</result>
<wind></wind>
<rank>1</rank>
<round>-22</round>
<roundstage>Final</roundstage>
<agegroup>Under 23</agegroup>
<competition_ID>12877731</competition_ID>
<compName>Meistaramót Íslands 15-22 ára</compName>
<date>2016-08-27</date>
<venue>Hafnarfjördur</venue>
<venueCountry>ISL</venueCountry>
</seasonalBest>
<athleteresulthistory>
<record>
<IndoorOutdoor>Indoor</IndoorOutdoor>
<event>SP</event>
<result>13.71</result>
<wind></wind>
<rank>4</rank>
<round></round>
<roundstage>Final</roundstage>
<agegroup></agegroup>
<competition_ID>12828197</competition_ID>
<compName>Reykjavik International Games, Laugardalshöll</compName>
<date>2013-01-19</date>
<venue>Reykjavik</venue>
<venueCountry>ISL</venueCountry>
</record>
<record>
<IndoorOutdoor>Indoor</IndoorOutdoor>
<event>SP</event>
<result>14.26</result>
<wind></wind>
<rank>6</rank>
<round></round>
<roundstage>Final</roundstage>
<agegroup></agegroup>
<competition_ID>12847032</competition_ID>
<compName>Reykjavík International Games, Laugardalshöll</compName>
<date>2014-01-19</date>
<venue>Reykjavik</venue>
<venueCountry>ISL</venueCountry>
</record>
<record>
<IndoorOutdoor>Outdoor</IndoorOutdoor>
<event>DT</event>
<result>47.05</result>
<wind></wind>
<rank>1</rank>
<round></round>
<roundstage>Final</roundstage>
<agegroup></agegroup>
<competition_ID>12853501</competition_ID>
<compName>National Championships</compName>
<date>2014-07-13</date>
<venue>Hafnarfjördur</venue>
<venueCountry>ISL</venueCountry>
</record>
<record>
<IndoorOutdoor>Outdoor</IndoorOutdoor>
<event>SP6</event>
<result>16.83</result>
<wind></wind>
<rank>5</rank>
<round>-19</round>
<roundstage>Final</roundstage>
<agegroup>Under 20</agegroup>
<competition_ID>12853729</competition_ID>
<compName>Nordic Junior Match</compName>
<date>2014-08-16</date>
<venue>Kristiansand</venue>
<venueCountry>NOR</venueCountry>
</record>
<record>
<IndoorOutdoor>Outdoor</IndoorOutdoor>
<event>DT1.75</event>
<result>52.87</result>
<wind></wind>
<rank>5</rank>
<round>-19</round>
<roundstage>Final</roundstage>
<agegroup>Under 20</agegroup>
<competition_ID>12853729</competition_ID>
<compName>Nordic Junior Match</compName>
<date>2014-08-17</date>
<venue>Kristiansand</venue>
<venueCountry>NOR</venueCountry>
</record>
<record>
<IndoorOutdoor>Outdoor</IndoorOutdoor>
<event>DT</event>
<result>53.25</result>
<wind></wind>
<rank>1</rank>
<round></round>
<roundstage>Final</roundstage>
<agegroup></agegroup>
<competition_ID>12859119</competition_ID>
<compName></compName>
<date>2014-09-30</date>
<venue>Hafnarfjördur</venue>
<venueCountry>ISL</venueCountry>
</record>
<record>
<IndoorOutdoor>Indoor</IndoorOutdoor>
<event>SP</event>
<result>15.62</result>
<wind></wind>
<rank>3</rank>
<round></round>
<roundstage>Final</roundstage>
<agegroup></agegroup>
<competition_ID>12855899</competition_ID>
<compName>Reykjavik International Games</compName>
<date>2015-01-17</date>
<venue>Reykjavik</venue>
<venueCountry>ISL</venueCountry>
</record>
<record>
<IndoorOutdoor>Indoor</IndoorOutdoor>
<event>SP</event>
<result>16.29</result>
<wind></wind>
<rank>3</rank>
<round></round>
<roundstage>Final</roundstage>
<agegroup></agegroup>
<competition_ID>12856601</competition_ID>
<compName>Stórmót ÍR</compName>
<date>2015-01-31</date>
<venue>Reykjavik</venue>
<venueCountry>ISL</venueCountry>
</record>
<record>
<IndoorOutdoor>Outdoor</IndoorOutdoor>
<event>DT</event>
<result>54.61</result>
<wind></wind>
<rank>1</rank>
<round></round>
<roundstage>Final</roundstage>
<agegroup></agegroup>
<competition_ID>12860950</competition_ID>
<compName></compName>
<date>2015-05-02</date>
<venue>Hafnarfjördur</venue>
<venueCountry>ISL</venueCountry>
</record>
<record>
<IndoorOutdoor>Outdoor</IndoorOutdoor>
<event>DT</event>
<result>55.61</result>
<wind></wind>
<rank>1</rank>
<round></round>
<roundstage>Final</roundstage>
<agegroup></agegroup>
<competition_ID>12860952</competition_ID>
<compName></compName>
<date>2015-05-04</date>
<venue>Hafnarfjördur</venue>
<venueCountry>ISL</venueCountry>
</record>
<record>
<IndoorOutdoor>Outdoor</IndoorOutdoor>
<event>DT</event>
<result>56.40</result>
<wind></wind>
<rank>1</rank>
<round></round>
<roundstage>Final</roundstage>
<agegroup></agegroup>
<competition_ID>12860945</competition_ID>
<compName></compName>
<date>2015-06-04</date>
<venue>Reykjavik</venue>
<venueCountry>ISL</venueCountry>
</record>
<record>
<IndoorOutdoor>Outdoor</IndoorOutdoor>
<event>DT</event>
<result>57.89</result>
<wind></wind>
<rank>4</rank>
<round></round>
<roundstage>Final</roundstage>
<agegroup></agegroup>
<competition_ID>12861915</competition_ID>
<compName></compName>
<date>2015-06-21</date>
<venue>Stara Zagora</venue>
<venueCountry>BUL</venueCountry>
</record>
<record>
<IndoorOutdoor>Outdoor</IndoorOutdoor>
<event>DT</event>
<result>58.01</result>
<wind></wind>
<rank>1</rank>
<round></round>
<roundstage>Final</roundstage>
<agegroup></agegroup>
<competition_ID>12862365</competition_ID>
<compName></compName>
<date>2015-06-26</date>
<venue>Hafnarfjördur</venue>
<venueCountry>ISL</venueCountry>
</record>
<record>
<IndoorOutdoor>Outdoor</IndoorOutdoor>
<event>DT</event>
<result>57.50</result>
<wind></wind>
<rank>1</rank>
<round></round>
<roundstage>Final</roundstage>
<agegroup></agegroup>
<competition_ID>12862371</competition_ID>
<compName></compName>
<date>2015-06-29</date>
<venue>Reykjavik</venue>
<venueCountry>ISL</venueCountry>
</record>
<record>
<IndoorOutdoor>Outdoor</IndoorOutdoor>
<event>DT</event>
<result>58.39</result>
<wind></wind>
<rank>1</rank>
<round></round>
<roundstage>Final</roundstage>
<agegroup></agegroup>
<competition_ID>12862929</competition_ID>
<compName></compName>
<date>2015-07-04</date>
<venue>Reykjavik</venue>
<venueCountry>ISL</venueCountry>
</record>
<record>
<IndoorOutdoor>Outdoor</IndoorOutdoor>
<event>DT</event>
<result>53.66</result>
<wind></wind>
<rank>15</rank>
<round>q-22</round>
<roundstage>Prelim</roundstage>
<agegroup></agegroup>
<competition_ID>12862438</competition_ID>
<compName>10th European Athletics U23 Championships, Kadriorg Stadium</compName>
<date>2015-07-09</date>
<venue>Tallinn</venue>
<venueCountry>EST</venueCountry>
</record>
<record>
<IndoorOutdoor>Outdoor</IndoorOutdoor>
<event>DT</event>
<result>55.90</result>
<wind></wind>
<rank>1</rank>
<round></round>
<roundstage>Final</roundstage>
<agegroup></agegroup>
<competition_ID>12862912</competition_ID>
<compName>89th National Championships</compName>
<date>2015-07-26</date>
<venue>Kópavogur</venue>
<venueCountry>ISL</venueCountry>
</record>
<record>
<IndoorOutdoor>Outdoor</IndoorOutdoor>
<event>DT</event>
<result>54.60</result>
<wind></wind>
<rank>1</rank>
<round></round>
<roundstage>Final</roundstage>
<agegroup></agegroup>
<competition_ID>12863627</competition_ID>
<compName></compName>
<date>2015-08-08</date>
<venue>Reykjavik</venue>
<venueCountry>ISL</venueCountry>
</record>
<record>
<IndoorOutdoor>Outdoor</IndoorOutdoor>
<event>DT</event>
<result>51.59</result>
<wind></wind>
<rank>1</rank>
<round></round>
<roundstage>Final</roundstage>
<agegroup></agegroup>
<competition_ID>12863635</competition_ID>
<compName></compName>
<date>2015-08-15</date>
<venue>Saudárkrókur</venue>
<venueCountry>ISL</venueCountry>
</record>
<record>
<IndoorOutdoor>Outdoor</IndoorOutdoor>
<event>DT</event>
<result>63.50</result>
<wind></wind>
<rank>1</rank>
<round></round>
<roundstage>Final</roundstage>
<agegroup></agegroup>
<competition_ID>12864312</competition_ID>
<compName></compName>
<date>2015-09-10</date>
<venue>Hafnarfjördur</venue>
<venueCountry>ISL</venueCountry>
</record>
<record>
<IndoorOutdoor>Indoor</IndoorOutdoor>
<event>SP</event>
<result>16.90</result>
<wind></wind>
<rank>4</rank>
<round></round>
<roundstage>Final</roundstage>
<agegroup></agegroup>
<competition_ID>12867648</competition_ID>
<compName>Reykjavík Internatlonal Games, Laugardalshöllin</compName>
<date>2016-01-23</date>
<venue>Reykjavik</venue>
<venueCountry>ISL</venueCountry>
</record>
<record>
<IndoorOutdoor>Indoor</IndoorOutdoor>
<event>DT</event>
<result>58.59</result>
<wind></wind>
<rank>2</rank>
<round></round>
<roundstage>Final</roundstage>
<agegroup></agegroup>
<competition_ID>12869529</competition_ID>
<compName>Botnia Games, Botniahalli, 400m oversized track</compName>
<date>2016-02-06</date>
<venue>Mustasaari</venue>
<venueCountry>FIN</venueCountry>
</record>
<record>
<IndoorOutdoor>Indoor</IndoorOutdoor>
<event>SP</event>
<result>17.17</result>
<wind></wind>
<rank>4</rank>
<round></round>
<roundstage>Final</roundstage>
<agegroup></agegroup>
<competition_ID>12869529</competition_ID>
<compName>Botnia Games, Botniahalli, 400m oversized track</compName>
<date>2016-02-06</date>
<venue>Mustasaari</venue>
<venueCountry>FIN</venueCountry>
</record>
<record>
<IndoorOutdoor>Indoor</IndoorOutdoor>
<event>DT</event>
<result>58.47</result>
<wind></wind>
<rank>1</rank>
<round></round>
<roundstage>Final</roundstage>
<agegroup></agegroup>
<competition_ID>12869970</competition_ID>
<compName></compName>
<date>2016-02-13</date>
<venue>Växjö</venue>
<venueCountry>SWE</venueCountry>
</record>
<record>
<IndoorOutdoor>Indoor</IndoorOutdoor>
<event>SP</event>
<result>16.82</result>
<wind></wind>
<rank>8</rank>
<round></round>
<roundstage>Final</roundstage>
<agegroup></agegroup>
<competition_ID>12869850</competition_ID>
<compName>Nordenkampen, Sweden-Finland-Norway-Denmark International Indoor Match, Telekonsult Arena</compName>
<date>2016-02-13</date>
<venue>Växjö</venue>
<venueCountry>SWE</venueCountry>
</record>
<record>
<IndoorOutdoor>Indoor</IndoorOutdoor>
<event>SP</event>
<result>16.75</result>
<wind></wind>
<rank>1</rank>
<round>-22</round>
<roundstage>Final</roundstage>
<agegroup>Under 23</agegroup>
<competition_ID>12870581</competition_ID>
<compName>National U23, Junior &amp; Youth Indoor Championships</compName>
<date>2016-02-27</date>
<venue>Reykjavik</venue>
<venueCountry>ISL</venueCountry>
</record>
<record>
<IndoorOutdoor>Outdoor</IndoorOutdoor>
<event>DT</event>
<result>58.41</result>
<wind></wind>
<rank>1</rank>
<round></round>
<roundstage>Final</roundstage>
<agegroup></agegroup>
<competition_ID>12874865</competition_ID>
<compName>Kringlukastmót ÍR 2</compName>
<date>2016-05-12</date>
<venue>Reykjavik</venue>
<venueCountry>ISL</venueCountry>
</record>
<record>
<IndoorOutdoor>Outdoor</IndoorOutdoor>
<event>DT</event>
<result>52.87</result>
<wind></wind>
<rank>9</rank>
<round>cB</round>
<roundstage>Prelim</roundstage>
<agegroup></agegroup>
<competition_ID>12873645</competition_ID>
<compName>Hallesche Werfertage, Sportzentrum Brandberge</compName>
<date>2016-05-21</date>
<venue>Halle</venue>
<venueCountry>GER</venueCountry>
</record>
<record>
<IndoorOutdoor>Outdoor</IndoorOutdoor>
<event>DT</event>
<result>57.83</result>
<wind></wind>
<rank>6</rank>
<round>-22</round>
<roundstage>Final</roundstage>
<agegroup>Under 23</agegroup>
<competition_ID>12873645</competition_ID>
<compName></compName>
<date>2016-05-22</date>
<venue>Halle</venue>
<venueCountry>GER</venueCountry>
</record>
<record>
<IndoorOutdoor>Outdoor</IndoorOutdoor>
<event>DT</event>
<result>59.65</result>
<wind></wind>
<rank>1</rank>
<round></round>
<roundstage>Final</roundstage>
<agegroup></agegroup>
<competition_ID>12874858</competition_ID>
<compName>JJ-mót Ármanns 2016</compName>
<date>2016-05-25</date>
<venue>Reykjavik</venue>
<venueCountry>ISL</venueCountry>
</record>
<record>
<IndoorOutdoor>Outdoor</IndoorOutdoor>
<event>DT</event>
<result>60.72</result>
<wind></wind>
<rank>1</rank>
<round></round>
<roundstage>Final</roundstage>
<agegroup></agegroup>
<competition_ID>12874818</competition_ID>
<compName>Vormót UFA</compName>
<date>2016-05-29</date>
<venue>Akureyri</venue>
<venueCountry>ISL</venueCountry>
</record>
<record>
<IndoorOutdoor>Outdoor</IndoorOutdoor>
<event>DT</event>
<result>60.05</result>
<wind></wind>
<rank>1</rank>
<round></round>
<roundstage>Final</roundstage>
<agegroup></agegroup>
<competition_ID>12875251</competition_ID>
<compName>Championships of the Small States of Europe, Matthew Micallef St John Athletics Stadium</compName>
<date>2016-06-11</date>
<venue>Marsa</venue>
<venueCountry>MLT</venueCountry>
</record>
<record>
<IndoorOutdoor>Outdoor</IndoorOutdoor>
<event>DT</event>
<result>59.05</result>
<wind></wind>
<rank>7</rank>
<round></round>
<roundstage>Final</roundstage>
<agegroup></agegroup>
<competition_ID>12876040</competition_ID>
<compName></compName>
<date>2016-06-28</date>
<venue>Sollentuna</venue>
<venueCountry>SWE</venueCountry>
</record>
<record>
<IndoorOutdoor>Outdoor</IndoorOutdoor>
<event>DT</event>
<result>61.85</result>
<wind></wind>
<rank>3</rank>
<round></round>
<roundstage>Final</roundstage>
<agegroup></agegroup>
<competition_ID>12876442</competition_ID>
<compName>Leonardo Trainni Memorial</compName>
<date>2016-07-01</date>
<venue>Heerhugowaard</venue>
<venueCountry>NED</venueCountry>
</record>
<record>
<IndoorOutdoor>Outdoor</IndoorOutdoor>
<event>DT</event>
<result>60.43</result>
<wind></wind>
<rank>2</rank>
<round></round>
<roundstage>Final</roundstage>
<agegroup></agegroup>
<competition_ID>12876215</competition_ID>
<compName>Grote Prijs</compName>
<date>2016-07-03</date>
<venue>Lokeren</venue>
<venueCountry>BEL</venueCountry>
</record>
<record>
<IndoorOutdoor>Outdoor</IndoorOutdoor>
<event>DT</event>
<result>61.20</result>
<wind></wind>
<rank>22</rank>
<round>q</round>
<roundstage>Prelim</roundstage>
<agegroup></agegroup>
<competition_ID>12876245</competition_ID>
<compName></compName>
<date>2016-07-07</date>
<venue>Amsterdam</venue>
<venueCountry>NED</venueCountry>
</record>
<record>
<IndoorOutdoor>Outdoor</IndoorOutdoor>
<event>DT</event>
<result>56.83</result>
<wind></wind>
<rank>1</rank>
<round></round>
<roundstage>Final</roundstage>
<agegroup></agegroup>
<competition_ID>12877088</competition_ID>
<compName>90th National Championships</compName>
<date>2016-07-24</date>
<venue>Akureyri</venue>
<venueCountry>ISL</venueCountry>
</record>
<record>
<IndoorOutdoor>Outdoor</IndoorOutdoor>
<event>DT</event>
<result>59.12</result>
<wind></wind>
<rank>4</rank>
<round></round>
<roundstage>Final</roundstage>
<agegroup></agegroup>
<competition_ID>12877006</competition_ID>
<compName>Folksam Grand Prix</compName>
<date>2016-07-27</date>
<venue>Karlstad</venue>
<venueCountry>SWE</venueCountry>
</record>
<record>
<IndoorOutdoor>Outdoor</IndoorOutdoor>
<event>DT</event>
<result>57.80</result>
<wind></wind>
<rank>3</rank>
<round></round>
<roundstage>Final</roundstage>
<agegroup></agegroup>
<competition_ID>12877057</competition_ID>
<compName>Joensuu Games</compName>
<date>2016-07-30</date>
<venue>Joensuu</venue>
<venueCountry>FIN</venueCountry>
</record>
<record>
<IndoorOutdoor>Outdoor</IndoorOutdoor>
<event>DT</event>
<result>60.45</result>
<wind></wind>
<rank>21</rank>
<round>q</round>
<roundstage>Prelim</roundstage>
<agegroup></agegroup>
<competition_ID>12877460</competition_ID>
<compName>31st Olympic Games, Olympic Stadium</compName>
<date>2016-08-12</date>
<venue>Río de Janeiro</venue>
<venueCountry>BRA</venueCountry>
</record>
<record>
<IndoorOutdoor>Outdoor</IndoorOutdoor>
<event>DT</event>
<result>61.01</result>
<wind></wind>
<rank>1</rank>
<round>-22</round>
<roundstage>Final</roundstage>
<agegroup>Under 23</agegroup>
<competition_ID>12877532</competition_ID>
<compName></compName>
<date>2016-08-21</date>
<venue>Espoo</venue>
<venueCountry>FIN</venueCountry>
</record>
<record>
<IndoorOutdoor>Outdoor</IndoorOutdoor>
<event>SP</event>
<result>16.68</result>
<wind></wind>
<rank>1</rank>
<round>-22</round>
<roundstage>Final</roundstage>
<agegroup>Under 23</agegroup>
<competition_ID>12877731</competition_ID>
<compName>Meistaramót Íslands 15-22 ára</compName>
<date>2016-08-27</date>
<venue>Hafnarfjördur</venue>
<venueCountry>ISL</venueCountry>
</record>
<record>
<IndoorOutdoor>Outdoor</IndoorOutdoor>
<event>DT</event>
<result>59.93</result>
<wind></wind>
<rank>1</rank>
<round>-22</round>
<roundstage>Final</roundstage>
<agegroup>Under 23</agegroup>
<competition_ID>12877731</competition_ID>
<compName>Meistaramót Íslands 15-22 ára</compName>
<date>2016-08-28</date>
<venue>Hafnarfjördur</venue>
<venueCountry>ISL</venueCountry>
</record>
</athleteresulthistory>
</result>
</results>
