{
  "birthplace": null, 
  "weight": "64", 
  "firstname": "Mekonnen", 
  "club": "St.George", 
  "lastname": "Gebremedhin", 
  "results": [
    {
      "competition_ID": "8218801", 
      "compName": null, 
      "roundstage": "Final", 
      "venue": "Kampala", 
      "IndoorOutdoor": "Outdoor", 
      "agegroup": "Under 20", 
      "venueCountry": "UGA", 
      "rank": "4", 
      "event": "800", 
      "result": "1:50.6h", 
      "date": "2004-05-29", 
      "round": "-19", 
      "wind": null
    }, 
    {
      "competition_ID": "8218801", 
      "compName": null, 
      "roundstage": "Final", 
      "venue": "Kampala", 
      "IndoorOutdoor": "Outdoor", 
      "agegroup": "Under 20", 
      "venueCountry": "UGA", 
      "rank": "6", 
      "event": "1500", 
      "result": "3:47.1h", 
      "date": "2004-05-30", 
      "round": "-19", 
      "wind": null
    }, 
    {
      "competition_ID": "9243306", 
      "compName": null, 
      "roundstage": "Final", 
      "venue": "Khartoum", 
      "IndoorOutdoor": "Outdoor", 
      "agegroup": null, 
      "venueCountry": "SUD", 
      "rank": "1", 
      "event": "800", 
      "result": "1:47.8h", 
      "date": "2006-05-08", 
      "round": null, 
      "wind": null
    }, 
    {
      "competition_ID": "9160694", 
      "compName": null, 
      "roundstage": "Final", 
      "venue": "Gav\u00c3\u00a0", 
      "IndoorOutdoor": "Outdoor", 
      "agegroup": null, 
      "venueCountry": "ESP", 
      "rank": "1", 
      "event": "1500", 
      "result": "3:41.53", 
      "date": "2006-06-04", 
      "round": null, 
      "wind": null
    }, 
    {
      "competition_ID": "9166086", 
      "compName": null, 
      "roundstage": "Final", 
      "venue": "Avil\u00c3\u00a9s", 
      "IndoorOutdoor": "Outdoor", 
      "agegroup": null, 
      "venueCountry": "ESP", 
      "rank": "1", 
      "event": "1500", 
      "result": "3:41.16", 
      "date": "2006-06-10", 
      "round": null, 
      "wind": null
    }, 
    {
      "competition_ID": "9184108", 
      "compName": null, 
      "roundstage": "Final", 
      "venue": "Barakaldo", 
      "IndoorOutdoor": "Outdoor", 
      "agegroup": null, 
      "venueCountry": "ESP", 
      "rank": "2", 
      "event": "1500", 
      "result": "3:41.00", 
      "date": "2006-06-24", 
      "round": null, 
      "wind": null
    }, 
    {
      "competition_ID": "9202426", 
      "compName": null, 
      "roundstage": "Final", 
      "venue": "C\u00c3\u00a1ceres", 
      "IndoorOutdoor": "Outdoor", 
      "agegroup": null, 
      "venueCountry": "ESP", 
      "rank": "1", 
      "event": "800", 
      "result": "1:48.89", 
      "date": "2006-06-28", 
      "round": null, 
      "wind": null
    }, 
    {
      "competition_ID": "9204034", 
      "compName": null, 
      "roundstage": "Final", 
      "venue": "Bilbao", 
      "IndoorOutdoor": "Outdoor", 
      "agegroup": null, 
      "venueCountry": "ESP", 
      "rank": "2", 
      "event": "800", 
      "result": "1:48.30", 
      "date": "2006-07-01", 
      "round": null, 
      "wind": null
    }, 
    {
      "competition_ID": "9204575", 
      "compName": null, 
      "roundstage": "Final", 
      "venue": "La Laguna", 
      "IndoorOutdoor": "Outdoor", 
      "agegroup": null, 
      "venueCountry": "ESP", 
      "rank": "3", 
      "event": "800", 
      "result": "1:49.09", 
      "date": "2006-07-08", 
      "round": null, 
      "wind": null
    }, 
    {
      "competition_ID": "9238748", 
      "compName": null, 
      "roundstage": "Prelim", 
      "venue": "Beijing", 
      "IndoorOutdoor": "Outdoor", 
      "agegroup": null, 
      "venueCountry": "CHN", 
      "rank": "4", 
      "event": "800", 
      "result": "1:49.73", 
      "date": "2006-08-15", 
      "round": "h6-19", 
      "wind": null
    }, 
    {
      "competition_ID": "9238748", 
      "compName": null, 
      "roundstage": "Prelim", 
      "venue": "Beijing", 
      "IndoorOutdoor": "Outdoor", 
      "agegroup": null, 
      "venueCountry": "CHN", 
      "rank": "7", 
      "event": "800", 
      "result": "1:50.47", 
      "date": "2006-08-16", 
      "round": "s2-19", 
      "wind": null
    }, 
    {
      "competition_ID": "11542064", 
      "compName": null, 
      "roundstage": "Final", 
      "venue": "Addis Ababa", 
      "IndoorOutdoor": "Outdoor", 
      "agegroup": null, 
      "venueCountry": "ETH", 
      "rank": "5", 
      "event": "800", 
      "result": "1:48.8h", 
      "date": "2007-05-27", 
      "round": null, 
      "wind": null
    }, 
    {
      "competition_ID": "10239214", 
      "compName": null, 
      "roundstage": "Final", 
      "venue": "Bilbao", 
      "IndoorOutdoor": "Outdoor", 
      "agegroup": null, 
      "venueCountry": "ESP", 
      "rank": "2", 
      "event": "1500", 
      "result": "3:38.11", 
      "date": "2007-06-23", 
      "round": null, 
      "wind": null
    }, 
    {
      "competition_ID": "10279491", 
      "compName": null, 
      "roundstage": "Final", 
      "venue": "Alcal\u00c3\u00a1 de Henares", 
      "IndoorOutdoor": "Outdoor", 
      "agegroup": null, 
      "venueCountry": "ESP", 
      "rank": "1", 
      "event": "1500", 
      "result": "3:37.41", 
      "date": "2007-07-07", 
      "round": null, 
      "wind": null
    }, 
    {
      "competition_ID": "10564922", 
      "compName": null, 
      "roundstage": "Final", 
      "venue": "Barakaldo", 
      "IndoorOutdoor": "Outdoor", 
      "agegroup": null, 
      "venueCountry": "ESP", 
      "rank": "1", 
      "event": "1500", 
      "result": "3:36.48", 
      "date": "2007-07-14", 
      "round": null, 
      "wind": null
    }, 
    {
      "competition_ID": "10577577", 
      "compName": null, 
      "roundstage": "Final", 
      "venue": "Heusden", 
      "IndoorOutdoor": "Outdoor", 
      "agegroup": null, 
      "venueCountry": "BEL", 
      "rank": "4", 
      "event": "1500", 
      "result": "3:36.04", 
      "date": "2007-07-28", 
      "round": null, 
      "wind": null
    }, 
    {
      "competition_ID": "10626603", 
      "compName": null, 
      "roundstage": "Prelim", 
      "venue": "Osaka", 
      "IndoorOutdoor": "Outdoor", 
      "agegroup": null, 
      "venueCountry": "JPN", 
      "rank": "2", 
      "event": "1500", 
      "result": "3:41.43", 
      "date": "2007-08-25", 
      "round": "h3", 
      "wind": null
    }, 
    {
      "competition_ID": "10626603", 
      "compName": null, 
      "roundstage": "Prelim", 
      "venue": "Osaka", 
      "IndoorOutdoor": "Outdoor", 
      "agegroup": null, 
      "venueCountry": "JPN", 
      "rank": "7", 
      "event": "1500", 
      "result": "3:43.41", 
      "date": "2007-08-27", 
      "round": "s1", 
      "wind": null
    }, 
    {
      "competition_ID": "10658541", 
      "compName": null, 
      "roundstage": "Final", 
      "venue": "Huelva", 
      "IndoorOutdoor": "Outdoor", 
      "agegroup": null, 
      "venueCountry": "ESP", 
      "rank": "3", 
      "event": "1500", 
      "result": "3:37.89", 
      "date": "2007-09-13", 
      "round": null, 
      "wind": null
    }, 
    {
      "competition_ID": "11342392", 
      "compName": null, 
      "roundstage": "Final", 
      "venue": "Stuttgart", 
      "IndoorOutdoor": "Indoor", 
      "agegroup": null, 
      "venueCountry": "GER", 
      "rank": "2", 
      "event": "1500", 
      "result": "3:38.90", 
      "date": "2008-02-02", 
      "round": null, 
      "wind": null
    }, 
    {
      "competition_ID": "11356500", 
      "compName": null, 
      "roundstage": "Final", 
      "venue": "Valencia", 
      "IndoorOutdoor": "Indoor", 
      "agegroup": null, 
      "venueCountry": "ESP", 
      "rank": "1", 
      "event": "1500", 
      "result": "3:36.63", 
      "date": "2008-02-09", 
      "round": null, 
      "wind": null
    }, 
    {
      "competition_ID": "11465020", 
      "compName": null, 
      "roundstage": "Prelim", 
      "venue": "Valencia", 
      "IndoorOutdoor": "Indoor", 
      "agegroup": null, 
      "venueCountry": "ESP", 
      "rank": "1", 
      "event": "1500", 
      "result": "3:37.16", 
      "date": "2008-03-07", 
      "round": "h3", 
      "wind": null
    }, 
    {
      "competition_ID": "11465020", 
      "compName": null, 
      "roundstage": "Final", 
      "venue": "Valencia", 
      "IndoorOutdoor": "Indoor", 
      "agegroup": null, 
      "venueCountry": "ESP", 
      "rank": "6", 
      "event": "1500", 
      "result": "3:40.42", 
      "date": "2008-03-08", 
      "round": null, 
      "wind": null
    }, 
    {
      "competition_ID": "11729236", 
      "compName": null, 
      "roundstage": "Final", 
      "venue": "Zaragoza", 
      "IndoorOutdoor": "Outdoor", 
      "agegroup": null, 
      "venueCountry": "ESP", 
      "rank": "6", 
      "event": "1500", 
      "result": "3:38.85", 
      "date": "2008-05-31", 
      "round": null, 
      "wind": null
    }, 
    {
      "competition_ID": "11797050", 
      "compName": null, 
      "roundstage": "Final", 
      "venue": "Huelva", 
      "IndoorOutdoor": "Outdoor", 
      "agegroup": null, 
      "venueCountry": "ESP", 
      "rank": "9", 
      "event": "1500", 
      "result": "3:37.99", 
      "date": "2008-06-13", 
      "round": null, 
      "wind": null
    }, 
    {
      "competition_ID": "11847245", 
      "compName": null, 
      "roundstage": "Final", 
      "venue": "Jerez de la Frontera", 
      "IndoorOutdoor": "Outdoor", 
      "agegroup": null, 
      "venueCountry": "ESP", 
      "rank": "9", 
      "event": "1500", 
      "result": "3:36.88", 
      "date": "2008-06-24", 
      "round": null, 
      "wind": null
    }, 
    {
      "competition_ID": "11895969", 
      "compName": null, 
      "roundstage": "Final", 
      "venue": "Madrid", 
      "IndoorOutdoor": "Outdoor", 
      "agegroup": null, 
      "venueCountry": "ESP", 
      "rank": "5", 
      "event": "1500", 
      "result": "3:37.93", 
      "date": "2008-07-05", 
      "round": null, 
      "wind": null
    }, 
    {
      "competition_ID": "11960965", 
      "compName": null, 
      "roundstage": "Final", 
      "venue": "Heusden", 
      "IndoorOutdoor": "Outdoor", 
      "agegroup": null, 
      "venueCountry": "BEL", 
      "rank": "11", 
      "event": "1500", 
      "result": "3:39.28", 
      "date": "2008-07-20", 
      "round": null, 
      "wind": null
    }, 
    {
      "competition_ID": "12072346", 
      "compName": null, 
      "roundstage": "Final", 
      "venue": "Rieti", 
      "IndoorOutdoor": "Outdoor", 
      "agegroup": null, 
      "venueCountry": "ITA", 
      "rank": "3", 
      "event": "1500", 
      "result": "3:35.68", 
      "date": "2008-09-07", 
      "round": null, 
      "wind": null
    }, 
    {
      "competition_ID": "12585900", 
      "compName": null, 
      "roundstage": "Final", 
      "venue": "Gent", 
      "IndoorOutdoor": "Indoor", 
      "agegroup": null, 
      "venueCountry": "BEL", 
      "rank": "3", 
      "event": "1500", 
      "result": "3:36.46", 
      "date": "2009-02-08", 
      "round": null, 
      "wind": null
    }, 
    {
      "competition_ID": "12602576", 
      "compName": null, 
      "roundstage": "Final", 
      "venue": "Valencia", 
      "IndoorOutdoor": "Indoor", 
      "agegroup": null, 
      "venueCountry": "ESP", 
      "rank": "2", 
      "event": "1500", 
      "result": "3:35.71", 
      "date": "2009-02-14", 
      "round": null, 
      "wind": null
    }, 
    {
      "competition_ID": "12635909", 
      "compName": null, 
      "roundstage": "Final", 
      "venue": "Ath\u00c3\u00adna", 
      "IndoorOutdoor": "Indoor", 
      "agegroup": null, 
      "venueCountry": "GRE", 
      "rank": "4", 
      "event": "1500", 
      "result": "3:38.42", 
      "date": "2009-02-25", 
      "round": null, 
      "wind": null
    }, 
    {
      "competition_ID": "12787247", 
      "compName": null, 
      "roundstage": "Final", 
      "venue": "Addis Ababa", 
      "IndoorOutdoor": "Outdoor", 
      "agegroup": null, 
      "venueCountry": "ETH", 
      "rank": "8", 
      "event": "1500", 
      "result": "3:47.6h", 
      "date": "2009-05-03", 
      "round": null, 
      "wind": null
    }, 
    {
      "competition_ID": "12787683", 
      "compName": null, 
      "roundstage": "Final", 
      "venue": "Huelva", 
      "IndoorOutdoor": "Outdoor", 
      "agegroup": null, 
      "venueCountry": "ESP", 
      "rank": "2", 
      "event": "1500", 
      "result": "3:35.17", 
      "date": "2009-06-10", 
      "round": null, 
      "wind": null
    }, 
    {
      "competition_ID": "12787889", 
      "compName": null, 
      "roundstage": "Final", 
      "venue": "Casablanca", 
      "IndoorOutdoor": "Outdoor", 
      "agegroup": null, 
      "venueCountry": "MAR", 
      "rank": "3", 
      "event": "1500", 
      "result": "3:37.45", 
      "date": "2009-06-14", 
      "round": null, 
      "wind": null
    }, 
    {
      "competition_ID": "12788259", 
      "compName": null, 
      "roundstage": "Final", 
      "venue": "M\u00c3\u00a1laga", 
      "IndoorOutdoor": "Outdoor", 
      "agegroup": null, 
      "venueCountry": "ESP", 
      "rank": "2", 
      "event": "1500", 
      "result": "3:35.75", 
      "date": "2009-06-27", 
      "round": null, 
      "wind": null
    }, 
    {
      "competition_ID": "12788372", 
      "compName": null, 
      "roundstage": "Final", 
      "venue": "Oslo", 
      "IndoorOutdoor": "Outdoor", 
      "agegroup": null, 
      "venueCountry": "NOR", 
      "rank": "3", 
      "event": "1500", 
      "result": "3:34.49", 
      "date": "2009-07-03", 
      "round": null, 
      "wind": null
    }, 
    {
      "competition_ID": "12788372", 
      "compName": null, 
      "roundstage": "Final", 
      "venue": "Oslo", 
      "IndoorOutdoor": "Outdoor", 
      "agegroup": null, 
      "venueCountry": "NOR", 
      "rank": "4", 
      "event": "Mile", 
      "result": "3:50.74", 
      "date": "2009-07-03", 
      "round": null, 
      "wind": null
    }, 
    {
      "competition_ID": "12788705", 
      "compName": null, 
      "roundstage": "Final", 
      "venue": "Heusden", 
      "IndoorOutdoor": "Outdoor", 
      "agegroup": null, 
      "venueCountry": "BEL", 
      "rank": "6", 
      "event": "1500", 
      "result": "3:38.48", 
      "date": "2009-07-18", 
      "round": null, 
      "wind": null
    }, 
    {
      "competition_ID": "12789100", 
      "compName": null, 
      "roundstage": "Prelim", 
      "venue": "Berlin", 
      "IndoorOutdoor": "Outdoor", 
      "agegroup": null, 
      "venueCountry": "GER", 
      "rank": "7", 
      "event": "1500", 
      "result": "3:43.22", 
      "date": "2009-08-15", 
      "round": "h1", 
      "wind": null
    }, 
    {
      "competition_ID": "12792965", 
      "compName": null, 
      "roundstage": "Final", 
      "venue": "Karlsruhe", 
      "IndoorOutdoor": "Indoor", 
      "agegroup": null, 
      "venueCountry": "GER", 
      "rank": "2", 
      "event": "1500", 
      "result": "3:37.46", 
      "date": "2010-01-31", 
      "round": null, 
      "wind": null
    }, 
    {
      "competition_ID": "12793228", 
      "compName": null, 
      "roundstage": "Final", 
      "venue": "D\u00c3\u00bcsseldorf", 
      "IndoorOutdoor": "Indoor", 
      "agegroup": null, 
      "venueCountry": "GER", 
      "rank": "4", 
      "event": "1500", 
      "result": "3:38.36", 
      "date": "2010-02-03", 
      "round": null, 
      "wind": null
    }, 
    {
      "competition_ID": "12793709", 
      "compName": null, 
      "roundstage": "Final", 
      "venue": "Gent", 
      "IndoorOutdoor": "Indoor", 
      "agegroup": null, 
      "venueCountry": "BEL", 
      "rank": "4", 
      "event": "1500", 
      "result": "3:37.46", 
      "date": "2010-02-14", 
      "round": null, 
      "wind": null
    }, 
    {
      "competition_ID": "12794620", 
      "compName": null, 
      "roundstage": "Prelim", 
      "venue": "Doha", 
      "IndoorOutdoor": "Indoor", 
      "agegroup": null, 
      "venueCountry": "QAT", 
      "rank": "2", 
      "event": "1500", 
      "result": "3:38.90", 
      "date": "2010-03-12", 
      "round": "h3", 
      "wind": null
    }, 
    {
      "competition_ID": "12794620", 
      "compName": null, 
      "roundstage": "Final", 
      "venue": "Doha", 
      "IndoorOutdoor": "Indoor", 
      "agegroup": null, 
      "venueCountry": "QAT", 
      "rank": "4", 
      "event": "1500", 
      "result": "3:42.42", 
      "date": "2010-03-13", 
      "round": null, 
      "wind": null
    }, 
    {
      "competition_ID": "12797353", 
      "compName": null, 
      "roundstage": "Final", 
      "venue": "Shanghai", 
      "IndoorOutdoor": "Outdoor", 
      "agegroup": null, 
      "venueCountry": "CHN", 
      "rank": "3", 
      "event": "1500", 
      "result": "3:33.35", 
      "date": "2010-05-23", 
      "round": null, 
      "wind": null
    }, 
    {
      "competition_ID": "12797898", 
      "compName": null, 
      "roundstage": "Final", 
      "venue": "Oslo", 
      "IndoorOutdoor": "Outdoor", 
      "agegroup": null, 
      "venueCountry": "NOR", 
      "rank": "1", 
      "event": "1500", 
      "result": "3:35.00", 
      "date": "2010-06-04", 
      "round": null, 
      "wind": null
    }, 
    {
      "competition_ID": "12797898", 
      "compName": null, 
      "roundstage": "Final", 
      "venue": "Oslo", 
      "IndoorOutdoor": "Outdoor", 
      "agegroup": null, 
      "venueCountry": "NOR", 
      "rank": "2", 
      "event": "Mile", 
      "result": "3:49.83", 
      "date": "2010-06-04", 
      "round": null, 
      "wind": null
    }, 
    {
      "competition_ID": "12798024", 
      "compName": null, 
      "roundstage": "Final", 
      "venue": "Roma", 
      "IndoorOutdoor": "Outdoor", 
      "agegroup": null, 
      "venueCountry": "ITA", 
      "rank": "10", 
      "event": "1500", 
      "result": "3:35.40", 
      "date": "2010-06-10", 
      "round": null, 
      "wind": null
    }, 
    {
      "competition_ID": "12799268", 
      "compName": null, 
      "roundstage": "Final", 
      "venue": "Eugene OR", 
      "IndoorOutdoor": "Outdoor", 
      "agegroup": null, 
      "venueCountry": "USA", 
      "rank": "3", 
      "event": "Mile", 
      "result": "3:50.68", 
      "date": "2010-07-03", 
      "round": null, 
      "wind": null
    }, 
    {
      "competition_ID": "12799406", 
      "compName": null, 
      "roundstage": "Final", 
      "venue": "Gateshead", 
      "IndoorOutdoor": "Outdoor", 
      "agegroup": null, 
      "venueCountry": "GBR", 
      "rank": "4", 
      "event": "1500", 
      "result": "3:33.96", 
      "date": "2010-07-10", 
      "round": null, 
      "wind": null
    }, 
    {
      "competition_ID": "12800125", 
      "compName": null, 
      "roundstage": "Prelim", 
      "venue": "Nairobi", 
      "IndoorOutdoor": "Outdoor", 
      "agegroup": null, 
      "venueCountry": "KEN", 
      "rank": "1", 
      "event": "1500", 
      "result": "3:44.24", 
      "date": "2010-07-31", 
      "round": "h2", 
      "wind": null
    }, 
    {
      "competition_ID": "12800125", 
      "compName": null, 
      "roundstage": "Final", 
      "venue": "Nairobi", 
      "IndoorOutdoor": "Outdoor", 
      "agegroup": null, 
      "venueCountry": "KEN", 
      "rank": "3", 
      "event": "1500", 
      "result": "3:36.65", 
      "date": "2010-08-01", 
      "round": null, 
      "wind": null
    }, 
    {
      "competition_ID": "12800367", 
      "compName": null, 
      "roundstage": "Final", 
      "venue": "London", 
      "IndoorOutdoor": "Outdoor", 
      "agegroup": null, 
      "venueCountry": "GBR", 
      "rank": "2", 
      "event": "1500", 
      "result": "3:35.74", 
      "date": "2010-08-14", 
      "round": null, 
      "wind": null
    }, 
    {
      "competition_ID": "12800367", 
      "compName": null, 
      "roundstage": "Final", 
      "venue": "London", 
      "IndoorOutdoor": "Outdoor", 
      "agegroup": null, 
      "venueCountry": "GBR", 
      "rank": "2", 
      "event": "Mile", 
      "result": "3:50.35", 
      "date": "2010-08-14", 
      "round": null, 
      "wind": null
    }, 
    {
      "competition_ID": "12800712", 
      "compName": "ISTAF 2010, Olympiastadion", 
      "roundstage": "Final", 
      "venue": "Berlin", 
      "IndoorOutdoor": "Outdoor", 
      "agegroup": null, 
      "venueCountry": "GER", 
      "rank": "2", 
      "event": "1500", 
      "result": "3:31.57", 
      "date": "2010-08-22", 
      "round": null, 
      "wind": null
    }, 
    {
      "competition_ID": "12800757", 
      "compName": "Belgacom Memorial Van Damme", 
      "roundstage": "Final", 
      "venue": "Bruxelles", 
      "IndoorOutdoor": "Outdoor", 
      "agegroup": null, 
      "venueCountry": "BEL", 
      "rank": "4", 
      "event": "1500", 
      "result": "3:33.40", 
      "date": "2010-08-27", 
      "round": null, 
      "wind": null
    }, 
    {
      "competition_ID": "12801161", 
      "compName": null, 
      "roundstage": "Final", 
      "venue": "Split", 
      "IndoorOutdoor": "Outdoor", 
      "agegroup": null, 
      "venueCountry": "CRO", 
      "rank": "2", 
      "event": "1500", 
      "result": "3:35.70", 
      "date": "2010-09-04", 
      "round": null, 
      "wind": null
    }, 
    {
      "competition_ID": "12806076", 
      "compName": "Sparkassen Cup, Schleyer-Halle", 
      "roundstage": "Final", 
      "venue": "Stuttgart", 
      "IndoorOutdoor": "Indoor", 
      "agegroup": null, 
      "venueCountry": "GER", 
      "rank": "5", 
      "event": "1500", 
      "result": "3:38.26", 
      "date": "2011-02-05", 
      "round": null, 
      "wind": null
    }, 
    {
      "competition_ID": "12806460", 
      "compName": "PSD Bank Meeting, Arena-Sportpark", 
      "roundstage": "Final", 
      "venue": "D\u00c3\u00bcsseldorf", 
      "IndoorOutdoor": "Indoor", 
      "agegroup": null, 
      "venueCountry": "GER", 
      "rank": "7", 
      "event": "1500", 
      "result": "3:39.38", 
      "date": "2011-02-11", 
      "round": null, 
      "wind": null
    }, 
    {
      "competition_ID": "12809192", 
      "compName": "Samsung Diamond League", 
      "roundstage": "Final", 
      "venue": "Doha", 
      "IndoorOutdoor": "Outdoor", 
      "agegroup": null, 
      "venueCountry": "QAT", 
      "rank": "3", 
      "event": "1500", 
      "result": "3:32.28", 
      "date": "2011-05-06", 
      "round": null, 
      "wind": null
    }, 
    {
      "competition_ID": "12809718", 
      "compName": null, 
      "roundstage": "Final", 
      "venue": "Shanghai", 
      "IndoorOutdoor": "Outdoor", 
      "agegroup": null, 
      "venueCountry": "CHN", 
      "rank": "3", 
      "event": "1500", 
      "result": "3:32.36", 
      "date": "2011-05-15", 
      "round": null, 
      "wind": null
    }, 
    {
      "competition_ID": "12810676", 
      "compName": null, 
      "roundstage": "Final", 
      "venue": "Hengelo", 
      "IndoorOutdoor": "Outdoor", 
      "agegroup": null, 
      "venueCountry": "NED", 
      "rank": "3", 
      "event": "1500", 
      "result": "3:31.90", 
      "date": "2011-05-29", 
      "round": null, 
      "wind": null
    }, 
    {
      "competition_ID": "12814109", 
      "compName": null, 
      "roundstage": "Final", 
      "venue": "Eugene OR", 
      "IndoorOutdoor": "Outdoor", 
      "agegroup": null, 
      "venueCountry": "USA", 
      "rank": "2", 
      "event": "1500", 
      "result": "3:34.62", 
      "date": "2011-06-04", 
      "round": null, 
      "wind": null
    }, 
    {
      "competition_ID": "12811033", 
      "compName": null, 
      "roundstage": "Final", 
      "venue": "Eugene OR", 
      "IndoorOutdoor": "Outdoor", 
      "agegroup": null, 
      "venueCountry": "USA", 
      "rank": "4", 
      "event": "Mile", 
      "result": "3:49.70", 
      "date": "2011-06-04", 
      "round": null, 
      "wind": null
    }, 
    {
      "competition_ID": "12811341", 
      "compName": null, 
      "roundstage": "Final", 
      "venue": "Oslo", 
      "IndoorOutdoor": "Outdoor", 
      "agegroup": null, 
      "venueCountry": "NOR", 
      "rank": "1", 
      "event": "1500", 
      "result": "3:36.08", 
      "date": "2011-06-09", 
      "round": null, 
      "wind": null
    }, 
    {
      "competition_ID": "12811341", 
      "compName": "ExxonMobil Bislett Games, Samsung Diamond League, Bislett Stadium", 
      "roundstage": "Final", 
      "venue": "Oslo", 
      "IndoorOutdoor": "Outdoor", 
      "agegroup": null, 
      "venueCountry": "NOR", 
      "rank": "3", 
      "event": "Mile", 
      "result": "3:51.30", 
      "date": "2011-06-09", 
      "round": null, 
      "wind": null
    }, 
    {
      "competition_ID": "12812869", 
      "compName": "Meeting Areva, Samsung Diamond League, Stade-de-France", 
      "roundstage": "Final", 
      "venue": "Saint-Denis", 
      "IndoorOutdoor": "Outdoor", 
      "agegroup": null, 
      "venueCountry": "FRA", 
      "rank": "12", 
      "event": "1500", 
      "result": "3:34.86", 
      "date": "2011-07-08", 
      "round": null, 
      "wind": null
    }, 
    {
      "competition_ID": "12814135", 
      "compName": null, 
      "roundstage": "Prelim", 
      "venue": "Daegu", 
      "IndoorOutdoor": "Outdoor", 
      "agegroup": null, 
      "venueCountry": "KOR", 
      "rank": "2", 
      "event": "1500", 
      "result": "3:41.28", 
      "date": "2011-08-30", 
      "round": "h2", 
      "wind": null
    }, 
    {
      "competition_ID": "12814135", 
      "compName": null, 
      "roundstage": "Prelim", 
      "venue": "Daegu", 
      "IndoorOutdoor": "Outdoor", 
      "agegroup": null, 
      "venueCountry": "KOR", 
      "rank": "2", 
      "event": "1500", 
      "result": "3:46.71", 
      "date": "2011-09-01", 
      "round": "s1", 
      "wind": null
    }, 
    {
      "competition_ID": "12814135", 
      "compName": null, 
      "roundstage": "Final", 
      "venue": "Daegu", 
      "IndoorOutdoor": "Outdoor", 
      "agegroup": null, 
      "venueCountry": "KOR", 
      "rank": "7", 
      "event": "1500", 
      "result": "3:36.81", 
      "date": "2011-09-03", 
      "round": null, 
      "wind": null
    }, 
    {
      "competition_ID": "12814625", 
      "compName": null, 
      "roundstage": "Final", 
      "venue": "Z\u00c3\u00bcrich", 
      "IndoorOutdoor": "Outdoor", 
      "agegroup": null, 
      "venueCountry": "SUI", 
      "rank": "6", 
      "event": "1500", 
      "result": "3:34.75", 
      "date": "2011-09-08", 
      "round": null, 
      "wind": null
    }, 
    {
      "competition_ID": "12814710", 
      "compName": null, 
      "roundstage": "Final", 
      "venue": "Berlin", 
      "IndoorOutdoor": "Outdoor", 
      "agegroup": null, 
      "venueCountry": "GER", 
      "rank": "6", 
      "event": "1500", 
      "result": "3:32.71", 
      "date": "2011-09-11", 
      "round": null, 
      "wind": null
    }, 
    {
      "competition_ID": "12814743", 
      "compName": "Notturna di Milano", 
      "roundstage": "Final", 
      "venue": "Milano", 
      "IndoorOutdoor": "Outdoor", 
      "agegroup": null, 
      "venueCountry": "ITA", 
      "rank": "2", 
      "event": "3000", 
      "result": "7:41.42", 
      "date": "2011-09-18", 
      "round": null, 
      "wind": null
    }, 
    {
      "competition_ID": "12820237", 
      "compName": "7th PSD Bank Meeting, Arena-Sportpark", 
      "roundstage": "Final", 
      "venue": "D\u00c3\u00bcsseldorf", 
      "IndoorOutdoor": "Indoor", 
      "agegroup": null, 
      "venueCountry": "GER", 
      "rank": "6", 
      "event": "1500", 
      "result": "3:38.81", 
      "date": "2012-02-10", 
      "round": null, 
      "wind": null
    }, 
    {
      "competition_ID": "12820317", 
      "compName": null, 
      "roundstage": "Final", 
      "venue": "Karlsruhe", 
      "IndoorOutdoor": "Indoor", 
      "agegroup": null, 
      "venueCountry": "GER", 
      "rank": "3", 
      "event": "1500", 
      "result": "3:36.05", 
      "date": "2012-02-12", 
      "round": null, 
      "wind": null
    }, 
    {
      "competition_ID": "12820543", 
      "compName": "Aviva Grand Prix, National Indoor Arena", 
      "roundstage": "Final", 
      "venue": "Birmingham", 
      "IndoorOutdoor": "Indoor", 
      "agegroup": null, 
      "venueCountry": "GBR", 
      "rank": "3", 
      "event": "1500", 
      "result": "3:34.89", 
      "date": "2012-02-18", 
      "round": null, 
      "wind": null
    }, 
    {
      "competition_ID": "12820757", 
      "compName": "XL Galan, Ericsson Globe", 
      "roundstage": "Final", 
      "venue": "Stockholm", 
      "IndoorOutdoor": "Indoor", 
      "agegroup": null, 
      "venueCountry": "SWE", 
      "rank": "10", 
      "event": "3000", 
      "result": "7:46.89", 
      "date": "2012-02-23", 
      "round": null, 
      "wind": null
    }, 
    {
      "competition_ID": "12821019", 
      "compName": null, 
      "roundstage": "Prelim", 
      "venue": "Istanbul", 
      "IndoorOutdoor": "Indoor", 
      "agegroup": null, 
      "venueCountry": "TUR", 
      "rank": "2", 
      "event": "1500", 
      "result": "3:39.16", 
      "date": "2012-03-09", 
      "round": "h2", 
      "wind": null
    }, 
    {
      "competition_ID": "12821019", 
      "compName": "Milo Central Athletics  Championship", 
      "roundstage": "Final", 
      "venue": "Istanbul", 
      "IndoorOutdoor": "Indoor", 
      "agegroup": null, 
      "venueCountry": "TUR", 
      "rank": "3", 
      "event": "1500", 
      "result": "3:45.90", 
      "date": "2012-03-10", 
      "round": null, 
      "wind": null
    }, 
    {
      "competition_ID": "12822541", 
      "compName": "Golden Grand Prix Japan", 
      "roundstage": "Final", 
      "venue": "Kawasaki", 
      "IndoorOutdoor": "Outdoor", 
      "agegroup": null, 
      "venueCountry": "JPN", 
      "rank": "8", 
      "event": "3000S", 
      "result": "8:59.06", 
      "date": "2012-05-06", 
      "round": null, 
      "wind": null
    }, 
    {
      "competition_ID": "12822732", 
      "compName": "Doha 2012, Samsung Diamond League, Qatar Sports Club", 
      "roundstage": "Final", 
      "venue": "Doha", 
      "IndoorOutdoor": "Outdoor", 
      "agegroup": null, 
      "venueCountry": "QAT", 
      "rank": "7", 
      "event": "1500", 
      "result": "3:33.38", 
      "date": "2012-05-11", 
      "round": null, 
      "wind": null
    }, 
    {
      "competition_ID": "12823164", 
      "compName": "Fanny Blankers-Koen Games", 
      "roundstage": "Final", 
      "venue": "Hengelo", 
      "IndoorOutdoor": "Outdoor", 
      "agegroup": null, 
      "venueCountry": "NED", 
      "rank": "3", 
      "event": "1500", 
      "result": "3:31.45", 
      "date": "2012-05-27", 
      "round": null, 
      "wind": null
    }, 
    {
      "competition_ID": "12823456", 
      "compName": null, 
      "roundstage": "Final", 
      "venue": "Eugene OR", 
      "IndoorOutdoor": "Outdoor", 
      "agegroup": null, 
      "venueCountry": "USA", 
      "rank": "6", 
      "event": "1500", 
      "result": "3:35.72", 
      "date": "2012-06-02", 
      "round": null, 
      "wind": null
    }, 
    {
      "competition_ID": "12823456", 
      "compName": null, 
      "roundstage": "Final", 
      "venue": "Eugene OR", 
      "IndoorOutdoor": "Outdoor", 
      "agegroup": null, 
      "venueCountry": "USA", 
      "rank": "2", 
      "event": "Mile", 
      "result": "3:50.17", 
      "date": "2012-06-02", 
      "round": null, 
      "wind": null
    }, 
    {
      "competition_ID": "12823623", 
      "compName": null, 
      "roundstage": "Final", 
      "venue": "Oslo", 
      "IndoorOutdoor": "Outdoor", 
      "agegroup": null, 
      "venueCountry": "NOR", 
      "rank": "4", 
      "event": "1500", 
      "result": "3:34.82", 
      "date": "2012-06-07", 
      "round": null, 
      "wind": null
    }, 
    {
      "competition_ID": "12823623", 
      "compName": "Aviva All Ireland Schools\u00e2\u0080\u0099 Track and Field Championships", 
      "roundstage": "Final", 
      "venue": "Oslo", 
      "IndoorOutdoor": "Outdoor", 
      "agegroup": null, 
      "venueCountry": "NOR", 
      "rank": "3", 
      "event": "Mile", 
      "result": "3:50.02", 
      "date": "2012-06-07", 
      "round": null, 
      "wind": null
    }, 
    {
      "competition_ID": "12824477", 
      "compName": "30th Meeting de Atletismo Madrid", 
      "roundstage": "Final", 
      "venue": "Madrid", 
      "IndoorOutdoor": "Outdoor", 
      "agegroup": null, 
      "venueCountry": "ESP", 
      "rank": "7", 
      "event": "800", 
      "result": "1:46.63", 
      "date": "2012-07-07", 
      "round": null, 
      "wind": null
    }, 
    {
      "competition_ID": "12825110", 
      "compName": null, 
      "roundstage": "Prelim", 
      "venue": "London", 
      "IndoorOutdoor": "Outdoor", 
      "agegroup": null, 
      "venueCountry": "GBR", 
      "rank": "2", 
      "event": "1500", 
      "result": "3:36.56", 
      "date": "2012-08-03", 
      "round": "h1", 
      "wind": null
    }, 
    {
      "competition_ID": "12825110", 
      "compName": null, 
      "roundstage": "Prelim", 
      "venue": "London", 
      "IndoorOutdoor": "Outdoor", 
      "agegroup": null, 
      "venueCountry": "GBR", 
      "rank": "3", 
      "event": "1500", 
      "result": "3:42.93", 
      "date": "2012-08-05", 
      "round": "s1", 
      "wind": null
    }, 
    {
      "competition_ID": "12825110", 
      "compName": null, 
      "roundstage": "Final", 
      "venue": "London", 
      "IndoorOutdoor": "Outdoor", 
      "agegroup": null, 
      "venueCountry": "GBR", 
      "rank": "6", 
      "event": "1500", 
      "result": "3:35.44", 
      "date": "2012-08-07", 
      "round": null, 
      "wind": null
    }, 
    {
      "competition_ID": "12825371", 
      "compName": "Athletissima, Samsung Diamond League", 
      "roundstage": "Final", 
      "venue": "Lausanne", 
      "IndoorOutdoor": "Outdoor", 
      "agegroup": null, 
      "venueCountry": "SUI", 
      "rank": "2", 
      "event": "1500", 
      "result": "3:31.86", 
      "date": "2012-08-23", 
      "round": null, 
      "wind": null
    }, 
    {
      "competition_ID": "12825385", 
      "compName": "Aviva Grand Prix, Samsung Diamond League, Alexander Stadium", 
      "roundstage": "Final", 
      "venue": "Birmingham", 
      "IndoorOutdoor": "Outdoor", 
      "agegroup": null, 
      "venueCountry": "GBR", 
      "rank": "1", 
      "event": "1500", 
      "result": "3:34.80", 
      "date": "2012-08-26", 
      "round": null, 
      "wind": null
    }, 
    {
      "competition_ID": "12825587", 
      "compName": "Van Damme Memorial, Samsung Diamond League, King Baudoin Stadium", 
      "roundstage": "Final", 
      "venue": "Bruxelles", 
      "IndoorOutdoor": "Outdoor", 
      "agegroup": null, 
      "venueCountry": "BEL", 
      "rank": "2", 
      "event": "1500", 
      "result": "3:32.10", 
      "date": "2012-09-07", 
      "round": null, 
      "wind": null
    }, 
    {
      "competition_ID": "12826141", 
      "compName": "Four Miles of Groningen", 
      "roundstage": "Final", 
      "venue": "Groningen", 
      "IndoorOutdoor": "Outdoor", 
      "agegroup": null, 
      "venueCountry": "NED", 
      "rank": "7", 
      "event": "4M", 
      "result": "17:51", 
      "date": "2012-10-14", 
      "round": null, 
      "wind": null
    }, 
    {
      "competition_ID": "12838818", 
      "compName": null, 
      "roundstage": "Final", 
      "venue": "Moskva", 
      "IndoorOutdoor": "Indoor", 
      "agegroup": null, 
      "venueCountry": "RUS", 
      "rank": "7", 
      "event": "1500", 
      "result": "3:39.74", 
      "date": "2013-02-03", 
      "round": null, 
      "wind": null
    }, 
    {
      "competition_ID": "12839046", 
      "compName": "Flanders Indoor", 
      "roundstage": "Final", 
      "venue": "Gent", 
      "IndoorOutdoor": "Indoor", 
      "agegroup": null, 
      "venueCountry": "BEL", 
      "rank": "5", 
      "event": "3000", 
      "result": "7:41.59", 
      "date": "2013-02-10", 
      "round": null, 
      "wind": null
    }, 
    {
      "competition_ID": "12839169", 
      "compName": "British Athletics Grand Prix, National Indoor Arena", 
      "roundstage": "Final", 
      "venue": "Birmingham", 
      "IndoorOutdoor": "Indoor", 
      "agegroup": null, 
      "venueCountry": "GBR", 
      "rank": "7", 
      "event": "1500", 
      "result": "3:39.30", 
      "date": "2013-02-16", 
      "round": null, 
      "wind": null
    }, 
    {
      "competition_ID": "12841311", 
      "compName": "IAAF Diamond League Meeting, Qatar Sports Club", 
      "roundstage": "Final", 
      "venue": "Doha", 
      "IndoorOutdoor": "Outdoor", 
      "agegroup": null, 
      "venueCountry": "QAT", 
      "rank": "9", 
      "event": "1500", 
      "result": "3:34.49", 
      "date": "2013-05-10", 
      "round": null, 
      "wind": null
    }, 
    {
      "competition_ID": "12841582", 
      "compName": "Shanghai Golden Grand Prix, IAAF Diamond League Meeting, Shanghai Stadium", 
      "roundstage": "Final", 
      "venue": "Shanghai", 
      "IndoorOutdoor": "Outdoor", 
      "agegroup": null, 
      "venueCountry": "CHN", 
      "rank": "2", 
      "event": "1500", 
      "result": "3:32.43", 
      "date": "2013-05-18", 
      "round": null, 
      "wind": null
    }, 
    {
      "competition_ID": "12841904", 
      "compName": null, 
      "roundstage": "Final", 
      "venue": "Eugene OR", 
      "IndoorOutdoor": "Outdoor", 
      "agegroup": null, 
      "venueCountry": "USA", 
      "rank": "12", 
      "event": "1500", 
      "result": "3:37.99", 
      "date": "2013-06-01", 
      "round": null, 
      "wind": null
    }, 
    {
      "competition_ID": "12841904", 
      "compName": "Prefontaine Classic, IAAF Diamond League, Hayward Field", 
      "roundstage": "Final", 
      "venue": "Eugene OR", 
      "IndoorOutdoor": "Outdoor", 
      "agegroup": null, 
      "venueCountry": "USA", 
      "rank": "12", 
      "event": "Mile", 
      "result": "3:54.04", 
      "date": "2013-06-01", 
      "round": null, 
      "wind": null
    }, 
    {
      "competition_ID": "12842129", 
      "compName": "Fanny Blankers Koen Games, Fanny Blankers Koen Stadium", 
      "roundstage": "Final", 
      "venue": "Hengelo", 
      "IndoorOutdoor": "Outdoor", 
      "agegroup": null, 
      "venueCountry": "NED", 
      "rank": "3", 
      "event": "1500", 
      "result": "3:36.85", 
      "date": "2013-06-08", 
      "round": null, 
      "wind": null
    }, 
    {
      "competition_ID": "12842739", 
      "compName": "Bislett Games, IAAF Diamond League, Bislett Stadium", 
      "roundstage": "Final", 
      "venue": "Oslo", 
      "IndoorOutdoor": "Outdoor", 
      "agegroup": null, 
      "venueCountry": "NOR", 
      "rank": null, 
      "event": "Mile", 
      "result": null, 
      "date": "2013-06-13", 
      "round": null, 
      "wind": null
    }, 
    {
      "competition_ID": "12843453", 
      "compName": "Meeting Areva, IAAF Diamond League, Stade-de-France", 
      "roundstage": "Final", 
      "venue": "Saint-Denis", 
      "IndoorOutdoor": "Outdoor", 
      "agegroup": null, 
      "venueCountry": "FRA", 
      "rank": "14", 
      "event": "1500", 
      "result": "3:37.36", 
      "date": "2013-07-06", 
      "round": null, 
      "wind": null
    }, 
    {
      "competition_ID": "12844203", 
      "compName": null, 
      "roundstage": "Prelim", 
      "venue": "Moskva", 
      "IndoorOutdoor": "Outdoor", 
      "agegroup": null, 
      "venueCountry": "RUS", 
      "rank": "3", 
      "event": "1500", 
      "result": "3:38.55", 
      "date": "2013-08-14", 
      "round": "h3", 
      "wind": null
    }, 
    {
      "competition_ID": "12844203", 
      "compName": null, 
      "roundstage": "Prelim", 
      "venue": "Moskva", 
      "IndoorOutdoor": "Outdoor", 
      "agegroup": null, 
      "venueCountry": "RUS", 
      "rank": "3", 
      "event": "1500", 
      "result": "3:43.54", 
      "date": "2013-08-16", 
      "round": "s1", 
      "wind": null
    }, 
    {
      "competition_ID": "12844203", 
      "compName": null, 
      "roundstage": "Final", 
      "venue": "Moskva", 
      "IndoorOutdoor": "Outdoor", 
      "agegroup": null, 
      "venueCountry": "RUS", 
      "rank": "7", 
      "event": "1500", 
      "result": "3:37.21", 
      "date": "2013-08-18", 
      "round": null, 
      "wind": null
    }, 
    {
      "competition_ID": "12844295", 
      "compName": "DN Galan, IAAF Diamond League, Olympic Stadium", 
      "roundstage": "Final", 
      "venue": "Stockholm", 
      "IndoorOutdoor": "Outdoor", 
      "agegroup": null, 
      "venueCountry": "SWE", 
      "rank": "9", 
      "event": "1500", 
      "result": "3:38.38", 
      "date": "2013-08-22", 
      "round": null, 
      "wind": null
    }, 
    {
      "competition_ID": "12844360", 
      "compName": "Weltklasse, IAAF Diamond League, Letzigrund Stadium (Shot put Hauptbahnhof, indoors)", 
      "roundstage": "Final", 
      "venue": "Z\u00c3\u00bcrich", 
      "IndoorOutdoor": "Outdoor", 
      "agegroup": null, 
      "venueCountry": "SUI", 
      "rank": "5", 
      "event": "1500", 
      "result": "3:33.64", 
      "date": "2013-08-29", 
      "round": null, 
      "wind": null
    }, 
    {
      "competition_ID": "12844419", 
      "compName": "63rd Memorial Boris Han\u00c5\u00beekovi\u00c4\u0087, \u00c5\u00a0portski park Mladost, IAAF World Challenge", 
      "roundstage": "Final", 
      "venue": "Zagreb", 
      "IndoorOutdoor": "Outdoor", 
      "agegroup": null, 
      "venueCountry": "CRO", 
      "rank": null, 
      "event": "3000", 
      "result": null, 
      "date": "2013-09-03", 
      "round": null, 
      "wind": null
    }, 
    {
      "competition_ID": "12845038", 
      "compName": "Four Miles of Groningen", 
      "roundstage": "Final", 
      "venue": "Groningen", 
      "IndoorOutdoor": "Outdoor", 
      "agegroup": null, 
      "venueCountry": "NED", 
      "rank": "5", 
      "event": "4M", 
      "result": "17:48", 
      "date": "2013-10-13", 
      "round": null, 
      "wind": null
    }, 
    {
      "competition_ID": "12847494", 
      "compName": "Indoor Meeting Weltklasse Karlsruhe, Europahalle", 
      "roundstage": "Final", 
      "venue": "Karlsruhe", 
      "IndoorOutdoor": "Indoor", 
      "agegroup": null, 
      "venueCountry": "GER", 
      "rank": "2", 
      "event": "1500", 
      "result": "3:37.42", 
      "date": "2014-02-01", 
      "round": null, 
      "wind": null
    }, 
    {
      "competition_ID": "12847972", 
      "compName": "Sainsbury's Indoor Grand Prix, National Indoor Arena", 
      "roundstage": "Final", 
      "venue": "Birmingham", 
      "IndoorOutdoor": "Indoor", 
      "agegroup": null, 
      "venueCountry": "GBR", 
      "rank": "5", 
      "event": "1500", 
      "result": "3:38.61", 
      "date": "2014-02-15", 
      "round": null, 
      "wind": null
    }, 
    {
      "competition_ID": "12848482", 
      "compName": "15th World Indoor Championships, ERGO Arena", 
      "roundstage": "Prelim", 
      "venue": "Sopot", 
      "IndoorOutdoor": "Indoor", 
      "agegroup": null, 
      "venueCountry": "POL", 
      "rank": "3", 
      "event": "1500", 
      "result": "3:47.22", 
      "date": "2014-03-07", 
      "round": "h1", 
      "wind": null
    }, 
    {
      "competition_ID": "12849979", 
      "compName": null, 
      "roundstage": "Final", 
      "venue": "Doha", 
      "IndoorOutdoor": "Outdoor", 
      "agegroup": null, 
      "venueCountry": "QAT", 
      "rank": null, 
      "event": "1500", 
      "result": null, 
      "date": "2014-05-09", 
      "round": null, 
      "wind": null
    }, 
    {
      "competition_ID": "12851436", 
      "compName": null, 
      "roundstage": "Final", 
      "venue": "Eugene OR", 
      "IndoorOutdoor": "Outdoor", 
      "agegroup": null, 
      "venueCountry": "USA", 
      "rank": "12", 
      "event": "1500", 
      "result": "3:36.94", 
      "date": "2014-05-31", 
      "round": null, 
      "wind": null
    }, 
    {
      "competition_ID": "12851436", 
      "compName": null, 
      "roundstage": "Final", 
      "venue": "Eugene OR", 
      "IndoorOutdoor": "Outdoor", 
      "agegroup": null, 
      "venueCountry": "USA", 
      "rank": "12", 
      "event": "Mile", 
      "result": "3:53.22", 
      "date": "2014-05-31", 
      "round": null, 
      "wind": null
    }, 
    {
      "competition_ID": "12851686", 
      "compName": "AA-Drink Fanny Blankers-Koen Games, IAAF World Challenge", 
      "roundstage": "Final", 
      "venue": "Hengelo", 
      "IndoorOutdoor": "Outdoor", 
      "agegroup": null, 
      "venueCountry": "NED", 
      "rank": "4", 
      "event": "3000", 
      "result": "7:42.90", 
      "date": "2014-06-08", 
      "round": null, 
      "wind": null
    }, 
    {
      "competition_ID": "12851916", 
      "compName": "Bislett Games, Bislett Stadium, IAAF Diamond League", 
      "roundstage": "Final", 
      "venue": "Oslo", 
      "IndoorOutdoor": "Outdoor", 
      "agegroup": null, 
      "venueCountry": "NOR", 
      "rank": "6", 
      "event": "1500", 
      "result": "3:35.90", 
      "date": "2014-06-11", 
      "round": null, 
      "wind": null
    }, 
    {
      "competition_ID": "12851916", 
      "compName": "Bislett Games, Bislett Stadium, IAAF Diamond League", 
      "roundstage": "Final", 
      "venue": "Oslo", 
      "IndoorOutdoor": "Outdoor", 
      "agegroup": null, 
      "venueCountry": "NOR", 
      "rank": "6", 
      "event": "Mile", 
      "result": "3:51.59", 
      "date": "2014-06-11", 
      "round": null, 
      "wind": null
    }, 
    {
      "competition_ID": "12852602", 
      "compName": null, 
      "roundstage": "Final", 
      "venue": "Lausanne", 
      "IndoorOutdoor": "Outdoor", 
      "agegroup": null, 
      "venueCountry": "SUI", 
      "rank": "11", 
      "event": "1500", 
      "result": "3:35.24", 
      "date": "2014-07-03", 
      "round": null, 
      "wind": null
    }, 
    {
      "competition_ID": "12853643", 
      "compName": null, 
      "roundstage": "Prelim", 
      "venue": "Marrakech", 
      "IndoorOutdoor": "Outdoor", 
      "agegroup": null, 
      "venueCountry": "MAR", 
      "rank": "1", 
      "event": "1500", 
      "result": "3:54.73", 
      "date": "2014-08-13", 
      "round": "h1", 
      "wind": null
    }, 
    {
      "competition_ID": "12853643", 
      "compName": null, 
      "roundstage": "Final", 
      "venue": "Marrakech", 
      "IndoorOutdoor": "Outdoor", 
      "agegroup": null, 
      "venueCountry": "MAR", 
      "rank": "4", 
      "event": "1500", 
      "result": "3:42.65", 
      "date": "2014-08-14", 
      "round": null, 
      "wind": null
    }, 
    {
      "competition_ID": "12853856", 
      "compName": "73rd ISTAF, Olympic Stadium", 
      "roundstage": "Final", 
      "venue": "Berlin", 
      "IndoorOutdoor": "Outdoor", 
      "agegroup": null, 
      "venueCountry": "GER", 
      "rank": "1", 
      "event": "1500", 
      "result": "3:33.24", 
      "date": "2014-08-31", 
      "round": null, 
      "wind": null
    }, 
    {
      "competition_ID": "12854005", 
      "compName": "Van Damme Memorial, IAAF Diamond League, King Baudoin Stadium", 
      "roundstage": "Final", 
      "venue": "Bruxelles", 
      "IndoorOutdoor": "Outdoor", 
      "agegroup": null, 
      "venueCountry": "BEL", 
      "rank": "9", 
      "event": "1500", 
      "result": "3:33.70", 
      "date": "2014-09-05", 
      "round": null, 
      "wind": null
    }, 
    {
      "competition_ID": "12854010", 
      "compName": null, 
      "roundstage": "Final", 
      "venue": "Rieti", 
      "IndoorOutdoor": "Outdoor", 
      "agegroup": null, 
      "venueCountry": "ITA", 
      "rank": "4", 
      "event": "1500", 
      "result": "3:32.79", 
      "date": "2014-09-07", 
      "round": null, 
      "wind": null
    }, 
    {
      "competition_ID": "12860449", 
      "compName": "Shanghai Golden Grand Prix, IAAF Diamond League Meeting, Shanghai Stadium", 
      "roundstage": "Final", 
      "venue": "Shanghai", 
      "IndoorOutdoor": "Outdoor", 
      "agegroup": null, 
      "venueCountry": "CHN", 
      "rank": "11", 
      "event": "1500", 
      "result": "3:42.14", 
      "date": "2015-05-17", 
      "round": null, 
      "wind": null
    }, 
    {
      "competition_ID": "12860704", 
      "compName": null, 
      "roundstage": "Final", 
      "venue": "Hengelo", 
      "IndoorOutdoor": "Outdoor", 
      "agegroup": null, 
      "venueCountry": "NED", 
      "rank": "4", 
      "event": "1500", 
      "result": "3:35.73", 
      "date": "2015-05-24", 
      "round": null, 
      "wind": null
    }, 
    {
      "competition_ID": "12862652", 
      "compName": "KBC-Nacht, KBC Night of Athletics, Stadion De Veen", 
      "roundstage": "Final", 
      "venue": "Heusden", 
      "IndoorOutdoor": "Outdoor", 
      "agegroup": null, 
      "venueCountry": "BEL", 
      "rank": "4", 
      "event": "1500", 
      "result": "3:35.67", 
      "date": "2015-07-18", 
      "round": null, 
      "wind": null
    }, 
    {
      "competition_ID": "12863607", 
      "compName": "Tilastopajacup, Paavo Nurmi Stadium", 
      "roundstage": "Prelim", 
      "venue": "Beijing", 
      "IndoorOutdoor": "Outdoor", 
      "agegroup": null, 
      "venueCountry": "CHN", 
      "rank": "8", 
      "event": "1500", 
      "result": "3:38.66", 
      "date": "2015-08-27", 
      "round": "h3", 
      "wind": null
    }, 
    {
      "competition_ID": "12863607", 
      "compName": "Tilastopajacup, Paavo Nurmi Stadium", 
      "roundstage": "Prelim", 
      "venue": "Beijing", 
      "IndoorOutdoor": "Outdoor", 
      "agegroup": null, 
      "venueCountry": "CHN", 
      "rank": "6", 
      "event": "1500", 
      "result": "3:44.31", 
      "date": "2015-08-28", 
      "round": "s1", 
      "wind": null
    }, 
    {
      "competition_ID": "12863929", 
      "compName": null, 
      "roundstage": "Prelim", 
      "venue": "Brazzaville", 
      "IndoorOutdoor": "Outdoor", 
      "agegroup": null, 
      "venueCountry": "CGO", 
      "rank": "1", 
      "event": "1500", 
      "result": "3:48.32", 
      "date": "2015-09-13", 
      "round": "h1", 
      "wind": null
    }, 
    {
      "competition_ID": "12863929", 
      "compName": null, 
      "roundstage": "Final", 
      "venue": "Brazzaville", 
      "IndoorOutdoor": "Outdoor", 
      "agegroup": null, 
      "venueCountry": "CGO", 
      "rank": "1", 
      "event": "1500", 
      "result": "3:45.73", 
      "date": "2015-09-14", 
      "round": null, 
      "wind": null
    }, 
    {
      "competition_ID": "12869237", 
      "compName": "EC Classic Shootout", 
      "roundstage": "Final", 
      "venue": "Pretoria", 
      "IndoorOutdoor": "Outdoor", 
      "agegroup": null, 
      "venueCountry": "RSA", 
      "rank": "1", 
      "event": "2000", 
      "result": "5:08.06", 
      "date": "2016-01-28", 
      "round": null, 
      "wind": null
    }, 
    {
      "competition_ID": "12869444", 
      "compName": "11PSD-Bankth PSD Bank Meeting, Leichtathletikhalle im Arena Sportpark", 
      "roundstage": "Final", 
      "venue": "D\u00c3\u00bcsseldorf", 
      "IndoorOutdoor": "Indoor", 
      "agegroup": null, 
      "venueCountry": "GER", 
      "rank": "10", 
      "event": "1500", 
      "result": "3:42.77", 
      "date": "2016-02-03", 
      "round": null, 
      "wind": null
    }, 
    {
      "competition_ID": "12869863", 
      "compName": null, 
      "roundstage": "Final", 
      "venue": "Gent", 
      "IndoorOutdoor": "Indoor", 
      "agegroup": null, 
      "venueCountry": "BEL", 
      "rank": "2", 
      "event": "1500", 
      "result": "3:41.14", 
      "date": "2016-02-13", 
      "round": null, 
      "wind": null
    }, 
    {
      "competition_ID": "12870062", 
      "compName": "Meeting National En Salle De Reims", 
      "roundstage": "Final", 
      "venue": "Reims", 
      "IndoorOutdoor": "Indoor", 
      "agegroup": null, 
      "venueCountry": "FRA", 
      "rank": "3", 
      "event": "1500", 
      "result": "3:40.31", 
      "date": "2016-02-17", 
      "round": null, 
      "wind": null
    }, 
    {
      "competition_ID": "12870077", 
      "compName": "M\u00c3\u00adting Centenari FCA, Pista Coberta de Catalunya", 
      "roundstage": "Final", 
      "venue": "Sabadell", 
      "IndoorOutdoor": "Indoor", 
      "agegroup": null, 
      "venueCountry": "ESP", 
      "rank": "8", 
      "event": "1500", 
      "result": "3:41.27", 
      "date": "2016-02-19", 
      "round": null, 
      "wind": null
    }, 
    {
      "competition_ID": "12875008", 
      "compName": "Meeting Premium de Montreuil", 
      "roundstage": "Final", 
      "venue": "Montreuil", 
      "IndoorOutdoor": "Outdoor", 
      "agegroup": null, 
      "venueCountry": "FRA", 
      "rank": "3", 
      "event": "1500", 
      "result": "3:36.72", 
      "date": "2016-06-07", 
      "round": null, 
      "wind": null
    }, 
    {
      "competition_ID": "12875501", 
      "compName": "Meeting Premium de Nancy", 
      "roundstage": "Final", 
      "venue": "Tomblaine", 
      "IndoorOutdoor": "Outdoor", 
      "agegroup": null, 
      "venueCountry": "FRA", 
      "rank": "2", 
      "event": "1500", 
      "result": "3:36.43", 
      "date": "2016-06-14", 
      "round": null, 
      "wind": null
    }, 
    {
      "competition_ID": "12876125", 
      "compName": "96th Campionat de Catalunya Absolut, Estadi Joan Serrahima", 
      "roundstage": "Final", 
      "venue": "Barcelona", 
      "IndoorOutdoor": "Outdoor", 
      "agegroup": null, 
      "venueCountry": "ESP", 
      "rank": "3", 
      "event": "1500", 
      "result": "3:35.50", 
      "date": "2016-06-30", 
      "round": null, 
      "wind": null
    }, 
    {
      "competition_ID": "12877460", 
      "compName": null, 
      "roundstage": "Prelim", 
      "venue": "R\u00c3\u00ado de Janeiro", 
      "IndoorOutdoor": "Outdoor", 
      "agegroup": null, 
      "venueCountry": "BRA", 
      "rank": "5", 
      "event": "1500", 
      "result": "3:47.33", 
      "date": "2016-08-16", 
      "round": "h2", 
      "wind": null
    }, 
    {
      "competition_ID": "12877460", 
      "compName": null, 
      "roundstage": "Prelim", 
      "venue": "R\u00c3\u00ado de Janeiro", 
      "IndoorOutdoor": "Outdoor", 
      "agegroup": null, 
      "venueCountry": "BRA", 
      "rank": "6", 
      "event": "1500", 
      "result": "3:40.69", 
      "date": "2016-08-18", 
      "round": "s2", 
      "wind": null
    }
  ], 
  "athlete_id": "62913", 
  "birthdate": "11.10.1988", 
  "height": "180", 
  "birthyear": "1988", 
  "accomplishments": [
    {
      "description": "World Indoor Bronze Medallist", 
      "details": {
        "details": null
      }
    }, 
    {
      "description": "4th at World Indoor Championships", 
      "details": {
        "details": null
      }
    }, 
    {
      "description": "6th at Olympic Games", 
      "details": {
        "details": null
      }
    }, 
    {
      "description": "6th at World Indoor Championships", 
      "details": {
        "details": null
      }
    }, 
    {
      "description": "7th at World Championships", 
      "details": {
        "details": null
      }
    }, 
    {
      "description": "7th at World Championships", 
      "details": {
        "details": null
      }
    }
  ], 
  "gender": "M", 
  "nationality": "ETH"
}