﻿<?xml version="1.0" encoding="utf-8" ?>
<results>
<result>
<athlete_id>71905</athlete_id>
<gender>M</gender>
<personalBest>
<IndoorOutdoor>Outdoor</IndoorOutdoor>
<event>PV</event>
<result>5.72</result>
<wind></wind>
<rank>1</rank>
<round></round>
<roundstage>Final</roundstage>
<agegroup></agegroup>
<competition_ID>12813625</competition_ID>
<compName>17th Int. Stabhochsprung Meeting, TSG Jockgrim Stadion</compName>
<date>2011-07-27</date>
<venue>Jockgrim</venue>
<venueCountry>GER</venueCountry>
</personalBest>
<personalBest>
<IndoorOutdoor>Indoor</IndoorOutdoor>
<event>PV</event>
<result>5.73</result>
<wind></wind>
<rank>1</rank>
<round></round>
<roundstage>Final</roundstage>
<agegroup></agegroup>
<competition_ID>12820914</competition_ID>
<compName></compName>
<date>2012-03-03</date>
<venue>Bad Oeynhausen</venue>
<venueCountry>GER</venueCountry>
</personalBest>
<seasonalBest>
<IndoorOutdoor>Indoor</IndoorOutdoor>
<event>PV</event>
<result>5.50</result>
<wind></wind>
<rank>3</rank>
<round></round>
<roundstage>Final</roundstage>
<agegroup></agegroup>
<competition_ID>12870091</competition_ID>
<compName>18th Internationales Erdgas-Hallenmeeting, Sportforum</compName>
<date>2016-02-20</date>
<venue>Chemnitz</venue>
<venueCountry>GER</venueCountry>
</seasonalBest>
<seasonalBest>
<IndoorOutdoor>Outdoor</IndoorOutdoor>
<event>PV</event>
<result>5.70</result>
<wind></wind>
<rank>2</rank>
<round></round>
<roundstage>Final</roundstage>
<agegroup></agegroup>
<competition_ID>12876092</competition_ID>
<compName>Stabhochsprung-Meeting</compName>
<date>2016-06-28</date>
<venue>Landau</venue>
<venueCountry>GER</venueCountry>
</seasonalBest>
<athleteresulthistory>
<record>
<IndoorOutdoor>Outdoor</IndoorOutdoor>
<event>PV</event>
<result>4.75</result>
<wind></wind>
<rank>2</rank>
<round>-17</round>
<roundstage>Final</roundstage>
<agegroup>Under 18</agegroup>
<competition_ID>8934683</competition_ID>
<compName></compName>
<date>2005-07-29</date>
<venue>Braunschweig</venue>
<venueCountry>GER</venueCountry>
</record>
<record>
<IndoorOutdoor>Outdoor</IndoorOutdoor>
<event>PV</event>
<result>5.02</result>
<wind></wind>
<rank>1</rank>
<round>-17</round>
<roundstage>Final</roundstage>
<agegroup>Under 18</agegroup>
<competition_ID>9141791</competition_ID>
<compName></compName>
<date>2006-06-03</date>
<venue>Holzminden</venue>
<venueCountry>GER</venueCountry>
</record>
<record>
<IndoorOutdoor>Outdoor</IndoorOutdoor>
<event>PV</event>
<result>4.80</result>
<wind></wind>
<rank>8</rank>
<round>-19</round>
<roundstage>Final</roundstage>
<agegroup>Under 20</agegroup>
<competition_ID>9199502</competition_ID>
<compName></compName>
<date>2006-07-08</date>
<venue>Mannheim</venue>
<venueCountry>GER</venueCountry>
</record>
<record>
<IndoorOutdoor>Outdoor</IndoorOutdoor>
<event>PV</event>
<result>5.05</result>
<wind></wind>
<rank>1</rank>
<round>-17</round>
<roundstage>Final</roundstage>
<agegroup>Under 18</agegroup>
<competition_ID>9218008</competition_ID>
<compName></compName>
<date>2006-07-21</date>
<venue>Wattenscheid</venue>
<venueCountry>GER</venueCountry>
</record>
<record>
<IndoorOutdoor>Indoor</IndoorOutdoor>
<event>PV</event>
<result>4.90</result>
<wind></wind>
<rank>2</rank>
<round>-19</round>
<roundstage>Final</roundstage>
<agegroup>Under 20</agegroup>
<competition_ID>9534678</competition_ID>
<compName></compName>
<date>2007-01-14</date>
<venue>Leverkusen</venue>
<venueCountry>GER</venueCountry>
</record>
<record>
<IndoorOutdoor>Indoor</IndoorOutdoor>
<event>PV</event>
<result>5.20</result>
<wind></wind>
<rank>1</rank>
<round>-19</round>
<roundstage>Final</roundstage>
<agegroup>Under 20</agegroup>
<competition_ID>9646503</competition_ID>
<compName></compName>
<date>2007-01-28</date>
<venue>Dortmund</venue>
<venueCountry>GER</venueCountry>
</record>
<record>
<IndoorOutdoor>Indoor</IndoorOutdoor>
<event>PV</event>
<result>5.05</result>
<wind></wind>
<rank>4</rank>
<round>-19</round>
<roundstage>Final</roundstage>
<agegroup>Under 20</agegroup>
<competition_ID>9735735</competition_ID>
<compName></compName>
<date>2007-02-11</date>
<venue>Sindelfingen</venue>
<venueCountry>GER</venueCountry>
</record>
<record>
<IndoorOutdoor>Outdoor</IndoorOutdoor>
<event>PV</event>
<result>5.22</result>
<wind></wind>
<rank>2</rank>
<round>-19</round>
<roundstage>Final</roundstage>
<agegroup>Under 20</agegroup>
<competition_ID>10189950</competition_ID>
<compName></compName>
<date>2007-05-26</date>
<venue>Holzminden</venue>
<venueCountry>GER</venueCountry>
</record>
<record>
<IndoorOutdoor>Outdoor</IndoorOutdoor>
<event>PV</event>
<result>5.30</result>
<wind></wind>
<rank>2</rank>
<round>-19</round>
<roundstage>Final</roundstage>
<agegroup>Under 20</agegroup>
<competition_ID>10173489</competition_ID>
<compName></compName>
<date>2007-06-09</date>
<venue>Potsdam</venue>
<venueCountry>GER</venueCountry>
</record>
<record>
<IndoorOutdoor>Outdoor</IndoorOutdoor>
<event>PV</event>
<result>4.80</result>
<wind></wind>
<rank>3</rank>
<round>-19</round>
<roundstage>Final</roundstage>
<agegroup>Under 20</agegroup>
<competition_ID>10223596</competition_ID>
<compName></compName>
<date>2007-06-23</date>
<venue>Mannheim</venue>
<venueCountry>GER</venueCountry>
</record>
<record>
<IndoorOutdoor>Outdoor</IndoorOutdoor>
<event>PV</event>
<result>5.27</result>
<wind></wind>
<rank>2</rank>
<round></round>
<roundstage>Final</roundstage>
<agegroup></agegroup>
<competition_ID>10279486</competition_ID>
<compName></compName>
<date>2007-07-07</date>
<venue>Oordegem</venue>
<venueCountry>BEL</venueCountry>
</record>
<record>
<IndoorOutdoor>Outdoor</IndoorOutdoor>
<event>PV</event>
<result>5.00</result>
<wind></wind>
<rank>5</rank>
<round>q-19</round>
<roundstage>Prelim</roundstage>
<agegroup></agegroup>
<competition_ID>10547927</competition_ID>
<compName></compName>
<date>2007-07-21</date>
<venue>Hengelo</venue>
<venueCountry>NED</venueCountry>
</record>
<record>
<IndoorOutdoor>Outdoor</IndoorOutdoor>
<event>PV</event>
<result>5.35</result>
<wind></wind>
<rank>4</rank>
<round>-19</round>
<roundstage>Final</roundstage>
<agegroup>Under 20</agegroup>
<competition_ID>10547927</competition_ID>
<compName></compName>
<date>2007-07-22</date>
<venue>Hengelo</venue>
<venueCountry>NED</venueCountry>
</record>
<record>
<IndoorOutdoor>Outdoor</IndoorOutdoor>
<event>PV</event>
<result>5.15</result>
<wind></wind>
<rank>2</rank>
<round>-19</round>
<roundstage>Final</roundstage>
<agegroup>Under 20</agegroup>
<competition_ID>10602076</competition_ID>
<compName></compName>
<date>2007-08-04</date>
<venue>Ulm</venue>
<venueCountry>GER</venueCountry>
</record>
<record>
<IndoorOutdoor>Outdoor</IndoorOutdoor>
<event>PV</event>
<result>5.30</result>
<wind></wind>
<rank>8</rank>
<round></round>
<roundstage>Final</roundstage>
<agegroup></agegroup>
<competition_ID>10612789</competition_ID>
<compName></compName>
<date>2007-08-10</date>
<venue>Leverkusen</venue>
<venueCountry>GER</venueCountry>
</record>
<record>
<IndoorOutdoor>Outdoor</IndoorOutdoor>
<event>PV</event>
<result>5.30</result>
<wind></wind>
<rank>1</rank>
<round>-19</round>
<roundstage>Final</roundstage>
<agegroup>Under 20</agegroup>
<competition_ID>11670063</competition_ID>
<compName></compName>
<date>2008-05-10</date>
<venue>Holzminden</venue>
<venueCountry>GER</venueCountry>
</record>
<record>
<IndoorOutdoor>Outdoor</IndoorOutdoor>
<event>PV</event>
<result>5.10</result>
<wind></wind>
<rank>11</rank>
<round></round>
<roundstage>Final</roundstage>
<agegroup></agegroup>
<competition_ID>11707449</competition_ID>
<compName></compName>
<date>2008-05-18</date>
<venue>Köln</venue>
<venueCountry>GER</venueCountry>
</record>
<record>
<IndoorOutdoor>Outdoor</IndoorOutdoor>
<event>PV</event>
<result>5.33</result>
<wind></wind>
<rank>3</rank>
<round></round>
<roundstage>Final</roundstage>
<agegroup></agegroup>
<competition_ID>12488323</competition_ID>
<compName></compName>
<date>2008-05-23</date>
<venue>Recklinghausen</venue>
<venueCountry>GER</venueCountry>
</record>
<record>
<IndoorOutdoor>Outdoor</IndoorOutdoor>
<event>PV</event>
<result>5.10</result>
<wind></wind>
<rank>2</rank>
<round></round>
<roundstage>Final</roundstage>
<agegroup></agegroup>
<competition_ID>11730318</competition_ID>
<compName></compName>
<date>2008-05-30</date>
<venue>Saulheim</venue>
<venueCountry>GER</venueCountry>
</record>
<record>
<IndoorOutdoor>Outdoor</IndoorOutdoor>
<event>PV</event>
<result>5.40</result>
<wind></wind>
<rank>2</rank>
<round>-19</round>
<roundstage>Final</roundstage>
<agegroup>Under 20</agegroup>
<competition_ID>11764079</competition_ID>
<compName></compName>
<date>2008-06-06</date>
<venue>Kassel</venue>
<venueCountry>GER</venueCountry>
</record>
<record>
<IndoorOutdoor>Outdoor</IndoorOutdoor>
<event>PV</event>
<result>5.20</result>
<wind></wind>
<rank>5</rank>
<round></round>
<roundstage>Final</roundstage>
<agegroup></agegroup>
<competition_ID>11804315</competition_ID>
<compName></compName>
<date>2008-06-14</date>
<venue>Leiden</venue>
<venueCountry>NED</venueCountry>
</record>
<record>
<IndoorOutdoor>Outdoor</IndoorOutdoor>
<event>PV</event>
<result>5.30</result>
<wind></wind>
<rank>2</rank>
<round>-19</round>
<roundstage>Final</roundstage>
<agegroup>Under 20</agegroup>
<competition_ID>11837987</competition_ID>
<compName></compName>
<date>2008-06-22</date>
<venue>Mannheim</venue>
<venueCountry>GER</venueCountry>
</record>
<record>
<IndoorOutdoor>Outdoor</IndoorOutdoor>
<event>PV</event>
<result>5.10</result>
<wind></wind>
<rank>6</rank>
<round>q-19</round>
<roundstage>Prelim</roundstage>
<agegroup></agegroup>
<competition_ID>11909738</competition_ID>
<compName></compName>
<date>2008-07-10</date>
<venue>Bydgoszcz</venue>
<venueCountry>POL</venueCountry>
</record>
<record>
<IndoorOutdoor>Outdoor</IndoorOutdoor>
<event>PV</event>
<result>5.30</result>
<wind></wind>
<rank>3</rank>
<round>-19</round>
<roundstage>Final</roundstage>
<agegroup>Under 20</agegroup>
<competition_ID>11909738</competition_ID>
<compName></compName>
<date>2008-07-12</date>
<venue>Bydgoszcz</venue>
<venueCountry>POL</venueCountry>
</record>
<record>
<IndoorOutdoor>Outdoor</IndoorOutdoor>
<event>PV</event>
<result>5.40</result>
<wind></wind>
<rank>1</rank>
<round>-19</round>
<roundstage>Final</roundstage>
<agegroup>Under 20</agegroup>
<competition_ID>11979124</competition_ID>
<compName></compName>
<date>2008-07-19</date>
<venue>Berlin</venue>
<venueCountry>GER</venueCountry>
</record>
<record>
<IndoorOutdoor>Outdoor</IndoorOutdoor>
<event>PV</event>
<result>5.50</result>
<wind></wind>
<rank>3</rank>
<round></round>
<roundstage>Final</roundstage>
<agegroup></agegroup>
<competition_ID>12503730</competition_ID>
<compName></compName>
<date>2008-07-28</date>
<venue>Norderney</venue>
<venueCountry>GER</venueCountry>
</record>
<record>
<IndoorOutdoor>Outdoor</IndoorOutdoor>
<event>PV</event>
<result>5.50</result>
<wind></wind>
<rank>4</rank>
<round></round>
<roundstage>Final</roundstage>
<agegroup></agegroup>
<competition_ID>12002288</competition_ID>
<compName></compName>
<date>2008-07-30</date>
<venue>Leverkusen</venue>
<venueCountry>GER</venueCountry>
</record>
<record>
<IndoorOutdoor>Outdoor</IndoorOutdoor>
<event>PV</event>
<result>5.40</result>
<wind></wind>
<rank>1</rank>
<round>-19</round>
<roundstage>Final</roundstage>
<agegroup>Under 20</agegroup>
<competition_ID>12070602</competition_ID>
<compName></compName>
<date>2008-08-31</date>
<venue>Elstal</venue>
<venueCountry>GER</venueCountry>
</record>
<record>
<IndoorOutdoor>Indoor</IndoorOutdoor>
<event>PV</event>
<result>5.30</result>
<wind></wind>
<rank>4</rank>
<round></round>
<roundstage>Final</roundstage>
<agegroup></agegroup>
<competition_ID>12534673</competition_ID>
<compName></compName>
<date>2009-01-17</date>
<venue>Leverkusen</venue>
<venueCountry>GER</venueCountry>
</record>
<record>
<IndoorOutdoor>Indoor</IndoorOutdoor>
<event>PV</event>
<result>5.20</result>
<wind></wind>
<rank>10</rank>
<round></round>
<roundstage>Final</roundstage>
<agegroup></agegroup>
<competition_ID>12568558</competition_ID>
<compName></compName>
<date>2009-02-01</date>
<venue>Leipzig</venue>
<venueCountry>GER</venueCountry>
</record>
<record>
<IndoorOutdoor>Indoor</IndoorOutdoor>
<event>PV</event>
<result>5.40</result>
<wind></wind>
<rank>10</rank>
<round></round>
<roundstage>Final</roundstage>
<agegroup></agegroup>
<competition_ID>12599094</competition_ID>
<compName></compName>
<date>2009-02-13</date>
<venue>Düsseldorf</venue>
<venueCountry>GER</venueCountry>
</record>
<record>
<IndoorOutdoor>Indoor</IndoorOutdoor>
<event>PV</event>
<result>5.30</result>
<wind></wind>
<rank>12</rank>
<round></round>
<roundstage>Final</roundstage>
<agegroup></agegroup>
<competition_ID>12621534</competition_ID>
<compName></compName>
<date>2009-02-21</date>
<venue>Leipzig</venue>
<venueCountry>GER</venueCountry>
</record>
<record>
<IndoorOutdoor>Indoor</IndoorOutdoor>
<event>PV</event>
<result>5.40</result>
<wind></wind>
<rank>7</rank>
<round></round>
<roundstage>Final</roundstage>
<agegroup></agegroup>
<competition_ID>12637175</competition_ID>
<compName></compName>
<date>2009-02-27</date>
<venue>Chemnitz</venue>
<venueCountry>GER</venueCountry>
</record>
<record>
<IndoorOutdoor>Outdoor</IndoorOutdoor>
<event>PV</event>
<result>5.40</result>
<wind></wind>
<rank>5=</rank>
<round></round>
<roundstage>Final</roundstage>
<agegroup></agegroup>
<competition_ID>12786973</competition_ID>
<compName></compName>
<date>2009-05-24</date>
<venue>Soest</venue>
<venueCountry>GER</venueCountry>
</record>
<record>
<IndoorOutdoor>Outdoor</IndoorOutdoor>
<event>PV</event>
<result>5.40</result>
<wind></wind>
<rank>1</rank>
<round></round>
<roundstage>Final</roundstage>
<agegroup></agegroup>
<competition_ID>12787202</competition_ID>
<compName></compName>
<date>2009-05-30</date>
<venue>Holzminden</venue>
<venueCountry>GER</venueCountry>
</record>
<record>
<IndoorOutdoor>Outdoor</IndoorOutdoor>
<event>PV</event>
<result>5.30</result>
<wind></wind>
<rank>8</rank>
<round></round>
<roundstage>Final</roundstage>
<agegroup></agegroup>
<competition_ID>12787362</competition_ID>
<compName></compName>
<date>2009-06-05</date>
<venue>Baunatal</venue>
<venueCountry>GER</venueCountry>
</record>
<record>
<IndoorOutdoor>Outdoor</IndoorOutdoor>
<event>PV</event>
<result>5.00</result>
<wind></wind>
<rank>1</rank>
<round></round>
<roundstage>Final</roundstage>
<agegroup></agegroup>
<competition_ID>12787722</competition_ID>
<compName></compName>
<date>2009-06-11</date>
<venue>Duisburg</venue>
<venueCountry>GER</venueCountry>
</record>
<record>
<IndoorOutdoor>Outdoor</IndoorOutdoor>
<event>PV</event>
<result>5.50</result>
<wind></wind>
<rank>4</rank>
<round></round>
<roundstage>Final</roundstage>
<agegroup></agegroup>
<competition_ID>12787891</competition_ID>
<compName></compName>
<date>2009-06-17</date>
<venue>Ingolstadt</venue>
<venueCountry>GER</venueCountry>
</record>
<record>
<IndoorOutdoor>Outdoor</IndoorOutdoor>
<event>PV</event>
<result>5.20</result>
<wind></wind>
<rank>6</rank>
<round></round>
<roundstage>Final</roundstage>
<agegroup></agegroup>
<competition_ID>12788085</competition_ID>
<compName></compName>
<date>2009-06-24</date>
<venue>Biberach</venue>
<venueCountry>GER</venueCountry>
</record>
<record>
<IndoorOutdoor>Outdoor</IndoorOutdoor>
<event>PV</event>
<result>5.20</result>
<wind></wind>
<rank>8</rank>
<round>-22</round>
<roundstage>Final</roundstage>
<agegroup>Under 23</agegroup>
<competition_ID>12788260</competition_ID>
<compName></compName>
<date>2009-06-28</date>
<venue>Göttingen</venue>
<venueCountry>GER</venueCountry>
</record>
<record>
<IndoorOutdoor>Outdoor</IndoorOutdoor>
<event>PV</event>
<result>5.40</result>
<wind></wind>
<rank>8</rank>
<round></round>
<roundstage>Final</roundstage>
<agegroup></agegroup>
<competition_ID>12788378</competition_ID>
<compName></compName>
<date>2009-07-04</date>
<venue>Ulm</venue>
<venueCountry>GER</venueCountry>
</record>
<record>
<IndoorOutdoor>Outdoor</IndoorOutdoor>
<event>PV</event>
<result>5.20</result>
<wind></wind>
<rank>13</rank>
<round>q-22</round>
<roundstage>Prelim</roundstage>
<agegroup></agegroup>
<competition_ID>12788650</competition_ID>
<compName></compName>
<date>2009-07-17</date>
<venue>Kaunas</venue>
<venueCountry>LTU</venueCountry>
</record>
<record>
<IndoorOutdoor>Outdoor</IndoorOutdoor>
<event>PV</event>
<result>5.20</result>
<wind></wind>
<rank>10</rank>
<round></round>
<roundstage>Final</roundstage>
<agegroup></agegroup>
<competition_ID>12788977</competition_ID>
<compName></compName>
<date>2009-07-31</date>
<venue>Leverkusen</venue>
<venueCountry>GER</venueCountry>
</record>
<record>
<IndoorOutdoor>Outdoor</IndoorOutdoor>
<event>PV</event>
<result>5.30</result>
<wind></wind>
<rank>5</rank>
<round></round>
<roundstage>Final</roundstage>
<agegroup></agegroup>
<competition_ID>12789087</competition_ID>
<compName></compName>
<date>2009-08-08</date>
<venue>Cottbus</venue>
<venueCountry>GER</venueCountry>
</record>
<record>
<IndoorOutdoor>Outdoor</IndoorOutdoor>
<event>PV</event>
<result>5.20</result>
<wind></wind>
<rank>5</rank>
<round></round>
<roundstage>Final</roundstage>
<agegroup></agegroup>
<competition_ID>12789098</competition_ID>
<compName></compName>
<date>2009-08-10</date>
<venue>Düsseldorf</venue>
<venueCountry>GER</venueCountry>
</record>
<record>
<IndoorOutdoor>Indoor</IndoorOutdoor>
<event>PV</event>
<result>5.30</result>
<wind></wind>
<rank>3</rank>
<round></round>
<roundstage>Final</roundstage>
<agegroup></agegroup>
<competition_ID>12791983</competition_ID>
<compName></compName>
<date>2010-01-16</date>
<venue>Leverkusen</venue>
<venueCountry>GER</venueCountry>
</record>
<record>
<IndoorOutdoor>Indoor</IndoorOutdoor>
<event>PV</event>
<result>5.44</result>
<wind></wind>
<rank>3</rank>
<round></round>
<roundstage>Final</roundstage>
<agegroup></agegroup>
<competition_ID>12793248</competition_ID>
<compName></compName>
<date>2010-02-04</date>
<venue>Linz</venue>
<venueCountry>AUT</venueCountry>
</record>
<record>
<IndoorOutdoor>Indoor</IndoorOutdoor>
<event>PV</event>
<result>5.10</result>
<wind></wind>
<rank>3</rank>
<round></round>
<roundstage>Final</roundstage>
<agegroup></agegroup>
<competition_ID>12793345</competition_ID>
<compName></compName>
<date>2010-02-07</date>
<venue>Leverkusen</venue>
<venueCountry>GER</venueCountry>
</record>
<record>
<IndoorOutdoor>Indoor</IndoorOutdoor>
<event>PV</event>
<result>5.50</result>
<wind></wind>
<rank>4=</rank>
<round></round>
<roundstage>Final</roundstage>
<agegroup></agegroup>
<competition_ID>12793597</competition_ID>
<compName></compName>
<date>2010-02-13</date>
<venue>Leipzig</venue>
<venueCountry>GER</venueCountry>
</record>
<record>
<IndoorOutdoor>Indoor</IndoorOutdoor>
<event>PV</event>
<result>5.20</result>
<wind></wind>
<rank>6=</rank>
<round></round>
<roundstage>Final</roundstage>
<agegroup></agegroup>
<competition_ID>12793919</competition_ID>
<compName></compName>
<date>2010-02-20</date>
<venue>Dessau</venue>
<venueCountry>GER</venueCountry>
</record>
<record>
<IndoorOutdoor>Indoor</IndoorOutdoor>
<event>PV</event>
<result>5.60</result>
<wind></wind>
<rank>5</rank>
<round></round>
<roundstage>Final</roundstage>
<agegroup></agegroup>
<competition_ID>12794105</competition_ID>
<compName></compName>
<date>2010-02-27</date>
<venue>Karlsruhe</venue>
<venueCountry>GER</venueCountry>
</record>
<record>
<IndoorOutdoor>Outdoor</IndoorOutdoor>
<event>PV</event>
<result>5.50</result>
<wind></wind>
<rank>1</rank>
<round></round>
<roundstage>Final</roundstage>
<agegroup></agegroup>
<competition_ID>12797356</competition_ID>
<compName></compName>
<date>2010-05-22</date>
<venue>Holzminden</venue>
<venueCountry>GER</venueCountry>
</record>
<record>
<IndoorOutdoor>Outdoor</IndoorOutdoor>
<event>PV</event>
<result>5.50</result>
<wind></wind>
<rank>3</rank>
<round></round>
<roundstage>Final</roundstage>
<agegroup></agegroup>
<competition_ID>12797590</competition_ID>
<compName></compName>
<date>2010-05-28</date>
<venue>Dessau</venue>
<venueCountry>GER</venueCountry>
</record>
<record>
<IndoorOutdoor>Outdoor</IndoorOutdoor>
<event>PV</event>
<result>5.50</result>
<wind></wind>
<rank>5</rank>
<round></round>
<roundstage>Final</roundstage>
<agegroup></agegroup>
<competition_ID>12797662</competition_ID>
<compName></compName>
<date>2010-05-30</date>
<venue>Cottbus</venue>
<venueCountry>GER</venueCountry>
</record>
<record>
<IndoorOutdoor>Outdoor</IndoorOutdoor>
<event>PV</event>
<result>5.50</result>
<wind></wind>
<rank>3</rank>
<round></round>
<roundstage>Final</roundstage>
<agegroup></agegroup>
<competition_ID>12798013</competition_ID>
<compName></compName>
<date>2010-06-09</date>
<venue>Cuxhaven</venue>
<venueCountry>GER</venueCountry>
</record>
<record>
<IndoorOutdoor>Outdoor</IndoorOutdoor>
<event>PV</event>
<result>5.50</result>
<wind></wind>
<rank>3</rank>
<round>-22</round>
<roundstage>Final</roundstage>
<agegroup>Under 23</agegroup>
<competition_ID>12798228</competition_ID>
<compName></compName>
<date>2010-06-12</date>
<venue>Bydgoszcz</venue>
<venueCountry>POL</venueCountry>
</record>
<record>
<IndoorOutdoor>Outdoor</IndoorOutdoor>
<event>PV</event>
<result>5.40</result>
<wind></wind>
<rank>8</rank>
<round></round>
<roundstage>Final</roundstage>
<agegroup></agegroup>
<competition_ID>12798941</competition_ID>
<compName></compName>
<date>2010-06-25</date>
<venue>Tomblaine</venue>
<venueCountry>FRA</venueCountry>
</record>
<record>
<IndoorOutdoor>Outdoor</IndoorOutdoor>
<event>PV</event>
<result>5.55</result>
<wind></wind>
<rank>7</rank>
<round></round>
<roundstage>Final</roundstage>
<agegroup></agegroup>
<competition_ID>12799324</competition_ID>
<compName></compName>
<date>2010-07-04</date>
<venue>Rottach-Egern</venue>
<venueCountry>GER</venueCountry>
</record>
<record>
<IndoorOutdoor>Outdoor</IndoorOutdoor>
<event>PV</event>
<result></result>
<wind></wind>
<rank></rank>
<round></round>
<roundstage>Final</roundstage>
<agegroup></agegroup>
<competition_ID>12799366</competition_ID>
<compName></compName>
<date>2010-07-09</date>
<venue>Biberach</venue>
<venueCountry>GER</venueCountry>
</record>
<record>
<IndoorOutdoor>Outdoor</IndoorOutdoor>
<event>PV</event>
<result>5.40</result>
<wind></wind>
<rank>7</rank>
<round></round>
<roundstage>Final</roundstage>
<agegroup></agegroup>
<competition_ID>12799890</competition_ID>
<compName></compName>
<date>2010-07-17</date>
<venue>Braunschweig</venue>
<venueCountry>GER</venueCountry>
</record>
<record>
<IndoorOutdoor>Outdoor</IndoorOutdoor>
<event>PV</event>
<result>5.31</result>
<wind></wind>
<rank>8</rank>
<round></round>
<roundstage>Final</roundstage>
<agegroup></agegroup>
<competition_ID>12800032</competition_ID>
<compName></compName>
<date>2010-07-21</date>
<venue>Jockgrim</venue>
<venueCountry>GER</venueCountry>
</record>
<record>
<IndoorOutdoor>Outdoor</IndoorOutdoor>
<event>PV</event>
<result>5.45</result>
<wind></wind>
<rank>1</rank>
<round>-22</round>
<roundstage>Final</roundstage>
<agegroup>Under 23</agegroup>
<competition_ID>12800324</competition_ID>
<compName></compName>
<date>2010-07-28</date>
<venue>Leverkusen</venue>
<venueCountry>GER</venueCountry>
</record>
<record>
<IndoorOutdoor>Outdoor</IndoorOutdoor>
<event>PV</event>
<result>5.30</result>
<wind></wind>
<rank>4</rank>
<round></round>
<roundstage>Final</roundstage>
<agegroup></agegroup>
<competition_ID>12800298</competition_ID>
<compName></compName>
<date>2010-08-04</date>
<venue>Sondershausen</venue>
<venueCountry>GER</venueCountry>
</record>
<record>
<IndoorOutdoor>Outdoor</IndoorOutdoor>
<event>PV</event>
<result>5.23</result>
<wind></wind>
<rank>9</rank>
<round></round>
<roundstage>Final</roundstage>
<agegroup></agegroup>
<competition_ID>12800650</competition_ID>
<compName></compName>
<date>2010-08-06</date>
<venue>Silandro</venue>
<venueCountry>ITA</venueCountry>
</record>
<record>
<IndoorOutdoor>Outdoor</IndoorOutdoor>
<event>PV</event>
<result>5.40</result>
<wind></wind>
<rank>1</rank>
<round>-22</round>
<roundstage>Final</roundstage>
<agegroup>Under 23</agegroup>
<competition_ID>12800380</competition_ID>
<compName></compName>
<date>2010-08-15</date>
<venue>Regensburg</venue>
<venueCountry>GER</venueCountry>
</record>
<record>
<IndoorOutdoor>Outdoor</IndoorOutdoor>
<event>PV</event>
<result>5.50</result>
<wind></wind>
<rank>2</rank>
<round></round>
<roundstage>Final</roundstage>
<agegroup></agegroup>
<competition_ID>12800705</competition_ID>
<compName>17th Stadionfest</compName>
<date>2010-08-20</date>
<venue>Königs Wusterhausen</venue>
<venueCountry>GER</venueCountry>
</record>
<record>
<IndoorOutdoor>Outdoor</IndoorOutdoor>
<event>PV</event>
<result></result>
<wind></wind>
<rank></rank>
<round></round>
<roundstage>Final</roundstage>
<agegroup></agegroup>
<competition_ID>12800721</competition_ID>
<compName>Leichtathletik Meeting Haldensleben, Waldstadion</compName>
<date>2010-08-22</date>
<venue>Haldensleben</venue>
<venueCountry>GER</venueCountry>
</record>
<record>
<IndoorOutdoor>Outdoor</IndoorOutdoor>
<event>PV</event>
<result>5.41</result>
<wind></wind>
<rank>9</rank>
<round></round>
<roundstage>Final</roundstage>
<agegroup></agegroup>
<competition_ID>12801098</competition_ID>
<compName></compName>
<date>2010-09-01</date>
<venue>Aachen</venue>
<venueCountry>GER</venueCountry>
</record>
<record>
<IndoorOutdoor>Indoor</IndoorOutdoor>
<event>PV</event>
<result>5.40</result>
<wind></wind>
<rank>1</rank>
<round></round>
<roundstage>Final</roundstage>
<agegroup></agegroup>
<competition_ID>12805135</competition_ID>
<compName>Nordrhein-Hallenmeisterschaften</compName>
<date>2011-01-15</date>
<venue>Leverkusen</venue>
<venueCountry>GER</venueCountry>
</record>
<record>
<IndoorOutdoor>Indoor</IndoorOutdoor>
<event>PV</event>
<result>5.40</result>
<wind></wind>
<rank>5</rank>
<round></round>
<roundstage>Final</roundstage>
<agegroup></agegroup>
<competition_ID>12805679</competition_ID>
<compName>Springermeeting</compName>
<date>2011-01-26</date>
<venue>Cottbus</venue>
<venueCountry>GER</venueCountry>
</record>
<record>
<IndoorOutdoor>Indoor</IndoorOutdoor>
<event>PV</event>
<result>5.40</result>
<wind></wind>
<rank>1</rank>
<round></round>
<roundstage>Final</roundstage>
<agegroup></agegroup>
<competition_ID>12806055</competition_ID>
<compName></compName>
<date>2011-01-29</date>
<venue>Dormagen</venue>
<venueCountry>GER</venueCountry>
</record>
<record>
<IndoorOutdoor>Indoor</IndoorOutdoor>
<event>PV</event>
<result>5.40</result>
<wind></wind>
<rank>7</rank>
<round></round>
<roundstage>Final</roundstage>
<agegroup></agegroup>
<competition_ID>12806001</competition_ID>
<compName>10th Internationales Springermeeting</compName>
<date>2011-02-02</date>
<venue>Dessau</venue>
<venueCountry>GER</venueCountry>
</record>
<record>
<IndoorOutdoor>Indoor</IndoorOutdoor>
<event>PV</event>
<result>5.53</result>
<wind></wind>
<rank>2</rank>
<round></round>
<roundstage>Final</roundstage>
<agegroup></agegroup>
<competition_ID>12806119</competition_ID>
<compName></compName>
<date>2011-02-05</date>
<venue>Landau</venue>
<venueCountry>GER</venueCountry>
</record>
<record>
<IndoorOutdoor>Indoor</IndoorOutdoor>
<event>PV</event>
<result>5.60</result>
<wind></wind>
<rank>4</rank>
<round></round>
<roundstage>Final</roundstage>
<agegroup></agegroup>
<competition_ID>12806460</competition_ID>
<compName>PSD Bank Meeting, Arena-Sportpark</compName>
<date>2011-02-11</date>
<venue>Düsseldorf</venue>
<venueCountry>GER</venueCountry>
</record>
<record>
<IndoorOutdoor>Indoor</IndoorOutdoor>
<event>PV</event>
<result>5.45</result>
<wind></wind>
<rank>3</rank>
<round></round>
<roundstage>Final</roundstage>
<agegroup></agegroup>
<competition_ID>12806505</competition_ID>
<compName>Belgacom Indoor Flanders, Topsporthal</compName>
<date>2011-02-13</date>
<venue>Gent</venue>
<venueCountry>BEL</venueCountry>
</record>
<record>
<IndoorOutdoor>Indoor</IndoorOutdoor>
<event>PV</event>
<result>5.51</result>
<wind></wind>
<rank>4</rank>
<round></round>
<roundstage>Final</roundstage>
<agegroup></agegroup>
<competition_ID>12806817</competition_ID>
<compName></compName>
<date>2011-02-19</date>
<venue>Potsdam</venue>
<venueCountry>GER</venueCountry>
</record>
<record>
<IndoorOutdoor>Indoor</IndoorOutdoor>
<event>PV</event>
<result>5.50</result>
<wind></wind>
<rank>3</rank>
<round></round>
<roundstage>Final</roundstage>
<agegroup></agegroup>
<competition_ID>12807208</competition_ID>
<compName>National Indoor Championships</compName>
<date>2011-02-26</date>
<venue>Leipzig</venue>
<venueCountry>GER</venueCountry>
</record>
<record>
<IndoorOutdoor>Indoor</IndoorOutdoor>
<event>PV</event>
<result>5.42</result>
<wind></wind>
<rank>4</rank>
<round></round>
<roundstage>Final</roundstage>
<agegroup></agegroup>
<competition_ID>12807620</competition_ID>
<compName></compName>
<date>2011-03-12</date>
<venue>Bad Oeynhausen</venue>
<venueCountry>GER</venueCountry>
</record>
<record>
<IndoorOutdoor>Outdoor</IndoorOutdoor>
<event>PV</event>
<result></result>
<wind></wind>
<rank></rank>
<round></round>
<roundstage>Final</roundstage>
<agegroup></agegroup>
<competition_ID>12810306</competition_ID>
<compName></compName>
<date>2011-05-21</date>
<venue>Rechberghausen</venue>
<venueCountry>GER</venueCountry>
</record>
<record>
<IndoorOutdoor>Outdoor</IndoorOutdoor>
<event>PV</event>
<result>5.40</result>
<wind></wind>
<rank>1</rank>
<round></round>
<roundstage>Final</roundstage>
<agegroup></agegroup>
<competition_ID>12810724</competition_ID>
<compName></compName>
<date>2011-05-28</date>
<venue>Darmstadt</venue>
<venueCountry>GER</venueCountry>
</record>
<record>
<IndoorOutdoor>Outdoor</IndoorOutdoor>
<event>PV</event>
<result>5.22</result>
<wind></wind>
<rank>7</rank>
<round></round>
<roundstage>Final</roundstage>
<agegroup></agegroup>
<competition_ID>12810848</competition_ID>
<compName>Paul-Greifzu-Stadion</compName>
<date>2011-06-01</date>
<venue>Dessau</venue>
<venueCountry>GER</venueCountry>
</record>
<record>
<IndoorOutdoor>Outdoor</IndoorOutdoor>
<event>PV</event>
<result>5.53</result>
<wind></wind>
<rank>3</rank>
<round></round>
<roundstage>Final</roundstage>
<agegroup></agegroup>
<competition_ID>12811296</competition_ID>
<compName></compName>
<date>2011-06-03</date>
<venue>Recklinghausen</venue>
<venueCountry>GER</venueCountry>
</record>
<record>
<IndoorOutdoor>Outdoor</IndoorOutdoor>
<event>PV</event>
<result>5.42</result>
<wind></wind>
<rank>2</rank>
<round></round>
<roundstage>Final</roundstage>
<agegroup></agegroup>
<competition_ID>12811454</competition_ID>
<compName></compName>
<date>2011-06-10</date>
<venue>Soest</venue>
<venueCountry>GER</venueCountry>
</record>
<record>
<IndoorOutdoor>Outdoor</IndoorOutdoor>
<event>PV</event>
<result>5.62</result>
<wind></wind>
<rank>2</rank>
<round></round>
<roundstage>Final</roundstage>
<agegroup></agegroup>
<competition_ID>12811538</competition_ID>
<compName>47th Internationales Pfingstsportfest</compName>
<date>2011-06-13</date>
<venue>Rehlingen</venue>
<venueCountry>GER</venueCountry>
</record>
<record>
<IndoorOutdoor>Outdoor</IndoorOutdoor>
<event>PV</event>
<result>5.32</result>
<wind></wind>
<rank>3</rank>
<round></round>
<roundstage>Final</roundstage>
<agegroup></agegroup>
<competition_ID>12812098</competition_ID>
<compName></compName>
<date>2011-06-23</date>
<venue>Ingolstadt</venue>
<venueCountry>GER</venueCountry>
</record>
<record>
<IndoorOutdoor>Outdoor</IndoorOutdoor>
<event>PV</event>
<result>5.30</result>
<wind></wind>
<rank>5</rank>
<round>-22</round>
<roundstage>Final</roundstage>
<agegroup>Under 23</agegroup>
<competition_ID>12812337</competition_ID>
<compName>68th Deutsche Juniorenmeisterschaften</compName>
<date>2011-06-26</date>
<venue>Bremen</venue>
<venueCountry>GER</venueCountry>
</record>
<record>
<IndoorOutdoor>Outdoor</IndoorOutdoor>
<event>PV</event>
<result>5.60</result>
<wind></wind>
<rank>3</rank>
<round></round>
<roundstage>Final</roundstage>
<agegroup></agegroup>
<competition_ID>12812600</competition_ID>
<compName>1st Rottacher Springermeeting</compName>
<date>2011-07-02</date>
<venue>Rottach-Egern</venue>
<venueCountry>GER</venueCountry>
</record>
<record>
<IndoorOutdoor>Outdoor</IndoorOutdoor>
<event>PV</event>
<result>5.50</result>
<wind></wind>
<rank>4</rank>
<round></round>
<roundstage>Final</roundstage>
<agegroup></agegroup>
<competition_ID>12812883</competition_ID>
<compName>39th Meeting de Atletismo Madrid</compName>
<date>2011-07-09</date>
<venue>Madrid</venue>
<venueCountry>ESP</venueCountry>
</record>
<record>
<IndoorOutdoor>Outdoor</IndoorOutdoor>
<event>PV</event>
<result>5.20</result>
<wind></wind>
<rank>2</rank>
<round>q-22</round>
<roundstage>Prelim</roundstage>
<agegroup></agegroup>
<competition_ID>12813128</competition_ID>
<compName>8th European Athletics U23 Championships</compName>
<date>2011-07-14</date>
<venue>Ostrava</venue>
<venueCountry>CZE</venueCountry>
</record>
<record>
<IndoorOutdoor>Outdoor</IndoorOutdoor>
<event>PV</event>
<result>5.60</result>
<wind></wind>
<rank>2</rank>
<round>-22</round>
<roundstage>Final</roundstage>
<agegroup>Under 23</agegroup>
<competition_ID>12813128</competition_ID>
<compName></compName>
<date>2011-07-16</date>
<venue>Ostrava</venue>
<venueCountry>CZE</venueCountry>
</record>
<record>
<IndoorOutdoor>Outdoor</IndoorOutdoor>
<event>PV</event>
<result>5.62</result>
<wind></wind>
<rank>3</rank>
<round></round>
<roundstage>Final</roundstage>
<agegroup></agegroup>
<competition_ID>12813435</competition_ID>
<compName></compName>
<date>2011-07-24</date>
<venue>Kassel</venue>
<venueCountry>GER</venueCountry>
</record>
<record>
<IndoorOutdoor>Outdoor</IndoorOutdoor>
<event>PV</event>
<result>5.72</result>
<wind></wind>
<rank>1</rank>
<round></round>
<roundstage>Final</roundstage>
<agegroup></agegroup>
<competition_ID>12813625</competition_ID>
<compName>17th Int. Stabhochsprung Meeting, TSG Jockgrim Stadion</compName>
<date>2011-07-27</date>
<venue>Jockgrim</venue>
<venueCountry>GER</venueCountry>
</record>
<record>
<IndoorOutdoor>Outdoor</IndoorOutdoor>
<event>PV</event>
<result>5.50</result>
<wind></wind>
<rank>2</rank>
<round></round>
<roundstage>Final</roundstage>
<agegroup></agegroup>
<competition_ID>12813632</competition_ID>
<compName>LG-Hof 16th Internationales Hofer Commerzbank-Stabhochsprung-Meeting</compName>
<date>2011-07-30</date>
<venue>Hof</venue>
<venueCountry>GER</venueCountry>
</record>
<record>
<IndoorOutdoor>Outdoor</IndoorOutdoor>
<event>PV</event>
<result>5.72</result>
<wind></wind>
<rank>2</rank>
<round></round>
<roundstage>Final</roundstage>
<agegroup></agegroup>
<competition_ID>12813650</competition_ID>
<compName>Int. Stabhochsprung-Meeting Obertorplatz</compName>
<date>2011-08-02</date>
<venue>Landau</venue>
<venueCountry>GER</venueCountry>
</record>
<record>
<IndoorOutdoor>Outdoor</IndoorOutdoor>
<event>PV</event>
<result>5.30</result>
<wind></wind>
<rank>3</rank>
<round></round>
<roundstage>Final</roundstage>
<agegroup></agegroup>
<competition_ID>12813843</competition_ID>
<compName>Meeting International du CASchifflange, Stade Jean Jacoby</compName>
<date>2011-08-07</date>
<venue>Schifflange</venue>
<venueCountry>LUX</venueCountry>
</record>
<record>
<IndoorOutdoor>Outdoor</IndoorOutdoor>
<event>PV</event>
<result>5.72</result>
<wind></wind>
<rank>2</rank>
<round></round>
<roundstage>Final</roundstage>
<agegroup></agegroup>
<competition_ID>12813847</competition_ID>
<compName></compName>
<date>2011-08-13</date>
<venue>Mannheim</venue>
<venueCountry>GER</venueCountry>
</record>
<record>
<IndoorOutdoor>Outdoor</IndoorOutdoor>
<event>PV</event>
<result>5.35</result>
<wind></wind>
<rank>24=</rank>
<round>q</round>
<roundstage>Prelim</roundstage>
<agegroup></agegroup>
<competition_ID>12814135</competition_ID>
<compName></compName>
<date>2011-08-27</date>
<venue>Daegu</venue>
<venueCountry>KOR</venueCountry>
</record>
<record>
<IndoorOutdoor>Indoor</IndoorOutdoor>
<event>PV</event>
<result>5.72</result>
<wind></wind>
<rank>1</rank>
<round></round>
<roundstage>Final</roundstage>
<agegroup></agegroup>
<competition_ID>12818763</competition_ID>
<compName>Nordrhein Hallenmeisterschaften</compName>
<date>2012-01-14</date>
<venue>Leverkusen</venue>
<venueCountry>GER</venueCountry>
</record>
<record>
<IndoorOutdoor>Indoor</IndoorOutdoor>
<event>PV</event>
<result>5.60</result>
<wind></wind>
<rank>3</rank>
<round></round>
<roundstage>Final</roundstage>
<agegroup></agegroup>
<competition_ID>12819424</competition_ID>
<compName>Springer-Meeting</compName>
<date>2012-01-25</date>
<venue>Cottbus</venue>
<venueCountry>GER</venueCountry>
</record>
<record>
<IndoorOutdoor>Indoor</IndoorOutdoor>
<event>PV</event>
<result>5.72</result>
<wind></wind>
<rank>1</rank>
<round></round>
<roundstage>Final</roundstage>
<agegroup></agegroup>
<competition_ID>12819592</competition_ID>
<compName>Aviva International (GBR v GER v RUS v Commonwealth v USA), Kelvin Hall</compName>
<date>2012-01-28</date>
<venue>Glasgow</venue>
<venueCountry>GBR</venueCountry>
</record>
<record>
<IndoorOutdoor>Indoor</IndoorOutdoor>
<event>PV</event>
<result>5.60</result>
<wind></wind>
<rank>4</rank>
<round></round>
<roundstage>Final</roundstage>
<agegroup></agegroup>
<competition_ID>12820165</competition_ID>
<compName></compName>
<date>2012-02-08</date>
<venue>Bydgoszcz</venue>
<venueCountry>POL</venueCountry>
</record>
<record>
<IndoorOutdoor>Indoor</IndoorOutdoor>
<event>PV</event>
<result>5.52</result>
<wind></wind>
<rank>10</rank>
<round></round>
<roundstage>Final</roundstage>
<agegroup></agegroup>
<competition_ID>12820288</competition_ID>
<compName>Samsung Pole Vault Stars</compName>
<date>2012-02-11</date>
<venue>Donetsk</venue>
<venueCountry>UKR</venueCountry>
</record>
<record>
<IndoorOutdoor>Indoor</IndoorOutdoor>
<event>PV</event>
<result>5.62</result>
<wind></wind>
<rank>3</rank>
<round></round>
<roundstage>Final</roundstage>
<agegroup></agegroup>
<competition_ID>12820527</competition_ID>
<compName></compName>
<date>2012-02-18</date>
<venue>Potsdam</venue>
<venueCountry>GER</venueCountry>
</record>
<record>
<IndoorOutdoor>Indoor</IndoorOutdoor>
<event>PV</event>
<result>5.62</result>
<wind></wind>
<rank>4</rank>
<round></round>
<roundstage>Final</roundstage>
<agegroup></agegroup>
<competition_ID>12820783</competition_ID>
<compName></compName>
<date>2012-02-26</date>
<venue>Karlsruhe</venue>
<venueCountry>GER</venueCountry>
</record>
<record>
<IndoorOutdoor>Indoor</IndoorOutdoor>
<event>PV</event>
<result>5.73</result>
<wind></wind>
<rank>1</rank>
<round></round>
<roundstage>Final</roundstage>
<agegroup></agegroup>
<competition_ID>12820914</competition_ID>
<compName></compName>
<date>2012-03-03</date>
<venue>Bad Oeynhausen</venue>
<venueCountry>GER</venueCountry>
</record>
<record>
<IndoorOutdoor>Outdoor</IndoorOutdoor>
<event>PV</event>
<result>5.52</result>
<wind></wind>
<rank>3</rank>
<round></round>
<roundstage>Final</roundstage>
<agegroup></agegroup>
<competition_ID>12821846</competition_ID>
<compName>
ICE Breaker PV Challenge</compName>
<date>2012-04-05</date>
<venue>Chula Vista CA</venue>
<venueCountry>USA</venueCountry>
</record>
<record>
<IndoorOutdoor>Outdoor</IndoorOutdoor>
<event>PV</event>
<result>5.55</result>
<wind></wind>
<rank>1</rank>
<round></round>
<roundstage>Final</roundstage>
<agegroup></agegroup>
<competition_ID>12823036</competition_ID>
<compName></compName>
<date>2012-05-09</date>
<venue>Rieti</venue>
<venueCountry>ITA</venueCountry>
</record>
<record>
<IndoorOutdoor>Outdoor</IndoorOutdoor>
<event>PV</event>
<result>5.60</result>
<wind></wind>
<rank>1</rank>
<round></round>
<roundstage>Final</roundstage>
<agegroup></agegroup>
<competition_ID>12822973</competition_ID>
<compName>EM-Normwettkampf Stabhochsprung</compName>
<date>2012-05-19</date>
<venue>Soest</venue>
<venueCountry>GER</venueCountry>
</record>
<record>
<IndoorOutdoor>Outdoor</IndoorOutdoor>
<event>PV</event>
<result>5.72</result>
<wind></wind>
<rank>2</rank>
<round></round>
<roundstage>Final</roundstage>
<agegroup></agegroup>
<competition_ID>12823064</competition_ID>
<compName>Zlatá Tretra, Golden Spike, IAAF World Challenge</compName>
<date>2012-05-25</date>
<venue>Ostrava</venue>
<venueCountry>CZE</venueCountry>
</record>
<record>
<IndoorOutdoor>Outdoor</IndoorOutdoor>
<event>PV</event>
<result></result>
<wind></wind>
<rank></rank>
<round></round>
<roundstage>Final</roundstage>
<agegroup></agegroup>
<competition_ID>12823270</competition_ID>
<compName>48th Internationales Pfingstsportfest, Bungertstadion</compName>
<date>2012-05-28</date>
<venue>Rehlingen</venue>
<venueCountry>GER</venueCountry>
</record>
<record>
<IndoorOutdoor>Outdoor</IndoorOutdoor>
<event>PV</event>
<result>5.52</result>
<wind></wind>
<rank>5</rank>
<round></round>
<roundstage>Final</roundstage>
<agegroup></agegroup>
<competition_ID>12823507</competition_ID>
<compName></compName>
<date>2012-06-03</date>
<venue>Bydgoszcz</venue>
<venueCountry>POL</venueCountry>
</record>
<record>
<IndoorOutdoor>Outdoor</IndoorOutdoor>
<event>PV</event>
<result>5.42</result>
<wind></wind>
<rank>5</rank>
<round></round>
<roundstage>Final</roundstage>
<agegroup></agegroup>
<competition_ID>12823656</competition_ID>
<compName>Meeting Lille Métropole</compName>
<date>2012-06-09</date>
<venue>Villeneuve d'Ascq</venue>
<venueCountry>FRA</venueCountry>
</record>
<record>
<IndoorOutdoor>Outdoor</IndoorOutdoor>
<event>PV</event>
<result>5.72</result>
<wind></wind>
<rank>3</rank>
<round></round>
<roundstage>Final</roundstage>
<agegroup></agegroup>
<competition_ID>12823844</competition_ID>
<compName></compName>
<date>2012-06-17</date>
<venue>Wattenscheid</venue>
<venueCountry>GER</venueCountry>
</record>
<record>
<IndoorOutdoor>Outdoor</IndoorOutdoor>
<event>PV</event>
<result>5.53</result>
<wind></wind>
<rank>2</rank>
<round></round>
<roundstage>Final</roundstage>
<agegroup></agegroup>
<competition_ID>12824264</competition_ID>
<compName>MTV Meet-IN</compName>
<date>2012-06-22</date>
<venue>Ingolstadt</venue>
<venueCountry>GER</venueCountry>
</record>
<record>
<IndoorOutdoor>Outdoor</IndoorOutdoor>
<event>PV</event>
<result>5.60</result>
<wind></wind>
<rank>1</rank>
<round></round>
<roundstage>Final</roundstage>
<agegroup></agegroup>
<competition_ID>12824481</competition_ID>
<compName>5th Rottacher Springer-Meeting 2012</compName>
<date>2012-07-07</date>
<venue>Rottach-Egern</venue>
<venueCountry>GER</venueCountry>
</record>
<record>
<IndoorOutdoor>Outdoor</IndoorOutdoor>
<event>PV</event>
<result>5.40</result>
<wind></wind>
<rank>5</rank>
<round></round>
<roundstage>Final</roundstage>
<agegroup></agegroup>
<competition_ID>12824594</competition_ID>
<compName>Aviva London Grand Prix, Samsung Diamond League, Crystal Palace</compName>
<date>2012-07-13</date>
<venue>London</venue>
<venueCountry>GBR</venueCountry>
</record>
<record>
<IndoorOutdoor>Outdoor</IndoorOutdoor>
<event>PV</event>
<result>5.42</result>
<wind></wind>
<rank>8=</rank>
<round></round>
<roundstage>Final</roundstage>
<agegroup></agegroup>
<competition_ID>12824835</competition_ID>
<compName></compName>
<date>2012-07-21</date>
<venue>Szczecin</venue>
<venueCountry>POL</venueCountry>
</record>
<record>
<IndoorOutdoor>Outdoor</IndoorOutdoor>
<event>PV</event>
<result>5.61</result>
<wind></wind>
<rank>7</rank>
<round></round>
<roundstage>Final</roundstage>
<agegroup></agegroup>
<competition_ID>12824881</competition_ID>
<compName></compName>
<date>2012-07-25</date>
<venue>Jockgrim</venue>
<venueCountry>GER</venueCountry>
</record>
<record>
<IndoorOutdoor>Outdoor</IndoorOutdoor>
<event>PV</event>
<result>5.53</result>
<wind></wind>
<rank>3</rank>
<round></round>
<roundstage>Final</roundstage>
<agegroup></agegroup>
<competition_ID>12825281</competition_ID>
<compName></compName>
<date>2012-08-15</date>
<venue>Albi</venue>
<venueCountry>FRA</venueCountry>
</record>
<record>
<IndoorOutdoor>Outdoor</IndoorOutdoor>
<event>PV</event>
<result>5.61</result>
<wind></wind>
<rank>3</rank>
<round></round>
<roundstage>Final</roundstage>
<agegroup></agegroup>
<competition_ID>12825389</competition_ID>
<compName></compName>
<date>2012-08-25</date>
<venue>Leverkusen</venue>
<venueCountry>GER</venueCountry>
</record>
<record>
<IndoorOutdoor>Outdoor</IndoorOutdoor>
<event>PV</event>
<result></result>
<wind></wind>
<rank></rank>
<round></round>
<roundstage>Final</roundstage>
<agegroup></agegroup>
<competition_ID>12825468</competition_ID>
<compName>Weltklasse, Samsung Diamond League, Stadion Letzigrund (Shot Put Zürich Main Station)</compName>
<date>2012-08-30</date>
<venue>Zürich</venue>
<venueCountry>SUI</venueCountry>
</record>
<record>
<IndoorOutdoor>Outdoor</IndoorOutdoor>
<event>PV</event>
<result>5.58</result>
<wind></wind>
<rank>5</rank>
<round></round>
<roundstage>Final</roundstage>
<agegroup></agegroup>
<competition_ID>12825487</competition_ID>
<compName></compName>
<date>2012-09-02</date>
<venue>Berlin</venue>
<venueCountry>GER</venueCountry>
</record>
<record>
<IndoorOutdoor>Outdoor</IndoorOutdoor>
<event>PV</event>
<result>5.56</result>
<wind></wind>
<rank>2</rank>
<round></round>
<roundstage>Final</roundstage>
<agegroup></agegroup>
<competition_ID>12825577</competition_ID>
<compName>NetAachen Domspringen</compName>
<date>2012-09-05</date>
<venue>Aachen</venue>
<venueCountry>GER</venueCountry>
</record>
<record>
<IndoorOutdoor>Outdoor</IndoorOutdoor>
<event>PV</event>
<result>5.43</result>
<wind></wind>
<rank>3</rank>
<round></round>
<roundstage>Final</roundstage>
<agegroup></agegroup>
<competition_ID>12825768</competition_ID>
<compName></compName>
<date>2012-09-09</date>
<venue>Geislingen</venue>
<venueCountry>GER</venueCountry>
</record>
<record>
<IndoorOutdoor>Indoor</IndoorOutdoor>
<event>PV</event>
<result>5.35</result>
<wind></wind>
<rank>4</rank>
<round></round>
<roundstage>Final</roundstage>
<agegroup></agegroup>
<competition_ID>12827520</competition_ID>
<compName>Stabhochsprung-Hallenwettkampf</compName>
<date>2013-01-05</date>
<venue>Leverkusen</venue>
<venueCountry>GER</venueCountry>
</record>
<record>
<IndoorOutdoor>Indoor</IndoorOutdoor>
<event>PV</event>
<result>5.65</result>
<wind></wind>
<rank>1</rank>
<round></round>
<roundstage>Final</roundstage>
<agegroup></agegroup>
<competition_ID>12828043</competition_ID>
<compName>Nordrhein-Hallenmeisterschaften</compName>
<date>2013-01-19</date>
<venue>Leverkusen</venue>
<venueCountry>GER</venueCountry>
</record>
<record>
<IndoorOutdoor>Indoor</IndoorOutdoor>
<event>PV</event>
<result>5.60</result>
<wind></wind>
<rank>4</rank>
<round></round>
<roundstage>Final</roundstage>
<agegroup></agegroup>
<competition_ID>12838608</competition_ID>
<compName>11th Internationales Spring-Meeting</compName>
<date>2013-01-30</date>
<venue>Cottbus</venue>
<venueCountry>GER</venueCountry>
</record>
<record>
<IndoorOutdoor>Indoor</IndoorOutdoor>
<event>PV</event>
<result></result>
<wind></wind>
<rank></rank>
<round></round>
<roundstage>Final</roundstage>
<agegroup></agegroup>
<competition_ID>12838790</competition_ID>
<compName>Weltklasse in Karlsruhe, Internationales Hallen-Meeting, Europahalle</compName>
<date>2013-02-02</date>
<venue>Karlsruhe</venue>
<venueCountry>GER</venueCountry>
</record>
<record>
<IndoorOutdoor>Indoor</IndoorOutdoor>
<event>PV</event>
<result></result>
<wind></wind>
<rank></rank>
<round></round>
<roundstage>Final</roundstage>
<agegroup></agegroup>
<competition_ID>12839423</competition_ID>
<compName>National Indoor Championships, Deutsche Hallen-Meisterschaften, Helmut-Körnig-Halle</compName>
<date>2013-02-24</date>
<venue>Dortmund</venue>
<venueCountry>GER</venueCountry>
</record>
<record>
<IndoorOutdoor>Indoor</IndoorOutdoor>
<event>PV</event>
<result>5.60</result>
<wind></wind>
<rank>3</rank>
<round></round>
<roundstage>Final</roundstage>
<agegroup></agegroup>
<competition_ID>12841229</competition_ID>
<compName></compName>
<date>2013-05-05</date>
<venue>Düsseldorf</venue>
<venueCountry>GER</venueCountry>
</record>
<record>
<IndoorOutdoor>Outdoor</IndoorOutdoor>
<event>PV</event>
<result>5.30</result>
<wind></wind>
<rank>8</rank>
<round></round>
<roundstage>Final</roundstage>
<agegroup></agegroup>
<competition_ID>12841311</competition_ID>
<compName>IAAF Diamond League Meeting, Qatar Sports Club</compName>
<date>2013-05-10</date>
<venue>Doha</venue>
<venueCountry>QAT</venueCountry>
</record>
<record>
<IndoorOutdoor>Outdoor</IndoorOutdoor>
<event>PV</event>
<result></result>
<wind></wind>
<rank></rank>
<round></round>
<roundstage>Final</roundstage>
<agegroup></agegroup>
<competition_ID>12841640</competition_ID>
<compName>49th Internationales Pfingstsportfest, Bungertstadion</compName>
<date>2013-05-20</date>
<venue>Rehlingen</venue>
<venueCountry>GER</venueCountry>
</record>
<record>
<IndoorOutdoor>Outdoor</IndoorOutdoor>
<event>PV</event>
<result>5.25</result>
<wind></wind>
<rank>5</rank>
<round></round>
<roundstage>Final</roundstage>
<agegroup></agegroup>
<competition_ID>12854075</competition_ID>
<compName>BT Great CityGames</compName>
<date>2013-05-25</date>
<venue>Manchester</venue>
<venueCountry>GBR</venueCountry>
</record>
<record>
<IndoorOutdoor>Outdoor</IndoorOutdoor>
<event>PV</event>
<result></result>
<wind></wind>
<rank></rank>
<round></round>
<roundstage>Final</roundstage>
<agegroup></agegroup>
<competition_ID>12841903</competition_ID>
<compName>Anhalt, Paul-Greifzu-Stadion</compName>
<date>2013-05-31</date>
<venue>Dessau</venue>
<venueCountry>GER</venueCountry>
</record>
<record>
<IndoorOutdoor>Outdoor</IndoorOutdoor>
<event>PV</event>
<result>5.55</result>
<wind></wind>
<rank>1</rank>
<round></round>
<roundstage>Final</roundstage>
<agegroup></agegroup>
<competition_ID>12842018</competition_ID>
<compName>Jump and Fly Munich, Odeonsplatz</compName>
<date>2013-06-04</date>
<venue>München</venue>
<venueCountry>GER</venueCountry>
</record>
<record>
<IndoorOutdoor>Outdoor</IndoorOutdoor>
<event>PV</event>
<result>5.30</result>
<wind></wind>
<rank>4</rank>
<round></round>
<roundstage>Final</roundstage>
<agegroup></agegroup>
<competition_ID>12842129</competition_ID>
<compName>Fanny Blankers Koen Games, Fanny Blankers Koen Stadium</compName>
<date>2013-06-08</date>
<venue>Hengelo</venue>
<venueCountry>NED</venueCountry>
</record>
<record>
<IndoorOutdoor>Outdoor</IndoorOutdoor>
<event>PV</event>
<result></result>
<wind></wind>
<rank></rank>
<round></round>
<roundstage>Final</roundstage>
<agegroup></agegroup>
<competition_ID>12842167</competition_ID>
<compName></compName>
<date>2013-06-10</date>
<venue>Praha</venue>
<venueCountry>CZE</venueCountry>
</record>
<record>
<IndoorOutdoor>Outdoor</IndoorOutdoor>
<event>PV</event>
<result>5.40</result>
<wind></wind>
<rank>7</rank>
<round></round>
<roundstage>Final</roundstage>
<agegroup></agegroup>
<competition_ID>12842825</competition_ID>
<compName>Internationales Stabhochsprung Meeting</compName>
<date>2013-06-16</date>
<venue>Köln</venue>
<venueCountry>GER</venueCountry>
</record>
<record>
<IndoorOutdoor>Outdoor</IndoorOutdoor>
<event>PV</event>
<result>5.61</result>
<wind></wind>
<rank>2</rank>
<round></round>
<roundstage>Final</roundstage>
<agegroup></agegroup>
<competition_ID>12843061</competition_ID>
<compName>18th Int. Hofer Commerzbank Stabhochsprung-Meeting</compName>
<date>2013-06-22</date>
<venue>Hof</venue>
<venueCountry>GER</venueCountry>
</record>
<record>
<IndoorOutdoor>Outdoor</IndoorOutdoor>
<event>PV</event>
<result>5.60</result>
<wind></wind>
<rank>1</rank>
<round></round>
<roundstage>Final</roundstage>
<agegroup></agegroup>
<competition_ID>12843153</competition_ID>
<compName></compName>
<date>2013-06-26</date>
<venue>Leverkusen</venue>
<venueCountry>GER</venueCountry>
</record>
<record>
<IndoorOutdoor>Outdoor</IndoorOutdoor>
<event>PV</event>
<result>5.30</result>
<wind></wind>
<rank>7</rank>
<round></round>
<roundstage>Final</roundstage>
<agegroup></agegroup>
<competition_ID>12843348</competition_ID>
<compName></compName>
<date>2013-06-30</date>
<venue>Soest</venue>
<venueCountry>GER</venueCountry>
</record>
<record>
<IndoorOutdoor>Outdoor</IndoorOutdoor>
<event>PV</event>
<result>5.60</result>
<wind></wind>
<rank>1</rank>
<round></round>
<roundstage>Final</roundstage>
<agegroup></agegroup>
<competition_ID>12843339</competition_ID>
<compName>Meeting Stanislas</compName>
<date>2013-07-02</date>
<venue>Tomblaine</venue>
<venueCountry>FRA</venueCountry>
</record>
<record>
<IndoorOutdoor>Outdoor</IndoorOutdoor>
<event>PV</event>
<result>5.60</result>
<wind></wind>
<rank>4</rank>
<round></round>
<roundstage>Final</roundstage>
<agegroup></agegroup>
<competition_ID>12843442</competition_ID>
<compName></compName>
<date>2013-07-07</date>
<venue>Ulm</venue>
<venueCountry>GER</venueCountry>
</record>
<record>
<IndoorOutdoor>Outdoor</IndoorOutdoor>
<event>PV</event>
<result>5.45</result>
<wind></wind>
<rank>3</rank>
<round></round>
<roundstage>Final</roundstage>
<agegroup></agegroup>
<competition_ID>12843593</competition_ID>
<compName>Meeting International de la Province de Liége</compName>
<date>2013-07-10</date>
<venue>Naimette-Xhovémont</venue>
<venueCountry>BEL</venueCountry>
</record>
<record>
<IndoorOutdoor>Outdoor</IndoorOutdoor>
<event>PV</event>
<result>5.72</result>
<wind></wind>
<rank>1</rank>
<round></round>
<roundstage>Final</roundstage>
<agegroup></agegroup>
<competition_ID>12845544</competition_ID>
<compName></compName>
<date>2013-07-13</date>
<venue>Rottach-Egern</venue>
<venueCountry>GER</venueCountry>
</record>
<record>
<IndoorOutdoor>Outdoor</IndoorOutdoor>
<event>PV</event>
<result>5.30</result>
<wind></wind>
<rank>4</rank>
<round></round>
<roundstage>Final</roundstage>
<agegroup></agegroup>
<competition_ID>12843823</competition_ID>
<compName></compName>
<date>2013-07-23</date>
<venue>Jockgrim</venue>
<venueCountry>GER</venueCountry>
</record>
<record>
<IndoorOutdoor>Outdoor</IndoorOutdoor>
<event>PV</event>
<result>5.60</result>
<wind></wind>
<rank>1</rank>
<round></round>
<roundstage>Final</roundstage>
<agegroup></agegroup>
<competition_ID>12844289</competition_ID>
<compName></compName>
<date>2013-08-15</date>
<venue>Szczecin</venue>
<venueCountry>POL</venueCountry>
</record>
<record>
<IndoorOutdoor>Outdoor</IndoorOutdoor>
<event>PV</event>
<result></result>
<wind></wind>
<rank></rank>
<round></round>
<roundstage>Final</roundstage>
<agegroup></agegroup>
<competition_ID>12844349</competition_ID>
<compName>Gugl Games</compName>
<date>2013-08-26</date>
<venue>Linz</venue>
<venueCountry>AUT</venueCountry>
</record>
<record>
<IndoorOutdoor>Outdoor</IndoorOutdoor>
<event>PV</event>
<result>5.60</result>
<wind></wind>
<rank>5</rank>
<round></round>
<roundstage>Final</roundstage>
<agegroup></agegroup>
<competition_ID>12844365</competition_ID>
<compName>Stabhochsprung-Classics</compName>
<date>2013-08-29</date>
<venue>Leverkusen</venue>
<venueCountry>GER</venueCountry>
</record>
<record>
<IndoorOutdoor>Outdoor</IndoorOutdoor>
<event>PV</event>
<result></result>
<wind></wind>
<rank></rank>
<round></round>
<roundstage>Final</roundstage>
<agegroup></agegroup>
<competition_ID>12844381</competition_ID>
<compName>72nd ISTAF, Olympic Stadium</compName>
<date>2013-09-01</date>
<venue>Berlin</venue>
<venueCountry>GER</venueCountry>
</record>
<record>
<IndoorOutdoor>Outdoor</IndoorOutdoor>
<event>PV</event>
<result>5.63</result>
<wind></wind>
<rank>3</rank>
<round></round>
<roundstage>Final</roundstage>
<agegroup></agegroup>
<competition_ID>12844467</competition_ID>
<compName>Domspring</compName>
<date>2013-09-04</date>
<venue>Aachen</venue>
<venueCountry>GER</venueCountry>
</record>
<record>
<IndoorOutdoor>Outdoor</IndoorOutdoor>
<event>PV</event>
<result>5.50</result>
<wind></wind>
<rank>6</rank>
<round></round>
<roundstage>Final</roundstage>
<agegroup></agegroup>
<competition_ID>12844463</competition_ID>
<compName>Van Damme Memorial, IAAF Diamond League, King Baudoin Stadium</compName>
<date>2013-09-06</date>
<venue>Bruxelles</venue>
<venueCountry>BEL</venueCountry>
</record>
<record>
<IndoorOutdoor>Outdoor</IndoorOutdoor>
<event>PV</event>
<result>5.53</result>
<wind></wind>
<rank>1</rank>
<round></round>
<roundstage>Final</roundstage>
<agegroup></agegroup>
<competition_ID>12846590</competition_ID>
<compName></compName>
<date>2013-09-07</date>
<venue>Geislingen</venue>
<venueCountry>GER</venueCountry>
</record>
<record>
<IndoorOutdoor>Outdoor</IndoorOutdoor>
<event>PV</event>
<result>5.30</result>
<wind></wind>
<rank>4</rank>
<round></round>
<roundstage>Final</roundstage>
<agegroup></agegroup>
<competition_ID>12844525</competition_ID>
<compName>1st Open Integrative CISM European Championships</compName>
<date>2013-09-12</date>
<venue>Warendorf</venue>
<venueCountry>GER</venueCountry>
</record>
<record>
<IndoorOutdoor>Indoor</IndoorOutdoor>
<event>PV</event>
<result>5.55</result>
<wind></wind>
<rank>2</rank>
<round></round>
<roundstage>Final</roundstage>
<agegroup></agegroup>
<competition_ID>12845891</competition_ID>
<compName></compName>
<date>2014-01-05</date>
<venue>Leverkusen</venue>
<venueCountry>GER</venueCountry>
</record>
<record>
<IndoorOutdoor>Indoor</IndoorOutdoor>
<event>PV</event>
<result>5.45</result>
<wind></wind>
<rank>1</rank>
<round></round>
<roundstage>Final</roundstage>
<agegroup></agegroup>
<competition_ID>12847026</competition_ID>
<compName>Nordrhein-Hallenmeisterschaften mit Winterwurf</compName>
<date>2014-01-18</date>
<venue>Leverkusen</venue>
<venueCountry>GER</venueCountry>
</record>
<record>
<IndoorOutdoor>Indoor</IndoorOutdoor>
<event>PV</event>
<result>5.30</result>
<wind></wind>
<rank>8=</rank>
<round></round>
<roundstage>Final</roundstage>
<agegroup></agegroup>
<competition_ID>12847150</competition_ID>
<compName>Springermeeting</compName>
<date>2014-01-22</date>
<venue>Cottbus</venue>
<venueCountry>GER</venueCountry>
</record>
<record>
<IndoorOutdoor>Indoor</IndoorOutdoor>
<event>PV</event>
<result>5.55</result>
<wind></wind>
<rank>3</rank>
<round></round>
<roundstage>Final</roundstage>
<agegroup></agegroup>
<competition_ID>12847449</competition_ID>
<compName>9th PSD Bank Meeting</compName>
<date>2014-01-30</date>
<venue>Düsseldorf</venue>
<venueCountry>GER</venueCountry>
</record>
<record>
<IndoorOutdoor>Indoor</IndoorOutdoor>
<event>PV</event>
<result>5.65</result>
<wind></wind>
<rank>3</rank>
<round></round>
<roundstage>Final</roundstage>
<agegroup></agegroup>
<competition_ID>12847494</competition_ID>
<compName>Indoor Meeting Weltklasse Karlsruhe, Europahalle</compName>
<date>2014-02-01</date>
<venue>Karlsruhe</venue>
<venueCountry>GER</venueCountry>
</record>
<record>
<IndoorOutdoor>Indoor</IndoorOutdoor>
<event>PV</event>
<result>5.61</result>
<wind></wind>
<rank>1</rank>
<round></round>
<roundstage>Final</roundstage>
<agegroup></agegroup>
<competition_ID>12847820</competition_ID>
<compName>Hallenstürmer-Cup</compName>
<date>2014-02-07</date>
<venue>Zweibrücken</venue>
<venueCountry>GER</venueCountry>
</record>
<record>
<IndoorOutdoor>Indoor</IndoorOutdoor>
<event>PV</event>
<result>5.65</result>
<wind></wind>
<rank>2</rank>
<round></round>
<roundstage>Final</roundstage>
<agegroup></agegroup>
<competition_ID>12847990</competition_ID>
<compName></compName>
<date>2014-02-15</date>
<venue>Potsdam</venue>
<venueCountry>GER</venueCountry>
</record>
<record>
<IndoorOutdoor>Indoor</IndoorOutdoor>
<event>PV</event>
<result>5.40</result>
<wind></wind>
<rank>4</rank>
<round></round>
<roundstage>Final</roundstage>
<agegroup></agegroup>
<competition_ID>12848231</competition_ID>
<compName></compName>
<date>2014-02-23</date>
<venue>Leipzig</venue>
<venueCountry>GER</venueCountry>
</record>
<record>
<IndoorOutdoor>Indoor</IndoorOutdoor>
<event>PV</event>
<result>5.51</result>
<wind></wind>
<rank>5</rank>
<round></round>
<roundstage>Final</roundstage>
<agegroup></agegroup>
<competition_ID>12848331</competition_ID>
<compName>13th Internationales Springmeeting, Anhalt Arena</compName>
<date>2014-02-27</date>
<venue>Dessau</venue>
<venueCountry>GER</venueCountry>
</record>
<record>
<IndoorOutdoor>Indoor</IndoorOutdoor>
<event>PV</event>
<result>5.40</result>
<wind></wind>
<rank>7</rank>
<round></round>
<roundstage>Final</roundstage>
<agegroup></agegroup>
<competition_ID>12848351</competition_ID>
<compName>ISTAF Indoor, O2 World</compName>
<date>2014-03-01</date>
<venue>Berlin</venue>
<venueCountry>GER</venueCountry>
</record>
<record>
<IndoorOutdoor>Outdoor</IndoorOutdoor>
<event>PV</event>
<result>5.70</result>
<wind></wind>
<rank>1</rank>
<round></round>
<roundstage>Final</roundstage>
<agegroup></agegroup>
<competition_ID>12850080</competition_ID>
<compName>OTC Pole Vault Invitational</compName>
<date>2014-05-09</date>
<venue>Chula Vista CA</venue>
<venueCountry>USA</venueCountry>
</record>
<record>
<IndoorOutdoor>Outdoor</IndoorOutdoor>
<event>PV</event>
<result>5.32</result>
<wind></wind>
<rank>9</rank>
<round></round>
<roundstage>Final</roundstage>
<agegroup></agegroup>
<competition_ID>12850236</competition_ID>
<compName>Golden Grand Prix, IAAF Diamond League</compName>
<date>2014-05-18</date>
<venue>Shanghai</venue>
<venueCountry>CHN</venueCountry>
</record>
<record>
<IndoorOutdoor>Outdoor</IndoorOutdoor>
<event>PV</event>
<result>5.30</result>
<wind></wind>
<rank>5=</rank>
<round></round>
<roundstage>Final</roundstage>
<agegroup></agegroup>
<competition_ID>12850730</competition_ID>
<compName></compName>
<date>2014-05-21</date>
<venue>Beijing</venue>
<venueCountry>CHN</venueCountry>
</record>
<record>
<IndoorOutdoor>Outdoor</IndoorOutdoor>
<event>PV</event>
<result>5.30</result>
<wind></wind>
<rank>7</rank>
<round></round>
<roundstage>Final</roundstage>
<agegroup></agegroup>
<competition_ID>12851496</competition_ID>
<compName>14th Europejski Festiwal Lekkoatletyczny, European Athletics Festival</compName>
<date>2014-06-02</date>
<venue>Bydgoszcz</venue>
<venueCountry>POL</venueCountry>
</record>
<record>
<IndoorOutdoor>Outdoor</IndoorOutdoor>
<event>PV</event>
<result>5.45</result>
<wind></wind>
<rank>5</rank>
<round></round>
<roundstage>Final</roundstage>
<agegroup></agegroup>
<competition_ID>12851686</competition_ID>
<compName>AA-Drink Fanny Blankers-Koen Games, IAAF World Challenge</compName>
<date>2014-06-08</date>
<venue>Hengelo</venue>
<venueCountry>NED</venueCountry>
</record>
<record>
<IndoorOutdoor>Outdoor</IndoorOutdoor>
<event>PV</event>
<result></result>
<wind></wind>
<rank></rank>
<round></round>
<roundstage>Final</roundstage>
<agegroup></agegroup>
<competition_ID>12851986</competition_ID>
<compName>Göteborg GP, Slottskogavallen</compName>
<date>2014-06-14</date>
<venue>Göteborg</venue>
<venueCountry>SWE</venueCountry>
</record>
<record>
<IndoorOutdoor>Outdoor</IndoorOutdoor>
<event>PV</event>
<result>5.65</result>
<wind></wind>
<rank>1</rank>
<round></round>
<roundstage>Final</roundstage>
<agegroup></agegroup>
<competition_ID>12852280</competition_ID>
<compName>Meet-IN</compName>
<date>2014-06-19</date>
<venue>Ingolstadt</venue>
<venueCountry>GER</venueCountry>
</record>
<record>
<IndoorOutdoor>Outdoor</IndoorOutdoor>
<event>PV</event>
<result>5.71</result>
<wind></wind>
<rank>1</rank>
<round></round>
<roundstage>Final</roundstage>
<agegroup></agegroup>
<competition_ID>12852385</competition_ID>
<compName>19th Internationales Hofer Commerzbank Stabhochsprung-Meeting</compName>
<date>2014-06-21</date>
<venue>Hof</venue>
<venueCountry>GER</venueCountry>
</record>
<record>
<IndoorOutdoor>Outdoor</IndoorOutdoor>
<event>PV</event>
<result>5.47</result>
<wind></wind>
<rank>7</rank>
<round></round>
<roundstage>Final</roundstage>
<agegroup></agegroup>
<competition_ID>12852602</competition_ID>
<compName></compName>
<date>2014-07-03</date>
<venue>Lausanne</venue>
<venueCountry>SUI</venueCountry>
</record>
<record>
<IndoorOutdoor>Outdoor</IndoorOutdoor>
<event>PV</event>
<result>5.70</result>
<wind></wind>
<rank>1</rank>
<round></round>
<roundstage>Final</roundstage>
<agegroup></agegroup>
<competition_ID>12852778</competition_ID>
<compName></compName>
<date>2014-07-05</date>
<venue>Rottach-Egern</venue>
<venueCountry>GER</venueCountry>
</record>
<record>
<IndoorOutdoor>Outdoor</IndoorOutdoor>
<event>PV</event>
<result>5.65</result>
<wind></wind>
<rank>2</rank>
<round></round>
<roundstage>Final</roundstage>
<agegroup></agegroup>
<competition_ID>12853093</competition_ID>
<compName></compName>
<date>2014-07-14</date>
<venue>Linz</venue>
<venueCountry>AUT</venueCountry>
</record>
<record>
<IndoorOutdoor>Outdoor</IndoorOutdoor>
<event>PV</event>
<result></result>
<wind></wind>
<rank></rank>
<round></round>
<roundstage>Final</roundstage>
<agegroup></agegroup>
<competition_ID>12853225</competition_ID>
<compName>Anniversary Games, Horse Guard Parade</compName>
<date>2014-07-20</date>
<venue>London</venue>
<venueCountry>GBR</venueCountry>
</record>
<record>
<IndoorOutdoor>Outdoor</IndoorOutdoor>
<event>PV</event>
<result></result>
<wind></wind>
<rank></rank>
<round></round>
<roundstage>Final</roundstage>
<agegroup></agegroup>
<competition_ID>12853393</competition_ID>
<compName></compName>
<date>2014-07-27</date>
<venue>Ulm</venue>
<venueCountry>GER</venueCountry>
</record>
<record>
<IndoorOutdoor>Outdoor</IndoorOutdoor>
<event>PV</event>
<result>5.40</result>
<wind></wind>
<rank>3</rank>
<round></round>
<roundstage>Final</roundstage>
<agegroup></agegroup>
<competition_ID>12853495</competition_ID>
<compName>
19th Internationales Stabhochsprung Meeting, TSG Jockgrim Stadion</compName>
<date>2014-07-31</date>
<venue>Jockgrim</venue>
<venueCountry>GER</venueCountry>
</record>
<record>
<IndoorOutdoor>Outdoor</IndoorOutdoor>
<event>PV</event>
<result>5.50</result>
<wind></wind>
<rank>7</rank>
<round>q</round>
<roundstage>Prelim</roundstage>
<agegroup></agegroup>
<competition_ID>12853650</competition_ID>
<compName>22nd European Athletics Championships, Letzigrund Stadium</compName>
<date>2014-08-14</date>
<venue>Zürich</venue>
<venueCountry>SUI</venueCountry>
</record>
<record>
<IndoorOutdoor>Outdoor</IndoorOutdoor>
<event>PV</event>
<result>5.40</result>
<wind></wind>
<rank>9</rank>
<round></round>
<roundstage>Final</roundstage>
<agegroup></agegroup>
<competition_ID>12853650</competition_ID>
<compName>22nd European Athletics Championships, Letzigrund Stadium</compName>
<date>2014-08-16</date>
<venue>Zürich</venue>
<venueCountry>SUI</venueCountry>
</record>
<record>
<IndoorOutdoor>Outdoor</IndoorOutdoor>
<event>PV</event>
<result>5.52</result>
<wind></wind>
<rank>5</rank>
<round></round>
<roundstage>Final</roundstage>
<agegroup></agegroup>
<competition_ID>12853730</competition_ID>
<compName>Internationales Stabhochsprung-Meeting, Obertorplatz</compName>
<date>2014-08-19</date>
<venue>Landau</venue>
<venueCountry>GER</venueCountry>
</record>
<record>
<IndoorOutdoor>Outdoor</IndoorOutdoor>
<event>PV</event>
<result>5.63</result>
<wind></wind>
<rank>2</rank>
<round></round>
<roundstage>Final</roundstage>
<agegroup></agegroup>
<competition_ID>12853783</competition_ID>
<compName>5th Toyota-Stabhochsprung-Classics</compName>
<date>2014-08-23</date>
<venue>Leverkusen</venue>
<venueCountry>GER</venueCountry>
</record>
<record>
<IndoorOutdoor>Outdoor</IndoorOutdoor>
<event>PV</event>
<result>5.50</result>
<wind></wind>
<rank>2</rank>
<round></round>
<roundstage>Final</roundstage>
<agegroup></agegroup>
<competition_ID>12853865</competition_ID>
<compName>Berlin fliegt!, Brandenburger Tor</compName>
<date>2014-08-30</date>
<venue>Berlin</venue>
<venueCountry>GER</venueCountry>
</record>
<record>
<IndoorOutdoor>Outdoor</IndoorOutdoor>
<event>PV</event>
<result>5.60</result>
<wind></wind>
<rank>5</rank>
<round></round>
<roundstage>Final</roundstage>
<agegroup></agegroup>
<competition_ID>12853976</competition_ID>
<compName>10th NetAachen Domspringen</compName>
<date>2014-09-03</date>
<venue>Aachen</venue>
<venueCountry>GER</venueCountry>
</record>
<record>
<IndoorOutdoor>Outdoor</IndoorOutdoor>
<event>PV</event>
<result>5.45</result>
<wind></wind>
<rank>11</rank>
<round></round>
<roundstage>Final</roundstage>
<agegroup></agegroup>
<competition_ID>12854005</competition_ID>
<compName>Van Damme Memorial, IAAF Diamond League, King Baudoin Stadium</compName>
<date>2014-09-05</date>
<venue>Bruxelles</venue>
<venueCountry>BEL</venueCountry>
</record>
<record>
<IndoorOutdoor>Indoor</IndoorOutdoor>
<event>PV</event>
<result>5.40</result>
<wind></wind>
<rank>1</rank>
<round></round>
<roundstage>Final</roundstage>
<agegroup></agegroup>
<competition_ID>12855562</competition_ID>
<compName>Neujahrsspringen</compName>
<date>2015-01-03</date>
<venue>Merzig</venue>
<venueCountry>GER</venueCountry>
</record>
<record>
<IndoorOutdoor>Indoor</IndoorOutdoor>
<event>PV</event>
<result>5.45</result>
<wind></wind>
<rank>1</rank>
<round></round>
<roundstage>Final</roundstage>
<agegroup></agegroup>
<competition_ID>12855758</competition_ID>
<compName>Season Opening Stabhochsprung</compName>
<date>2015-01-11</date>
<venue>Leverkusen</venue>
<venueCountry>GER</venueCountry>
</record>
<record>
<IndoorOutdoor>Indoor</IndoorOutdoor>
<event>PV</event>
<result></result>
<wind></wind>
<rank></rank>
<round></round>
<roundstage>Final</roundstage>
<agegroup></agegroup>
<competition_ID>12857061</competition_ID>
<compName>62nd National Indoor Championships, Deutsche Hallenmeisterschaften</compName>
<date>2015-02-22</date>
<venue>Karlsruhe</venue>
<venueCountry>GER</venueCountry>
</record>
<record>
<IndoorOutdoor>Indoor</IndoorOutdoor>
<event>PV</event>
<result>5.40</result>
<wind></wind>
<rank>6</rank>
<round></round>
<roundstage>Final</roundstage>
<agegroup></agegroup>
<competition_ID>12857262</competition_ID>
<compName></compName>
<date>2015-02-28</date>
<venue>Bad Oeynhausen</venue>
<venueCountry>GER</venueCountry>
</record>
<record>
<IndoorOutdoor>Outdoor</IndoorOutdoor>
<event>PV</event>
<result>5.35</result>
<wind></wind>
<rank>5</rank>
<round></round>
<roundstage>Final</roundstage>
<agegroup></agegroup>
<competition_ID>12859525</competition_ID>
<compName>106th Drake Relays, America's Athletic Classic, Drake Stadium, Jim Duncan Track</compName>
<date>2015-04-22</date>
<venue>Des Moines IA</venue>
<venueCountry>USA</venueCountry>
</record>
<record>
<IndoorOutdoor>Indoor</IndoorOutdoor>
<event>PV</event>
<result></result>
<wind></wind>
<rank></rank>
<round></round>
<roundstage>Final</roundstage>
<agegroup></agegroup>
<competition_ID>12859525</competition_ID>
<compName></compName>
<date>2015-04-25</date>
<venue>Des Moines IA</venue>
<venueCountry>USA</venueCountry>
</record>
<record>
<IndoorOutdoor>Outdoor</IndoorOutdoor>
<event>PV</event>
<result>5.41</result>
<wind></wind>
<rank>3</rank>
<round></round>
<roundstage>Final</roundstage>
<agegroup></agegroup>
<competition_ID>12859867</competition_ID>
<compName>Tennessee Challenge</compName>
<date>2015-05-02</date>
<venue>Knoxville TN</venue>
<venueCountry>USA</venueCountry>
</record>
<record>
<IndoorOutdoor>Outdoor</IndoorOutdoor>
<event>PV</event>
<result>5.34</result>
<wind></wind>
<rank>6</rank>
<round></round>
<roundstage>Final</roundstage>
<agegroup></agegroup>
<competition_ID>12860084</competition_ID>
<compName>3rd Athens Street Pole Vault, EA Special Premium Meeting</compName>
<date>2015-05-09</date>
<venue>Athína</venue>
<venueCountry>GRE</venueCountry>
</record>
<record>
<IndoorOutdoor>Outdoor</IndoorOutdoor>
<event>PV</event>
<result>5.40</result>
<wind></wind>
<rank>3</rank>
<round></round>
<roundstage>Final</roundstage>
<agegroup></agegroup>
<competition_ID>12860502</competition_ID>
<compName></compName>
<date>2015-05-20</date>
<venue>Beijing</venue>
<venueCountry>CHN</venueCountry>
</record>
<record>
<IndoorOutdoor>Outdoor</IndoorOutdoor>
<event>PV</event>
<result>5.20</result>
<wind></wind>
<rank>9</rank>
<round></round>
<roundstage>Final</roundstage>
<agegroup></agegroup>
<competition_ID>12860765</competition_ID>
<compName>National Team Championships</compName>
<date>2015-05-26</date>
<venue>Ostrava</venue>
<venueCountry>CZE</venueCountry>
</record>
<record>
<IndoorOutdoor>Outdoor</IndoorOutdoor>
<event>PV</event>
<result>5.50</result>
<wind></wind>
<rank>1</rank>
<round></round>
<roundstage>Final</roundstage>
<agegroup></agegroup>
<competition_ID>12861203</competition_ID>
<compName>Bayer Invitational Meeting, Manforter Stadion</compName>
<date>2015-06-05</date>
<venue>Leverkusen</venue>
<venueCountry>GER</venueCountry>
</record>
<record>
<IndoorOutdoor>Outdoor</IndoorOutdoor>
<event>PV</event>
<result>5.50</result>
<wind></wind>
<rank>5</rank>
<round></round>
<roundstage>Final</roundstage>
<agegroup></agegroup>
<competition_ID>12861395</competition_ID>
<compName>22nd Josef Odložil Memorial, Stadion Juliska</compName>
<date>2015-06-08</date>
<venue>Praha</venue>
<venueCountry>CZE</venueCountry>
</record>
<record>
<IndoorOutdoor>Outdoor</IndoorOutdoor>
<event>PV</event>
<result>5.60</result>
<wind></wind>
<rank>4</rank>
<round></round>
<roundstage>Final</roundstage>
<agegroup></agegroup>
<competition_ID>12861780</competition_ID>
<compName>Himmelsstürmer-Cup</compName>
<date>2015-06-14</date>
<venue>Zweibrücken</venue>
<venueCountry>GER</venueCountry>
</record>
<record>
<IndoorOutdoor>Outdoor</IndoorOutdoor>
<event>PV</event>
<result>5.41</result>
<wind></wind>
<rank>4</rank>
<round></round>
<roundstage>Final</roundstage>
<agegroup></agegroup>
<competition_ID>12861917</competition_ID>
<compName>20th Internationales Hofer Commerzbank Stabhochsprung</compName>
<date>2015-06-20</date>
<venue>Hof</venue>
<venueCountry>GER</venueCountry>
</record>
<record>
<IndoorOutdoor>Outdoor</IndoorOutdoor>
<event>PV</event>
<result>5.55</result>
<wind></wind>
<rank>4</rank>
<round></round>
<roundstage>Final</roundstage>
<agegroup></agegroup>
<competition_ID>12862029</competition_ID>
<compName>18th Internationales Stabhochsprung-Meeting, Obertorplatz</compName>
<date>2015-06-25</date>
<venue>Landau</venue>
<venueCountry>GER</venueCountry>
</record>
<record>
<IndoorOutdoor>Outdoor</IndoorOutdoor>
<event>PV</event>
<result>5.45</result>
<wind></wind>
<rank>5</rank>
<round></round>
<roundstage>Final</roundstage>
<agegroup></agegroup>
<competition_ID>12862555</competition_ID>
<compName>8th Tegernseer Tal Springermeeting, Kuranlage</compName>
<date>2015-07-10</date>
<venue>Rottach-Egern</venue>
<venueCountry>GER</venueCountry>
</record>
<record>
<IndoorOutdoor>Outdoor</IndoorOutdoor>
<event>PV</event>
<result>5.50</result>
<wind></wind>
<rank>4</rank>
<round></round>
<roundstage>Final</roundstage>
<agegroup></agegroup>
<competition_ID>12862616</competition_ID>
<compName>Meeting International d'Athlétisme de la Province de Liège</compName>
<date>2015-07-15</date>
<venue>Naimette-Xhovémont</venue>
<venueCountry>BEL</venueCountry>
</record>
<record>
<IndoorOutdoor>Outdoor</IndoorOutdoor>
<event>PV</event>
<result></result>
<wind></wind>
<rank></rank>
<round></round>
<roundstage>Final</roundstage>
<agegroup></agegroup>
<competition_ID>12862871</competition_ID>
<compName>115th Deutsche Meisterschaften, Grundig Stadion</compName>
<date>2015-07-26</date>
<venue>Nürnberg</venue>
<venueCountry>GER</venueCountry>
</record>
<record>
<IndoorOutdoor>Outdoor</IndoorOutdoor>
<event>PV</event>
<result>5.53</result>
<wind></wind>
<rank>4</rank>
<round></round>
<roundstage>Final</roundstage>
<agegroup></agegroup>
<competition_ID>12863342</competition_ID>
<compName>6th Stabhochsprung-Classics</compName>
<date>2015-08-07</date>
<venue>Leverkusen</venue>
<venueCountry>GER</venueCountry>
</record>
<record>
<IndoorOutdoor>Outdoor</IndoorOutdoor>
<event>PV</event>
<result>5.40</result>
<wind></wind>
<rank>2</rank>
<round></round>
<roundstage>Final</roundstage>
<agegroup></agegroup>
<competition_ID>12863585</competition_ID>
<compName>Wladyslaw Komar &amp; Tadeusz Ślusarski Memorial</compName>
<date>2015-08-17</date>
<venue>Międzyzdroje</venue>
<venueCountry>POL</venueCountry>
</record>
<record>
<IndoorOutdoor>Outdoor</IndoorOutdoor>
<event>PV</event>
<result></result>
<wind></wind>
<rank></rank>
<round></round>
<roundstage>Final</roundstage>
<agegroup></agegroup>
<competition_ID>12863898</competition_ID>
<compName>51st Palio Città della Quercia</compName>
<date>2015-09-08</date>
<venue>Rovereto</venue>
<venueCountry>ITA</venueCountry>
</record>
<record>
<IndoorOutdoor>Indoor</IndoorOutdoor>
<event>PV</event>
<result>5.35</result>
<wind></wind>
<rank>7</rank>
<round></round>
<roundstage>Final</roundstage>
<agegroup></agegroup>
<competition_ID>12869444</competition_ID>
<compName>11PSD-Bankth PSD Bank Meeting, Leichtathletikhalle im Arena Sportpark</compName>
<date>2016-02-03</date>
<venue>Düsseldorf</venue>
<venueCountry>GER</venueCountry>
</record>
<record>
<IndoorOutdoor>Indoor</IndoorOutdoor>
<event>PV</event>
<result>5.32</result>
<wind></wind>
<rank>12</rank>
<round></round>
<roundstage>Final</roundstage>
<agegroup></agegroup>
<competition_ID>12869537</competition_ID>
<compName></compName>
<date>2016-02-06</date>
<venue>Potsdam</venue>
<venueCountry>GER</venueCountry>
</record>
<record>
<IndoorOutdoor>Indoor</IndoorOutdoor>
<event>PV</event>
<result></result>
<wind></wind>
<rank></rank>
<round></round>
<roundstage>Final</roundstage>
<agegroup></agegroup>
<competition_ID>12869799</competition_ID>
<compName>2nd International Copernicus Meeting - Toruń Cup</compName>
<date>2016-02-12</date>
<venue>Toruń</venue>
<venueCountry>POL</venueCountry>
</record>
<record>
<IndoorOutdoor>Indoor</IndoorOutdoor>
<event>PV</event>
<result>5.50</result>
<wind></wind>
<rank>3</rank>
<round></round>
<roundstage>Final</roundstage>
<agegroup></agegroup>
<competition_ID>12870091</competition_ID>
<compName>18th Internationales Erdgas-Hallenmeeting, Sportforum</compName>
<date>2016-02-20</date>
<venue>Chemnitz</venue>
<venueCountry>GER</venueCountry>
</record>
<record>
<IndoorOutdoor>Indoor</IndoorOutdoor>
<event>PV</event>
<result>5.30</result>
<wind></wind>
<rank>6</rank>
<round></round>
<roundstage>Final</roundstage>
<agegroup></agegroup>
<competition_ID>12870340</competition_ID>
<compName></compName>
<date>2016-02-28</date>
<venue>Leipzig</venue>
<venueCountry>GER</venueCountry>
</record>
<record>
<IndoorOutdoor>Outdoor</IndoorOutdoor>
<event>PV</event>
<result>5.45</result>
<wind></wind>
<rank>1</rank>
<round></round>
<roundstage>Final</roundstage>
<agegroup></agegroup>
<competition_ID>12872741</competition_ID>
<compName></compName>
<date>2016-04-29</date>
<venue>Antalya</venue>
<venueCountry>TUR</venueCountry>
</record>
<record>
<IndoorOutdoor>Outdoor</IndoorOutdoor>
<event>PV</event>
<result></result>
<wind></wind>
<rank></rank>
<round></round>
<roundstage>Final</roundstage>
<agegroup></agegroup>
<competition_ID>12873000</competition_ID>
<compName>31st Bönnigheimer Sportfest an Himmelfahrt</compName>
<date>2016-05-05</date>
<venue>Bönnigheim</venue>
<venueCountry>GER</venueCountry>
</record>
<record>
<IndoorOutdoor>Outdoor</IndoorOutdoor>
<event>PV</event>
<result></result>
<wind></wind>
<rank></rank>
<round></round>
<roundstage>Final</roundstage>
<agegroup></agegroup>
<competition_ID>12873153</competition_ID>
<compName>7th Engener Stabhochsprungmeeting, Hegaustadion</compName>
<date>2016-05-08</date>
<venue>Engen</venue>
<venueCountry>GER</venueCountry>
</record>
<record>
<IndoorOutdoor>Outdoor</IndoorOutdoor>
<event>PV</event>
<result></result>
<wind></wind>
<rank></rank>
<round></round>
<roundstage>Final</roundstage>
<agegroup></agegroup>
<competition_ID>12873463</competition_ID>
<compName>52nd Internationales Pfingstsportfest</compName>
<date>2016-05-16</date>
<venue>Rehlingen</venue>
<venueCountry>GER</venueCountry>
</record>
<record>
<IndoorOutdoor>Outdoor</IndoorOutdoor>
<event>PV</event>
<result>5.40</result>
<wind></wind>
<rank>5</rank>
<round></round>
<roundstage>Final</roundstage>
<agegroup></agegroup>
<competition_ID>12873934</competition_ID>
<compName>Anhalt 2016, 18th Internationales Leichtathletik Meeting, Paul-Greifzu-Stadion</compName>
<date>2016-05-27</date>
<venue>Dessau</venue>
<venueCountry>GER</venueCountry>
</record>
<record>
<IndoorOutdoor>Outdoor</IndoorOutdoor>
<event>PV</event>
<result>5.50</result>
<wind></wind>
<rank>1</rank>
<round></round>
<roundstage>Final</roundstage>
<agegroup></agegroup>
<competition_ID>12874010</competition_ID>
<compName>Internationales Lauf- und Sprungmeeting</compName>
<date>2016-05-29</date>
<venue>Rechberghausen</venue>
<venueCountry>GER</venueCountry>
</record>
<record>
<IndoorOutdoor>Outdoor</IndoorOutdoor>
<event>PV</event>
<result>5.60</result>
<wind></wind>
<rank>2</rank>
<round></round>
<roundstage>Final</roundstage>
<agegroup></agegroup>
<competition_ID>12874884</competition_ID>
<compName>16th European Athletic Festival</compName>
<date>2016-06-04</date>
<venue>Bydgoszcz</venue>
<venueCountry>POL</venueCountry>
</record>
<record>
<IndoorOutdoor>Outdoor</IndoorOutdoor>
<event>PV</event>
<result>5.35</result>
<wind></wind>
<rank>5</rank>
<round></round>
<roundstage>Final</roundstage>
<agegroup></agegroup>
<competition_ID>12875314</competition_ID>
<compName>Himmelsstürmer-Cup</compName>
<date>2016-06-12</date>
<venue>Zweibrücken</venue>
<venueCountry>GER</venueCountry>
</record>
<record>
<IndoorOutdoor>Outdoor</IndoorOutdoor>
<event>PV</event>
<result>5.65</result>
<wind></wind>
<rank>2</rank>
<round></round>
<roundstage>Final</roundstage>
<agegroup></agegroup>
<competition_ID>12875741</competition_ID>
<compName></compName>
<date>2016-06-19</date>
<venue>Kassel</venue>
<venueCountry>GER</venueCountry>
</record>
<record>
<IndoorOutdoor>Outdoor</IndoorOutdoor>
<event>PV</event>
<result>5.40</result>
<wind></wind>
<rank>6</rank>
<round></round>
<roundstage>Final</roundstage>
<agegroup></agegroup>
<competition_ID>12876010</competition_ID>
<compName>7th Stabhochsprung-Classics</compName>
<date>2016-06-24</date>
<venue>Leverkusen</venue>
<venueCountry>GER</venueCountry>
</record>
<record>
<IndoorOutdoor>Outdoor</IndoorOutdoor>
<event>PV</event>
<result>5.70</result>
<wind></wind>
<rank>2</rank>
<round></round>
<roundstage>Final</roundstage>
<agegroup></agegroup>
<competition_ID>12876092</competition_ID>
<compName>Stabhochsprung-Meeting</compName>
<date>2016-06-28</date>
<venue>Landau</venue>
<venueCountry>GER</venueCountry>
</record>
<record>
<IndoorOutdoor>Outdoor</IndoorOutdoor>
<event>PV</event>
<result>5.35</result>
<wind></wind>
<rank>12=</rank>
<round>q</round>
<roundstage>Prelim</roundstage>
<agegroup></agegroup>
<competition_ID>12876245</competition_ID>
<compName>23rd European Athletics Championships, Olympic Stadium</compName>
<date>2016-07-06</date>
<venue>Amsterdam</venue>
<venueCountry>NED</venueCountry>
</record>
<record>
<IndoorOutdoor>Outdoor</IndoorOutdoor>
<event>PV</event>
<result>5.30</result>
<wind></wind>
<rank>7</rank>
<round></round>
<roundstage>Final</roundstage>
<agegroup></agegroup>
<competition_ID>12876245</competition_ID>
<compName></compName>
<date>2016-07-08</date>
<venue>Amsterdam</venue>
<venueCountry>NED</venueCountry>
</record>
<record>
<IndoorOutdoor>Outdoor</IndoorOutdoor>
<event>PV</event>
<result>5.50</result>
<wind></wind>
<rank>10</rank>
<round></round>
<roundstage>Final</roundstage>
<agegroup></agegroup>
<competition_ID>12876723</competition_ID>
<compName>Stabhochsprung-Meeting</compName>
<date>2016-07-16</date>
<venue>Rottach-Egern</venue>
<venueCountry>GER</venueCountry>
</record>
<record>
<IndoorOutdoor>Outdoor</IndoorOutdoor>
<event>PV</event>
<result></result>
<wind></wind>
<rank></rank>
<round></round>
<roundstage>Final</roundstage>
<agegroup></agegroup>
<competition_ID>12877052</competition_ID>
<compName>DLV-Olympiaverabschiedung</compName>
<date>2016-07-29</date>
<venue>Mannheim</venue>
<venueCountry>GER</venueCountry>
</record>
<record>
<IndoorOutdoor>Outdoor</IndoorOutdoor>
<event>PV</event>
<result>5.30</result>
<wind></wind>
<rank>28=</rank>
<round>q</round>
<roundstage>Prelim</roundstage>
<agegroup></agegroup>
<competition_ID>12877460</competition_ID>
<compName></compName>
<date>2016-08-13</date>
<venue>Río de Janeiro</venue>
<venueCountry>BRA</venueCountry>
</record>
<record>
<IndoorOutdoor>Outdoor</IndoorOutdoor>
<event>PV</event>
<result></result>
<wind></wind>
<rank></rank>
<round></round>
<roundstage>Final</roundstage>
<agegroup></agegroup>
<competition_ID>12877563</competition_ID>
<compName>41st Athletissima, IAAF Diamond League</compName>
<date>2016-08-25</date>
<venue>Lausanne</venue>
<venueCountry>SUI</venueCountry>
</record>
<record>
<IndoorOutdoor>Outdoor</IndoorOutdoor>
<event>PV</event>
<result>5.20</result>
<wind></wind>
<rank>6</rank>
<round></round>
<roundstage>Final</roundstage>
<agegroup></agegroup>
<competition_ID>12877575</competition_ID>
<compName>4th Kamila Skolimowska Memorial</compName>
<date>2016-08-28</date>
<venue>Warszawa</venue>
<venueCountry>POL</venueCountry>
</record>
</athleteresulthistory>
</result>
</results>
