{
  "birthplace": "Palma de Mallorca", 
  "weight": "65", 
  "firstname": "David", 
  "club": "CD Nike Running", 
  "lastname": "Bustos", 
  "results": [
    {
      "competition_ID": "9410699", 
      "compName": null, 
      "roundstage": "Prelim", 
      "venue": "Thessalon\u00c3\u00adki", 
      "IndoorOutdoor": "Outdoor", 
      "agegroup": null, 
      "venueCountry": "GRE", 
      "rank": "3", 
      "event": "800", 
      "result": "1:52.24", 
      "date": "2006-06-30", 
      "round": "h2-17", 
      "wind": null
    }, 
    {
      "competition_ID": "9421057", 
      "compName": null, 
      "roundstage": "Final", 
      "venue": "Vilafranca", 
      "IndoorOutdoor": "Indoor", 
      "agegroup": null, 
      "venueCountry": "ESP", 
      "rank": "1", 
      "event": "800", 
      "result": "1:51.65", 
      "date": "2007-01-13", 
      "round": null, 
      "wind": null
    }, 
    {
      "competition_ID": "9647064", 
      "compName": null, 
      "roundstage": "Final", 
      "venue": "Vilafranca", 
      "IndoorOutdoor": "Indoor", 
      "agegroup": null, 
      "venueCountry": "ESP", 
      "rank": "1", 
      "event": "1500", 
      "result": "3:52.41", 
      "date": "2007-01-28", 
      "round": null, 
      "wind": null
    }, 
    {
      "competition_ID": "9750619", 
      "compName": null, 
      "roundstage": "Prelim", 
      "venue": "Sevilla", 
      "IndoorOutdoor": "Indoor", 
      "agegroup": null, 
      "venueCountry": "ESP", 
      "rank": "4", 
      "event": "800", 
      "result": "1:52.06", 
      "date": "2007-02-17", 
      "round": "h3", 
      "wind": null
    }, 
    {
      "competition_ID": "9914258", 
      "compName": null, 
      "roundstage": "Final", 
      "venue": "La Laguna", 
      "IndoorOutdoor": "Outdoor", 
      "agegroup": null, 
      "venueCountry": "ESP", 
      "rank": "7", 
      "event": "1500", 
      "result": "3:54.7h", 
      "date": "2007-05-05", 
      "round": null, 
      "wind": null
    }, 
    {
      "competition_ID": "9948663", 
      "compName": null, 
      "roundstage": "Final", 
      "venue": "Herrera", 
      "IndoorOutdoor": "Outdoor", 
      "agegroup": null, 
      "venueCountry": "ESP", 
      "rank": "9", 
      "event": "800", 
      "result": "1:50.92", 
      "date": "2007-05-19", 
      "round": null, 
      "wind": null
    }, 
    {
      "competition_ID": "10190096", 
      "compName": null, 
      "roundstage": "Final", 
      "venue": "Palma de Mallorca", 
      "IndoorOutdoor": "Outdoor", 
      "agegroup": "Under 18", 
      "venueCountry": "ESP", 
      "rank": "1", 
      "event": "800", 
      "result": "1:51.51", 
      "date": "2007-06-03", 
      "round": "-17", 
      "wind": null
    }, 
    {
      "competition_ID": "10679039", 
      "compName": null, 
      "roundstage": "Final", 
      "venue": "Matar\u00c3\u00b3", 
      "IndoorOutdoor": "Outdoor", 
      "agegroup": null, 
      "venueCountry": "ESP", 
      "rank": "1", 
      "event": "1500", 
      "result": "3:46.66", 
      "date": "2007-06-12", 
      "round": null, 
      "wind": null
    }, 
    {
      "competition_ID": "10290642", 
      "compName": null, 
      "roundstage": "Prelim", 
      "venue": "Ostrava", 
      "IndoorOutdoor": "Outdoor", 
      "agegroup": null, 
      "venueCountry": "CZE", 
      "rank": "1", 
      "event": "1500", 
      "result": "3:51.63", 
      "date": "2007-07-13", 
      "round": "h3-17", 
      "wind": null
    }, 
    {
      "competition_ID": "10290642", 
      "compName": null, 
      "roundstage": "Final", 
      "venue": "Ostrava", 
      "IndoorOutdoor": "Outdoor", 
      "agegroup": "Under 18", 
      "venueCountry": "CZE", 
      "rank": "4", 
      "event": "1500", 
      "result": "3:46.73", 
      "date": "2007-07-15", 
      "round": "-17", 
      "wind": null
    }, 
    {
      "competition_ID": "10573352", 
      "compName": null, 
      "roundstage": "Prelim", 
      "venue": "Beograd", 
      "IndoorOutdoor": "Outdoor", 
      "agegroup": null, 
      "venueCountry": "SRB", 
      "rank": "1", 
      "event": "1500", 
      "result": "3:59.55", 
      "date": "2007-07-23", 
      "round": "h1-17", 
      "wind": null
    }, 
    {
      "competition_ID": "10573352", 
      "compName": null, 
      "roundstage": "Final", 
      "venue": "Beograd", 
      "IndoorOutdoor": "Outdoor", 
      "agegroup": "Under 18", 
      "venueCountry": "SRB", 
      "rank": "1", 
      "event": "1500", 
      "result": "3:53.24", 
      "date": "2007-07-25", 
      "round": "-17", 
      "wind": null
    }, 
    {
      "competition_ID": "10713277", 
      "compName": null, 
      "roundstage": "Final", 
      "venue": "Llodio", 
      "IndoorOutdoor": "Outdoor", 
      "agegroup": "Under 20", 
      "venueCountry": "ESP", 
      "rank": "13", 
      "event": "CC5.63", 
      "result": "19:06", 
      "date": "2007-11-18", 
      "round": "-19", 
      "wind": null
    }, 
    {
      "competition_ID": "11324448", 
      "compName": null, 
      "roundstage": "Final", 
      "venue": "Valencia", 
      "IndoorOutdoor": "Indoor", 
      "agegroup": null, 
      "venueCountry": "ESP", 
      "rank": "1", 
      "event": "1500", 
      "result": "3:49.14", 
      "date": "2008-01-12", 
      "round": null, 
      "wind": null
    }, 
    {
      "competition_ID": "11324438", 
      "compName": null, 
      "roundstage": "Final", 
      "venue": "Valencia", 
      "IndoorOutdoor": "Indoor", 
      "agegroup": null, 
      "venueCountry": "ESP", 
      "rank": "1", 
      "event": "800", 
      "result": "1:50.79", 
      "date": "2008-01-19", 
      "round": null, 
      "wind": null
    }, 
    {
      "competition_ID": "11347604", 
      "compName": null, 
      "roundstage": "Final", 
      "venue": "Zaragoza", 
      "IndoorOutdoor": "Indoor", 
      "agegroup": null, 
      "venueCountry": "ESP", 
      "rank": "6", 
      "event": "1500", 
      "result": "3:46.63", 
      "date": "2008-02-02", 
      "round": null, 
      "wind": null
    }, 
    {
      "competition_ID": "11377614", 
      "compName": null, 
      "roundstage": "Final", 
      "venue": "San Sebasti\u00c3\u00a1n", 
      "IndoorOutdoor": "Indoor", 
      "agegroup": "Under 20", 
      "venueCountry": "ESP", 
      "rank": "1", 
      "event": "1500", 
      "result": "4:06.05", 
      "date": "2008-02-10", 
      "round": "-19", 
      "wind": null
    }, 
    {
      "competition_ID": "11436711", 
      "compName": null, 
      "roundstage": "Prelim", 
      "venue": "Valencia", 
      "IndoorOutdoor": "Indoor", 
      "agegroup": null, 
      "venueCountry": "ESP", 
      "rank": "3", 
      "event": "800", 
      "result": "1:51.02", 
      "date": "2008-02-23", 
      "round": "h1", 
      "wind": null
    }, 
    {
      "competition_ID": "11436711", 
      "compName": null, 
      "roundstage": "Final", 
      "venue": "Valencia", 
      "IndoorOutdoor": "Indoor", 
      "agegroup": null, 
      "venueCountry": "ESP", 
      "rank": "6", 
      "event": "800", 
      "result": "1:52.76", 
      "date": "2008-02-24", 
      "round": null, 
      "wind": null
    }, 
    {
      "competition_ID": "11725470", 
      "compName": null, 
      "roundstage": "Final", 
      "venue": "Sevilla", 
      "IndoorOutdoor": "Outdoor", 
      "agegroup": null, 
      "venueCountry": "ESP", 
      "rank": "1", 
      "event": "800", 
      "result": "1:47.84", 
      "date": "2008-05-24", 
      "round": null, 
      "wind": null
    }, 
    {
      "competition_ID": "11729236", 
      "compName": null, 
      "roundstage": "Final", 
      "venue": "Zaragoza", 
      "IndoorOutdoor": "Outdoor", 
      "agegroup": null, 
      "venueCountry": "ESP", 
      "rank": "15", 
      "event": "1500", 
      "result": "3:45.25", 
      "date": "2008-05-31", 
      "round": null, 
      "wind": null
    }, 
    {
      "competition_ID": "11922346", 
      "compName": null, 
      "roundstage": "Final", 
      "venue": "Vitoria", 
      "IndoorOutdoor": "Outdoor", 
      "agegroup": "Under 20", 
      "venueCountry": "ESP", 
      "rank": "1", 
      "event": "1500", 
      "result": "4:00.89", 
      "date": "2008-06-22", 
      "round": "-19", 
      "wind": null
    }, 
    {
      "competition_ID": "11921988", 
      "compName": null, 
      "roundstage": "Final", 
      "venue": "Pamplona", 
      "IndoorOutdoor": "Outdoor", 
      "agegroup": null, 
      "venueCountry": "ESP", 
      "rank": "1", 
      "event": "800", 
      "result": "1:51.68", 
      "date": "2008-06-28", 
      "round": null, 
      "wind": null
    }, 
    {
      "competition_ID": "11909738", 
      "compName": null, 
      "roundstage": "Prelim", 
      "venue": "Bydgoszcz", 
      "IndoorOutdoor": "Outdoor", 
      "agegroup": null, 
      "venueCountry": "POL", 
      "rank": "7", 
      "event": "1500", 
      "result": "3:48.54", 
      "date": "2008-07-08", 
      "round": "h3-19", 
      "wind": null
    }, 
    {
      "competition_ID": "11956602", 
      "compName": null, 
      "roundstage": "Prelim", 
      "venue": "Barcelona", 
      "IndoorOutdoor": "Outdoor", 
      "agegroup": null, 
      "venueCountry": "ESP", 
      "rank": "2", 
      "event": "1500", 
      "result": "3:42.41", 
      "date": "2008-07-19", 
      "round": "rB", 
      "wind": null
    }, 
    {
      "competition_ID": "11999365", 
      "compName": null, 
      "roundstage": "Prelim", 
      "venue": "Santa Cruz de Tenerife", 
      "IndoorOutdoor": "Outdoor", 
      "agegroup": null, 
      "venueCountry": "ESP", 
      "rank": "5", 
      "event": "800", 
      "result": "1:49.44", 
      "date": "2008-07-26", 
      "round": "h3", 
      "wind": null
    }, 
    {
      "competition_ID": "12023366", 
      "compName": null, 
      "roundstage": "Final", 
      "venue": "Rabat", 
      "IndoorOutdoor": "Outdoor", 
      "agegroup": "Under 20", 
      "venueCountry": "MAR", 
      "rank": "4", 
      "event": "800", 
      "result": "1:49.00", 
      "date": "2008-08-02", 
      "round": "-19", 
      "wind": null
    }, 
    {
      "competition_ID": "12483660", 
      "compName": null, 
      "roundstage": "Final", 
      "venue": "Llodio", 
      "IndoorOutdoor": "Outdoor", 
      "agegroup": "Under 20", 
      "venueCountry": "ESP", 
      "rank": "10", 
      "event": "CC5.6", 
      "result": "18:38", 
      "date": "2008-11-30", 
      "round": "-19", 
      "wind": null
    }, 
    {
      "competition_ID": "12531503", 
      "compName": null, 
      "roundstage": "Final", 
      "venue": "Vilafranca", 
      "IndoorOutdoor": "Indoor", 
      "agegroup": null, 
      "venueCountry": "ESP", 
      "rank": "1", 
      "event": "3000", 
      "result": "8:07.02", 
      "date": "2009-01-10", 
      "round": null, 
      "wind": null
    }, 
    {
      "competition_ID": "12576591", 
      "compName": null, 
      "roundstage": "Final", 
      "venue": "Valencia", 
      "IndoorOutdoor": "Indoor", 
      "agegroup": null, 
      "venueCountry": "ESP", 
      "rank": "1", 
      "event": "1500", 
      "result": "3:44.11", 
      "date": "2009-01-28", 
      "round": null, 
      "wind": null
    }, 
    {
      "competition_ID": "12592237", 
      "compName": null, 
      "roundstage": "Final", 
      "venue": "Valencia", 
      "IndoorOutdoor": "Indoor", 
      "agegroup": null, 
      "venueCountry": "ESP", 
      "rank": "1", 
      "event": "800", 
      "result": "1:48.26", 
      "date": "2009-02-04", 
      "round": null, 
      "wind": null
    }, 
    {
      "competition_ID": "12621536", 
      "compName": null, 
      "roundstage": "Prelim", 
      "venue": "Sevilla", 
      "IndoorOutdoor": "Indoor", 
      "agegroup": null, 
      "venueCountry": "ESP", 
      "rank": "1", 
      "event": "800", 
      "result": "1:52.01", 
      "date": "2009-02-21", 
      "round": "h3", 
      "wind": null
    }, 
    {
      "competition_ID": "12621536", 
      "compName": null, 
      "roundstage": "Final", 
      "venue": "Sevilla", 
      "IndoorOutdoor": "Indoor", 
      "agegroup": null, 
      "venueCountry": "ESP", 
      "rank": "4", 
      "event": "800", 
      "result": "1:51.21", 
      "date": "2009-02-22", 
      "round": null, 
      "wind": null
    }, 
    {
      "competition_ID": "12787609", 
      "compName": null, 
      "roundstage": "Final", 
      "venue": "Sevilla", 
      "IndoorOutdoor": "Outdoor", 
      "agegroup": null, 
      "venueCountry": "ESP", 
      "rank": "1", 
      "event": "800", 
      "result": "1:47.50", 
      "date": "2009-06-03", 
      "round": null, 
      "wind": null
    }, 
    {
      "competition_ID": "12787857", 
      "compName": null, 
      "roundstage": "Final", 
      "venue": "Lorca", 
      "IndoorOutdoor": "Outdoor", 
      "agegroup": null, 
      "venueCountry": "ESP", 
      "rank": "1", 
      "event": "800", 
      "result": "1:54.17", 
      "date": "2009-06-13", 
      "round": null, 
      "wind": null
    }, 
    {
      "competition_ID": "12788150", 
      "compName": null, 
      "roundstage": "Final", 
      "venue": "Bilbao", 
      "IndoorOutdoor": "Outdoor", 
      "agegroup": null, 
      "venueCountry": "ESP", 
      "rank": "1", 
      "event": "1500", 
      "result": "3:42.78", 
      "date": "2009-06-20", 
      "round": null, 
      "wind": null
    }, 
    {
      "competition_ID": "12788259", 
      "compName": null, 
      "roundstage": "Final", 
      "venue": "M\u00c3\u00a1laga", 
      "IndoorOutdoor": "Outdoor", 
      "agegroup": null, 
      "venueCountry": "ESP", 
      "rank": "8", 
      "event": "1500", 
      "result": "3:39.84", 
      "date": "2009-06-27", 
      "round": null, 
      "wind": null
    }, 
    {
      "competition_ID": "12788806", 
      "compName": null, 
      "roundstage": "Final", 
      "venue": "Calvi\u00c3\u00a1", 
      "IndoorOutdoor": "Outdoor", 
      "agegroup": "Under 20", 
      "venueCountry": "ESP", 
      "rank": "1", 
      "event": "1500", 
      "result": "3:49.55", 
      "date": "2009-07-12", 
      "round": "-19", 
      "wind": null
    }, 
    {
      "competition_ID": "12788872", 
      "compName": null, 
      "roundstage": "Prelim", 
      "venue": "Novi Sad", 
      "IndoorOutdoor": "Outdoor", 
      "agegroup": null, 
      "venueCountry": "SRB", 
      "rank": "2", 
      "event": "1500", 
      "result": "3:46.23", 
      "date": "2009-07-23", 
      "round": "h2-19", 
      "wind": null
    }, 
    {
      "competition_ID": "12788872", 
      "compName": null, 
      "roundstage": "Final", 
      "venue": "Novi Sad", 
      "IndoorOutdoor": "Outdoor", 
      "agegroup": "Under 20", 
      "venueCountry": "SRB", 
      "rank": "1", 
      "event": "1500", 
      "result": "3:53.31", 
      "date": "2009-07-25", 
      "round": "-19", 
      "wind": null
    }, 
    {
      "competition_ID": "12788997", 
      "compName": null, 
      "roundstage": "Prelim", 
      "venue": "Barcelona", 
      "IndoorOutdoor": "Outdoor", 
      "agegroup": null, 
      "venueCountry": "ESP", 
      "rank": "2", 
      "event": "800", 
      "result": "1:52.22", 
      "date": "2009-08-01", 
      "round": "h1", 
      "wind": null
    }, 
    {
      "competition_ID": "12788997", 
      "compName": null, 
      "roundstage": "Final", 
      "venue": "Barcelona", 
      "IndoorOutdoor": "Outdoor", 
      "agegroup": null, 
      "venueCountry": "ESP", 
      "rank": "7", 
      "event": "800", 
      "result": "1:50.20", 
      "date": "2009-08-02", 
      "round": null, 
      "wind": null
    }, 
    {
      "competition_ID": "12790158", 
      "compName": null, 
      "roundstage": "Final", 
      "venue": "Madrid", 
      "IndoorOutdoor": "Outdoor", 
      "agegroup": "Under 20", 
      "venueCountry": "ESP", 
      "rank": "1", 
      "event": "800", 
      "result": "1:52.12", 
      "date": "2009-08-08", 
      "round": "-19", 
      "wind": null
    }, 
    {
      "competition_ID": "12790665", 
      "compName": null, 
      "roundstage": "Final", 
      "venue": "Llodio", 
      "IndoorOutdoor": "Outdoor", 
      "agegroup": "Under 20", 
      "venueCountry": "ESP", 
      "rank": "1", 
      "event": "CC5.8", 
      "result": "17:24", 
      "date": "2009-11-22", 
      "round": "-19", 
      "wind": null
    }, 
    {
      "competition_ID": "12791001", 
      "compName": null, 
      "roundstage": "Final", 
      "venue": "Dublin", 
      "IndoorOutdoor": "Outdoor", 
      "agegroup": "Under 20", 
      "venueCountry": "IRL", 
      "rank": "18", 
      "event": "CC6.039", 
      "result": "19:16", 
      "date": "2009-12-13", 
      "round": "-19", 
      "wind": null
    }, 
    {
      "competition_ID": "12792152", 
      "compName": null, 
      "roundstage": "Final", 
      "venue": "Valencia", 
      "IndoorOutdoor": "Indoor", 
      "agegroup": null, 
      "venueCountry": "ESP", 
      "rank": "1", 
      "event": "1500", 
      "result": "3:40.23", 
      "date": "2010-01-15", 
      "round": null, 
      "wind": null
    }, 
    {
      "competition_ID": "12793066", 
      "compName": null, 
      "roundstage": "Final", 
      "venue": "Valencia", 
      "IndoorOutdoor": "Indoor", 
      "agegroup": null, 
      "venueCountry": "ESP", 
      "rank": "1", 
      "event": "800", 
      "result": "1:47.23", 
      "date": "2010-01-30", 
      "round": null, 
      "wind": null
    }, 
    {
      "competition_ID": "12794103", 
      "compName": null, 
      "roundstage": "Prelim", 
      "venue": "Valencia", 
      "IndoorOutdoor": "Indoor", 
      "agegroup": null, 
      "venueCountry": "ESP", 
      "rank": "1", 
      "event": "800", 
      "result": "1:49.00", 
      "date": "2010-02-27", 
      "round": "h2", 
      "wind": null
    }, 
    {
      "competition_ID": "12794103", 
      "compName": null, 
      "roundstage": "Final", 
      "venue": "Valencia", 
      "IndoorOutdoor": "Indoor", 
      "agegroup": null, 
      "venueCountry": "ESP", 
      "rank": "2", 
      "event": "800", 
      "result": "1:50.14", 
      "date": "2010-02-28", 
      "round": null, 
      "wind": null
    }, 
    {
      "competition_ID": "12794620", 
      "compName": null, 
      "roundstage": "Prelim", 
      "venue": "Doha", 
      "IndoorOutdoor": "Indoor", 
      "agegroup": null, 
      "venueCountry": "QAT", 
      "rank": "2", 
      "event": "800", 
      "result": "1:47.65", 
      "date": "2010-03-12", 
      "round": "h2", 
      "wind": null
    }, 
    {
      "competition_ID": "12794620", 
      "compName": null, 
      "roundstage": "Prelim", 
      "venue": "Doha", 
      "IndoorOutdoor": "Indoor", 
      "agegroup": null, 
      "venueCountry": "QAT", 
      "rank": "4", 
      "event": "800", 
      "result": "1:47.05", 
      "date": "2010-03-13", 
      "round": "s1", 
      "wind": null
    }, 
    {
      "competition_ID": "12797944", 
      "compName": null, 
      "roundstage": "Final", 
      "venue": "San Fernando", 
      "IndoorOutdoor": "Outdoor", 
      "agegroup": null, 
      "venueCountry": "ESP", 
      "rank": "1", 
      "event": "1500", 
      "result": "3:43.19", 
      "date": "2010-06-05", 
      "round": null, 
      "wind": null
    }, 
    {
      "competition_ID": "12798830", 
      "compName": null, 
      "roundstage": "Final", 
      "venue": "Barakaldo", 
      "IndoorOutdoor": "Outdoor", 
      "agegroup": null, 
      "venueCountry": "ESP", 
      "rank": "1", 
      "event": "800", 
      "result": "1:46.12", 
      "date": "2010-06-23", 
      "round": null, 
      "wind": null
    }, 
    {
      "competition_ID": "12799531", 
      "compName": null, 
      "roundstage": "Final", 
      "venue": "Calvi\u00c3\u00a1", 
      "IndoorOutdoor": "Outdoor", 
      "agegroup": "Under 23", 
      "venueCountry": "ESP", 
      "rank": "1", 
      "event": "1500", 
      "result": "3:57.59", 
      "date": "2010-07-04", 
      "round": "-22", 
      "wind": null
    }, 
    {
      "competition_ID": "12799880", 
      "compName": null, 
      "roundstage": "Prelim", 
      "venue": "Avil\u00c3\u00a9s", 
      "IndoorOutdoor": "Outdoor", 
      "agegroup": null, 
      "venueCountry": "ESP", 
      "rank": "2", 
      "event": "800", 
      "result": "1:50.33", 
      "date": "2010-07-17", 
      "round": "h3", 
      "wind": null
    }, 
    {
      "competition_ID": "12799880", 
      "compName": null, 
      "roundstage": "Final", 
      "venue": "Avil\u00c3\u00a9s", 
      "IndoorOutdoor": "Outdoor", 
      "agegroup": null, 
      "venueCountry": "ESP", 
      "rank": "3", 
      "event": "800", 
      "result": "1:48.13", 
      "date": "2010-07-18", 
      "round": null, 
      "wind": null
    }, 
    {
      "competition_ID": "12800102", 
      "compName": null, 
      "roundstage": "Prelim", 
      "venue": "Barcelona", 
      "IndoorOutdoor": "Outdoor", 
      "agegroup": null, 
      "venueCountry": "ESP", 
      "rank": "3", 
      "event": "800", 
      "result": "1:50.01", 
      "date": "2010-07-28", 
      "round": "h1", 
      "wind": null
    }, 
    {
      "competition_ID": "12800102", 
      "compName": null, 
      "roundstage": "Prelim", 
      "venue": "Barcelona", 
      "IndoorOutdoor": "Outdoor", 
      "agegroup": null, 
      "venueCountry": "ESP", 
      "rank": "6", 
      "event": "800", 
      "result": "1:49.08", 
      "date": "2010-07-29", 
      "round": "s1", 
      "wind": null
    }, 
    {
      "competition_ID": "12803888", 
      "compName": "27th Cross Internacional Valle de Llodio", 
      "roundstage": "Final", 
      "venue": "Llodio", 
      "IndoorOutdoor": "Outdoor", 
      "agegroup": "Under 23", 
      "venueCountry": "ESP", 
      "rank": "15", 
      "event": "CC9.76", 
      "result": "36:57", 
      "date": "2010-11-28", 
      "round": "-22", 
      "wind": null
    }, 
    {
      "competition_ID": "12806076", 
      "compName": "Sparkassen Cup, Schleyer-Halle", 
      "roundstage": "Final", 
      "venue": "Stuttgart", 
      "IndoorOutdoor": "Indoor", 
      "agegroup": "Under 23", 
      "venueCountry": "GER", 
      "rank": "2", 
      "event": "1500", 
      "result": "3:41.31", 
      "date": "2011-02-05", 
      "round": "-22", 
      "wind": null
    }, 
    {
      "competition_ID": "12806290", 
      "compName": "Meeting du Pas de Calais, Stade Couvert R\u00c3\u00a9gional", 
      "roundstage": "Prelim", 
      "venue": "Li\u00c3\u00a9vin", 
      "IndoorOutdoor": "Indoor", 
      "agegroup": null, 
      "venueCountry": "FRA", 
      "rank": "4", 
      "event": "800", 
      "result": "1:49.50", 
      "date": "2011-02-08", 
      "round": "rB", 
      "wind": null
    }, 
    {
      "competition_ID": "12806925", 
      "compName": null, 
      "roundstage": "Prelim", 
      "venue": "Valencia", 
      "IndoorOutdoor": "Indoor", 
      "agegroup": null, 
      "venueCountry": "ESP", 
      "rank": "2", 
      "event": "800", 
      "result": "1:50.39", 
      "date": "2011-02-19", 
      "round": "h1", 
      "wind": null
    }, 
    {
      "competition_ID": "12806925", 
      "compName": null, 
      "roundstage": "Final", 
      "venue": "Valencia", 
      "IndoorOutdoor": "Indoor", 
      "agegroup": null, 
      "venueCountry": "ESP", 
      "rank": "5", 
      "event": "800", 
      "result": "1:51.47", 
      "date": "2011-02-20", 
      "round": null, 
      "wind": null
    }, 
    {
      "competition_ID": "12807375", 
      "compName": null, 
      "roundstage": "Prelim", 
      "venue": "Paris", 
      "IndoorOutdoor": "Indoor", 
      "agegroup": null, 
      "venueCountry": "FRA", 
      "rank": "3", 
      "event": "800", 
      "result": "1:49.04", 
      "date": "2011-03-04", 
      "round": "h1", 
      "wind": null
    }, 
    {
      "competition_ID": "12807375", 
      "compName": null, 
      "roundstage": "Prelim", 
      "venue": "Paris", 
      "IndoorOutdoor": "Indoor", 
      "agegroup": null, 
      "venueCountry": "FRA", 
      "rank": "6", 
      "event": "800", 
      "result": "1:50.46", 
      "date": "2011-03-05", 
      "round": "s1", 
      "wind": null
    }, 
    {
      "competition_ID": "12810993", 
      "compName": "Meeting Iberoamericano, Estadio Iberoamericano", 
      "roundstage": "Final", 
      "venue": "Huelva", 
      "IndoorOutdoor": "Outdoor", 
      "agegroup": null, 
      "venueCountry": "ESP", 
      "rank": "6", 
      "event": "1500", 
      "result": "3:39.09", 
      "date": "2011-06-02", 
      "round": null, 
      "wind": null
    }, 
    {
      "competition_ID": "12811470", 
      "compName": null, 
      "roundstage": "Final", 
      "venue": "Watford", 
      "IndoorOutdoor": "Outdoor", 
      "agegroup": null, 
      "venueCountry": "GBR", 
      "rank": "1", 
      "event": "1500", 
      "result": "3:40.01", 
      "date": "2011-06-11", 
      "round": null, 
      "wind": null
    }, 
    {
      "competition_ID": "12812678", 
      "compName": null, 
      "roundstage": "Final", 
      "venue": "And\u00c3\u00bajar", 
      "IndoorOutdoor": "Outdoor", 
      "agegroup": "Under 23", 
      "venueCountry": "ESP", 
      "rank": "1", 
      "event": "1500", 
      "result": "3:57.34", 
      "date": "2011-07-03", 
      "round": "-22", 
      "wind": null
    }, 
    {
      "competition_ID": "12813128", 
      "compName": null, 
      "roundstage": "Prelim", 
      "venue": "Ostrava", 
      "IndoorOutdoor": "Outdoor", 
      "agegroup": null, 
      "venueCountry": "CZE", 
      "rank": "2", 
      "event": "1500", 
      "result": "3:41.37", 
      "date": "2011-07-16", 
      "round": "h1-22", 
      "wind": null
    }, 
    {
      "competition_ID": "12813128", 
      "compName": null, 
      "roundstage": "Final", 
      "venue": "Ostrava", 
      "IndoorOutdoor": "Outdoor", 
      "agegroup": "Under 23", 
      "venueCountry": "CZE", 
      "rank": "3", 
      "event": "1500", 
      "result": "3:50.59", 
      "date": "2011-07-17", 
      "round": "-22", 
      "wind": null
    }, 
    {
      "competition_ID": "12813417", 
      "compName": "17th M\u00c3\u00adting Internacional D'Atletisme Ciutat de Barcelona, Estadi Ol\u00c3\u00admpic De Montju\u00c3\u00afc Llu\u00c3\u00ads Companys", 
      "roundstage": "Final", 
      "venue": "Barcelona", 
      "IndoorOutdoor": "Outdoor", 
      "agegroup": null, 
      "venueCountry": "ESP", 
      "rank": "14", 
      "event": "1500", 
      "result": "3:43.52", 
      "date": "2011-07-22", 
      "round": null, 
      "wind": null
    }, 
    {
      "competition_ID": "12813771", 
      "compName": "91st Campeonato de Espa\u00c3\u00b1a, Estadio Atletismo Ciudad de M\u00c3\u00a1laga", 
      "roundstage": "Prelim", 
      "venue": "M\u00c3\u00a1laga", 
      "IndoorOutdoor": "Outdoor", 
      "agegroup": null, 
      "venueCountry": "ESP", 
      "rank": "4", 
      "event": "1500", 
      "result": "3:47.93", 
      "date": "2011-08-06", 
      "round": "h2", 
      "wind": null
    }, 
    {
      "competition_ID": "12813771", 
      "compName": null, 
      "roundstage": "Final", 
      "venue": "M\u00c3\u00a1laga", 
      "IndoorOutdoor": "Outdoor", 
      "agegroup": null, 
      "venueCountry": "ESP", 
      "rank": "4", 
      "event": "1500", 
      "result": "3:54.82", 
      "date": "2011-08-07", 
      "round": null, 
      "wind": null
    }, 
    {
      "competition_ID": "12819661", 
      "compName": null, 
      "roundstage": "Final", 
      "venue": "Sabadell", 
      "IndoorOutdoor": "Indoor", 
      "agegroup": null, 
      "venueCountry": "ESP", 
      "rank": "1", 
      "event": "3000", 
      "result": "8:00.58", 
      "date": "2012-01-29", 
      "round": null, 
      "wind": null
    }, 
    {
      "competition_ID": "12820372", 
      "compName": null, 
      "roundstage": "Final", 
      "venue": "Sabadell", 
      "IndoorOutdoor": "Indoor", 
      "agegroup": null, 
      "venueCountry": "ESP", 
      "rank": "1", 
      "event": "1500", 
      "result": "3:41.16", 
      "date": "2012-02-10", 
      "round": null, 
      "wind": null
    }, 
    {
      "competition_ID": "12820404", 
      "compName": "Meeting du Pas de Calais, Stade Couvert R\u00c3\u00a9gional", 
      "roundstage": "Prelim", 
      "venue": "Li\u00c3\u00a9vin", 
      "IndoorOutdoor": "Indoor", 
      "agegroup": null, 
      "venueCountry": "FRA", 
      "rank": "6", 
      "event": "800", 
      "result": "1:49.92", 
      "date": "2012-02-14", 
      "round": "rB", 
      "wind": null
    }, 
    {
      "competition_ID": "12820796", 
      "compName": "National Indoor Championships", 
      "roundstage": "Final", 
      "venue": "Sabadell", 
      "IndoorOutdoor": "Indoor", 
      "agegroup": null, 
      "venueCountry": "ESP", 
      "rank": "2", 
      "event": "1500", 
      "result": "3:44.25", 
      "date": "2012-02-26", 
      "round": null, 
      "wind": null
    }, 
    {
      "competition_ID": "12821019", 
      "compName": null, 
      "roundstage": "Prelim", 
      "venue": "Istanbul", 
      "IndoorOutdoor": "Indoor", 
      "agegroup": null, 
      "venueCountry": "TUR", 
      "rank": "6", 
      "event": "1500", 
      "result": "3:43.66", 
      "date": "2012-03-09", 
      "round": "h1", 
      "wind": null
    }, 
    {
      "competition_ID": "12823510", 
      "compName": "Reunion Internacional De Atletismo Villa De Bilbao", 
      "roundstage": "Final", 
      "venue": "Bilbao", 
      "IndoorOutdoor": "Outdoor", 
      "agegroup": null, 
      "venueCountry": "ESP", 
      "rank": "1", 
      "event": "1500", 
      "result": "3:37.91", 
      "date": "2012-06-03", 
      "round": null, 
      "wind": null
    }, 
    {
      "competition_ID": "12823630", 
      "compName": "8th Meeting Iberoameric\u00c3\u00a1no de atletismo", 
      "roundstage": "Final", 
      "venue": "Huelva", 
      "IndoorOutdoor": "Outdoor", 
      "agegroup": null, 
      "venueCountry": "ESP", 
      "rank": "2", 
      "event": "1500", 
      "result": "3:34.77", 
      "date": "2012-06-07", 
      "round": null, 
      "wind": null
    }, 
    {
      "competition_ID": "12824352", 
      "compName": "21st European Championships, Olympic Stadium", 
      "roundstage": "Prelim", 
      "venue": "Helsinki", 
      "IndoorOutdoor": "Outdoor", 
      "agegroup": null, 
      "venueCountry": "FIN", 
      "rank": "3", 
      "event": "1500", 
      "result": "3:46.12", 
      "date": "2012-06-30", 
      "round": "h2", 
      "wind": null
    }, 
    {
      "competition_ID": "12824352", 
      "compName": "21st European Championships, Olympic Stadium", 
      "roundstage": "Final", 
      "venue": "Helsinki", 
      "IndoorOutdoor": "Outdoor", 
      "agegroup": null, 
      "venueCountry": "FIN", 
      "rank": "3", 
      "event": "1500", 
      "result": "3:46.45", 
      "date": "2012-07-01", 
      "round": null, 
      "wind": null
    }, 
    {
      "competition_ID": "12824477", 
      "compName": "30th Meeting de Atletismo Madrid", 
      "roundstage": "Final", 
      "venue": "Madrid", 
      "IndoorOutdoor": "Outdoor", 
      "agegroup": null, 
      "venueCountry": "ESP", 
      "rank": "11", 
      "event": "800", 
      "result": "1:48.03", 
      "date": "2012-07-07", 
      "round": null, 
      "wind": null
    }, 
    {
      "competition_ID": "12825110", 
      "compName": null, 
      "roundstage": "Prelim", 
      "venue": "London", 
      "IndoorOutdoor": "Outdoor", 
      "agegroup": null, 
      "venueCountry": "GBR", 
      "rank": "6", 
      "event": "1500", 
      "result": "3:41.34", 
      "date": "2012-08-03", 
      "round": "h2", 
      "wind": null
    }, 
    {
      "competition_ID": "12825383", 
      "compName": "National Championships", 
      "roundstage": "Prelim", 
      "venue": "Pamplona", 
      "IndoorOutdoor": "Outdoor", 
      "agegroup": null, 
      "venueCountry": "ESP", 
      "rank": "5", 
      "event": "1500", 
      "result": "3:50.26", 
      "date": "2012-08-25", 
      "round": "h2", 
      "wind": null
    }, 
    {
      "competition_ID": "12825383", 
      "compName": null, 
      "roundstage": "Final", 
      "venue": "Pamplona", 
      "IndoorOutdoor": "Outdoor", 
      "agegroup": null, 
      "venueCountry": "ESP", 
      "rank": "1", 
      "event": "1500", 
      "result": "3:45.93", 
      "date": "2012-08-26", 
      "round": null, 
      "wind": null
    }, 
    {
      "competition_ID": "12828351", 
      "compName": null, 
      "roundstage": "Final", 
      "venue": "Sabadell", 
      "IndoorOutdoor": "Indoor", 
      "agegroup": null, 
      "venueCountry": "ESP", 
      "rank": "1", 
      "event": "1500", 
      "result": "3:39.57", 
      "date": "2013-01-25", 
      "round": null, 
      "wind": null
    }, 
    {
      "competition_ID": "12838996", 
      "compName": "PSD Bank Meeting, Arena Sportpark", 
      "roundstage": "Final", 
      "venue": "D\u00c3\u00bcsseldorf", 
      "IndoorOutdoor": "Indoor", 
      "agegroup": null, 
      "venueCountry": "GER", 
      "rank": "3", 
      "event": "1500", 
      "result": "3:38.41", 
      "date": "2013-02-08", 
      "round": null, 
      "wind": null
    }, 
    {
      "competition_ID": "12839186", 
      "compName": null, 
      "roundstage": "Final", 
      "venue": "Sabadell", 
      "IndoorOutdoor": "Indoor", 
      "agegroup": null, 
      "venueCountry": "ESP", 
      "rank": "1", 
      "event": "1500", 
      "result": "3:57.07", 
      "date": "2013-02-17", 
      "round": null, 
      "wind": null
    }, 
    {
      "competition_ID": "12839558", 
      "compName": "32nd European Athletics Indoor Championships, Scandinavium", 
      "roundstage": "Prelim", 
      "venue": "G\u00c3\u00b6teborg", 
      "IndoorOutdoor": "Indoor", 
      "agegroup": null, 
      "venueCountry": "SWE", 
      "rank": "2", 
      "event": "1500", 
      "result": "3:39.90", 
      "date": "2013-03-02", 
      "round": "h1", 
      "wind": null
    }, 
    {
      "competition_ID": "12839558", 
      "compName": "32nd European Athletics Indoor Championships, Scandinavium", 
      "roundstage": "Final", 
      "venue": "G\u00c3\u00b6teborg", 
      "IndoorOutdoor": "Indoor", 
      "agegroup": null, 
      "venueCountry": "SWE", 
      "rank": "8", 
      "event": "1500", 
      "result": "3:40.14", 
      "date": "2013-03-03", 
      "round": null, 
      "wind": null
    }, 
    {
      "competition_ID": "12842739", 
      "compName": "Bislett Games, IAAF Diamond League, Bislett Stadium", 
      "roundstage": "Final", 
      "venue": "Oslo", 
      "IndoorOutdoor": "Outdoor", 
      "agegroup": null, 
      "venueCountry": "NOR", 
      "rank": "6", 
      "event": "Mile", 
      "result": "3:53.40", 
      "date": "2013-06-13", 
      "round": null, 
      "wind": null
    }, 
    {
      "competition_ID": "12842739", 
      "compName": null, 
      "roundstage": "Final", 
      "venue": "Oslo", 
      "IndoorOutdoor": "Outdoor", 
      "agegroup": null, 
      "venueCountry": "NOR", 
      "rank": "9", 
      "event": "1500", 
      "result": "3:37.83", 
      "date": "2013-06-13", 
      "round": null, 
      "wind": null
    }, 
    {
      "competition_ID": "12843611", 
      "compName": "KBC-Nacht, KBC Night of Athletics, Stadion De Veen", 
      "roundstage": "Final", 
      "venue": "Heusden", 
      "IndoorOutdoor": "Outdoor", 
      "agegroup": null, 
      "venueCountry": "BEL", 
      "rank": "2", 
      "event": "1500", 
      "result": "3:35.69", 
      "date": "2013-07-13", 
      "round": null, 
      "wind": null
    }, 
    {
      "competition_ID": "12843832", 
      "compName": "National Championships", 
      "roundstage": "Prelim", 
      "venue": "Alcobendas", 
      "IndoorOutdoor": "Outdoor", 
      "agegroup": null, 
      "venueCountry": "ESP", 
      "rank": "2", 
      "event": "1500", 
      "result": "3:47.84", 
      "date": "2013-07-27", 
      "round": "h2", 
      "wind": null
    }, 
    {
      "competition_ID": "12843832", 
      "compName": null, 
      "roundstage": "Final", 
      "venue": "Alcobendas", 
      "IndoorOutdoor": "Outdoor", 
      "agegroup": null, 
      "venueCountry": "ESP", 
      "rank": "1", 
      "event": "1500", 
      "result": "3:47.11", 
      "date": "2013-07-28", 
      "round": null, 
      "wind": null
    }, 
    {
      "competition_ID": "12844203", 
      "compName": null, 
      "roundstage": "Prelim", 
      "venue": "Moskva", 
      "IndoorOutdoor": "Outdoor", 
      "agegroup": null, 
      "venueCountry": "RUS", 
      "rank": "11", 
      "event": "1500", 
      "result": "3:41.69", 
      "date": "2013-08-14", 
      "round": "h1", 
      "wind": null
    }, 
    {
      "competition_ID": "12850956", 
      "compName": "14th Gran Premio", 
      "roundstage": "Final", 
      "venue": "Los Corrales de Buelna", 
      "IndoorOutdoor": "Outdoor", 
      "agegroup": null, 
      "venueCountry": "ESP", 
      "rank": "1", 
      "event": "800", 
      "result": "1:47.89", 
      "date": "2014-05-24", 
      "round": null, 
      "wind": null
    }, 
    {
      "competition_ID": "12851934", 
      "compName": "10th Meeting Iberoamericano de Atletismo, Estadio Iberoamericano", 
      "roundstage": "Final", 
      "venue": "Huelva", 
      "IndoorOutdoor": "Outdoor", 
      "agegroup": null, 
      "venueCountry": "ESP", 
      "rank": "6", 
      "event": "1500", 
      "result": "3:38.66", 
      "date": "2014-06-12", 
      "round": null, 
      "wind": null
    }, 
    {
      "competition_ID": "12853205", 
      "compName": "KBC-Nacht, De Veen Stadium", 
      "roundstage": "Final", 
      "venue": "Heusden", 
      "IndoorOutdoor": "Outdoor", 
      "agegroup": null, 
      "venueCountry": "BEL", 
      "rank": "5", 
      "event": "1500", 
      "result": "3:35.59", 
      "date": "2014-07-19", 
      "round": null, 
      "wind": null
    }, 
    {
      "competition_ID": "12853418", 
      "compName": "National Championships", 
      "roundstage": "Prelim", 
      "venue": "Alcobendas", 
      "IndoorOutdoor": "Outdoor", 
      "agegroup": null, 
      "venueCountry": "ESP", 
      "rank": "1", 
      "event": "1500", 
      "result": "3:46.49", 
      "date": "2014-07-26", 
      "round": "h2", 
      "wind": null
    }, 
    {
      "competition_ID": "12853418", 
      "compName": null, 
      "roundstage": "Final", 
      "venue": "Alcobendas", 
      "IndoorOutdoor": "Outdoor", 
      "agegroup": null, 
      "venueCountry": "ESP", 
      "rank": "3", 
      "event": "1500", 
      "result": "3:42.95", 
      "date": "2014-07-27", 
      "round": null, 
      "wind": null
    }, 
    {
      "competition_ID": "12853650", 
      "compName": "22nd European Athletics Championships, Letzigrund Stadium", 
      "roundstage": "Prelim", 
      "venue": "Z\u00c3\u00bcrich", 
      "IndoorOutdoor": "Outdoor", 
      "agegroup": null, 
      "venueCountry": "SUI", 
      "rank": "15", 
      "event": "1500", 
      "result": "4:21.39", 
      "date": "2014-08-15", 
      "round": "h2", 
      "wind": null
    }, 
    {
      "competition_ID": "12853650", 
      "compName": "22nd European Athletics Championships, Letzigrund Stadium", 
      "roundstage": "Final", 
      "venue": "Z\u00c3\u00bcrich", 
      "IndoorOutdoor": "Outdoor", 
      "agegroup": null, 
      "venueCountry": "SUI", 
      "rank": "6", 
      "event": "1500", 
      "result": "3:46.92", 
      "date": "2014-08-17", 
      "round": null, 
      "wind": null
    }, 
    {
      "competition_ID": "12853856", 
      "compName": "73rd ISTAF, Olympic Stadium", 
      "roundstage": "Final", 
      "venue": "Berlin", 
      "IndoorOutdoor": "Outdoor", 
      "agegroup": null, 
      "venueCountry": "GER", 
      "rank": "11", 
      "event": "1500", 
      "result": "3:37.67", 
      "date": "2014-08-31", 
      "round": null, 
      "wind": null
    }, 
    {
      "competition_ID": "12860489", 
      "compName": "15th Gran Premio de Los Corrales", 
      "roundstage": "Final", 
      "venue": "Los Corrales de Buelna", 
      "IndoorOutdoor": "Outdoor", 
      "agegroup": null, 
      "venueCountry": "ESP", 
      "rank": "1", 
      "event": "1500", 
      "result": "3:42.82", 
      "date": "2015-05-16", 
      "round": null, 
      "wind": null
    }, 
    {
      "competition_ID": "12861195", 
      "compName": "9th Trofeo Alfonso Posada", 
      "roundstage": "Final", 
      "venue": "Vigo", 
      "IndoorOutdoor": "Outdoor", 
      "agegroup": null, 
      "venueCountry": "ESP", 
      "rank": "1", 
      "event": "800", 
      "result": "1:48.47", 
      "date": "2015-06-03", 
      "round": null, 
      "wind": null
    }, 
    {
      "competition_ID": "12861470", 
      "compName": "11th Meeting Iberoamericano de Atletismo, Estadio Iberoamericano", 
      "roundstage": "Final", 
      "venue": "Huelva", 
      "IndoorOutdoor": "Outdoor", 
      "agegroup": null, 
      "venueCountry": "ESP", 
      "rank": "7", 
      "event": "1500", 
      "result": "3:43.11", 
      "date": "2015-06-10", 
      "round": null, 
      "wind": null
    }, 
    {
      "competition_ID": "12861937", 
      "compName": "15th Meeting Internacional Bilbao", 
      "roundstage": "Final", 
      "venue": "Bilbao", 
      "IndoorOutdoor": "Outdoor", 
      "agegroup": null, 
      "venueCountry": "ESP", 
      "rank": "16", 
      "event": "1500", 
      "result": "3:48.90", 
      "date": "2015-06-20", 
      "round": null, 
      "wind": null
    }, 
    {
      "competition_ID": "12862439", 
      "compName": "95th Campionat de Catalunya Absolut, Miting Internacional d'Atletisme Centenari FCA, Estadi Joan Serrahima", 
      "roundstage": "Final", 
      "venue": "Barcelona", 
      "IndoorOutdoor": "Outdoor", 
      "agegroup": null, 
      "venueCountry": "ESP", 
      "rank": "4", 
      "event": "1500", 
      "result": "3:36.90", 
      "date": "2015-07-08", 
      "round": null, 
      "wind": null
    }, 
    {
      "competition_ID": "12862652", 
      "compName": "KBC-Nacht, KBC Night of Athletics, Stadion De Veen", 
      "roundstage": "Final", 
      "venue": "Heusden", 
      "IndoorOutdoor": "Outdoor", 
      "agegroup": null, 
      "venueCountry": "BEL", 
      "rank": "6", 
      "event": "1500", 
      "result": "3:35.97", 
      "date": "2015-07-18", 
      "round": null, 
      "wind": null
    }, 
    {
      "competition_ID": "12862904", 
      "compName": "15th Campeonato de Espa\u00c3\u00b1a de Federaciones Auton\u00c3\u00b3micas", 
      "roundstage": "Final", 
      "venue": "Gij\u00c3\u00b3n", 
      "IndoorOutdoor": "Outdoor", 
      "agegroup": null, 
      "venueCountry": "ESP", 
      "rank": "1", 
      "event": "800", 
      "result": "1:49.16", 
      "date": "2015-07-25", 
      "round": null, 
      "wind": null
    }, 
    {
      "competition_ID": "12863062", 
      "compName": "95th Campeonato de Espa\u00c3\u00b1a, Pista Municipal Gaet\u00c3\u00a0 Huguet", 
      "roundstage": "Prelim", 
      "venue": "Castell\u00c3\u00b3n", 
      "IndoorOutdoor": "Outdoor", 
      "agegroup": null, 
      "venueCountry": "ESP", 
      "rank": "2", 
      "event": "1500", 
      "result": "3:46.18", 
      "date": "2015-08-01", 
      "round": "h3", 
      "wind": null
    }, 
    {
      "competition_ID": "12863062", 
      "compName": "95th Campeonato de Espa\u00c3\u00b1a, Pista Municipal Gaet\u00c3\u00a0 Huguet", 
      "roundstage": "Final", 
      "venue": "Castell\u00c3\u00b3n", 
      "IndoorOutdoor": "Outdoor", 
      "agegroup": null, 
      "venueCountry": "ESP", 
      "rank": "3", 
      "event": "1500", 
      "result": "3:45.82", 
      "date": "2015-08-02", 
      "round": null, 
      "wind": null
    }, 
    {
      "competition_ID": "12863607", 
      "compName": "Tilastopajacup, Paavo Nurmi Stadium", 
      "roundstage": "Prelim", 
      "venue": "Beijing", 
      "IndoorOutdoor": "Outdoor", 
      "agegroup": null, 
      "venueCountry": "CHN", 
      "rank": "10", 
      "event": "1500", 
      "result": "3:38.75", 
      "date": "2015-08-27", 
      "round": "h3", 
      "wind": null
    }, 
    {
      "competition_ID": "12863607", 
      "compName": "Tilastopajacup, Paavo Nurmi Stadium", 
      "roundstage": "Prelim", 
      "venue": "Beijing", 
      "IndoorOutdoor": "Outdoor", 
      "agegroup": null, 
      "venueCountry": "CHN", 
      "rank": "12", 
      "event": "1500", 
      "result": "3:42.48", 
      "date": "2015-08-28", 
      "round": "s2", 
      "wind": null
    }, 
    {
      "competition_ID": "12863889", 
      "compName": null, 
      "roundstage": "Final", 
      "venue": "Zagreb", 
      "IndoorOutdoor": "Outdoor", 
      "agegroup": null, 
      "venueCountry": "CRO", 
      "rank": "8", 
      "event": "1500", 
      "result": "3:39.49", 
      "date": "2015-09-08", 
      "round": null, 
      "wind": null
    }, 
    {
      "competition_ID": "12863914", 
      "compName": "Van Damme Memorial, IAAF Diamond League, King Baudoin Stadium", 
      "roundstage": "Final", 
      "venue": "Bruxelles", 
      "IndoorOutdoor": "Outdoor", 
      "agegroup": null, 
      "venueCountry": "BEL", 
      "rank": "8", 
      "event": "1500", 
      "result": "3:40.19", 
      "date": "2015-09-11", 
      "round": null, 
      "wind": null
    }, 
    {
      "competition_ID": "12867176", 
      "compName": "San Silvestre Vallecana", 
      "roundstage": "Final", 
      "venue": "Madrid", 
      "IndoorOutdoor": "Outdoor", 
      "agegroup": null, 
      "venueCountry": "ESP", 
      "rank": "19", 
      "event": "10K", 
      "result": "30:33", 
      "date": "2015-12-31", 
      "round": null, 
      "wind": null
    }, 
    {
      "competition_ID": "12867528", 
      "compName": null, 
      "roundstage": "Final", 
      "venue": "Valencia", 
      "IndoorOutdoor": "Indoor", 
      "agegroup": null, 
      "venueCountry": "ESP", 
      "rank": "1", 
      "event": "800", 
      "result": "1:49.28", 
      "date": "2016-01-16", 
      "round": null, 
      "wind": null
    }, 
    {
      "competition_ID": "12869652", 
      "compName": "Control RFEA Mediofondo - 1500 Hombres, Pista Coberta de Catalunya", 
      "roundstage": "Final", 
      "venue": "Sabadell", 
      "IndoorOutdoor": "Indoor", 
      "agegroup": null, 
      "venueCountry": "ESP", 
      "rank": "3", 
      "event": "1500", 
      "result": "3:42.08", 
      "date": "2016-02-07", 
      "round": null, 
      "wind": null
    }, 
    {
      "competition_ID": "12869866", 
      "compName": "Gran Premio Ciudad de Valencia, Palau Velodromo Luis Puig", 
      "roundstage": "Final", 
      "venue": "Valencia", 
      "IndoorOutdoor": "Indoor", 
      "agegroup": null, 
      "venueCountry": "ESP", 
      "rank": "1", 
      "event": "1500", 
      "result": "3:41.73", 
      "date": "2016-02-13", 
      "round": null, 
      "wind": null
    }, 
    {
      "competition_ID": "12870062", 
      "compName": "Meeting National En Salle De Reims", 
      "roundstage": "Final", 
      "venue": "Reims", 
      "IndoorOutdoor": "Indoor", 
      "agegroup": null, 
      "venueCountry": "FRA", 
      "rank": "5", 
      "event": "1500", 
      "result": "3:41.12", 
      "date": "2016-02-17", 
      "round": null, 
      "wind": null
    }, 
    {
      "competition_ID": "12870325", 
      "compName": "Reuni\u00c3\u00b3n Internacional de Atletismo en Pista Cubierta, Centro Deportivo Municipal Gallur", 
      "roundstage": "Final", 
      "venue": "Madrid", 
      "IndoorOutdoor": "Indoor", 
      "agegroup": null, 
      "venueCountry": "ESP", 
      "rank": "3", 
      "event": "800", 
      "result": "1:48.72", 
      "date": "2016-02-26", 
      "round": null, 
      "wind": null
    }, 
    {
      "competition_ID": "12870616", 
      "compName": "52th National Indoor Championships, Campeonato de Espa\u00c3\u00b1a Absoluto de Atletismo en Pista Cubierta, Centro Deportivo Municipal Gallur", 
      "roundstage": "Prelim", 
      "venue": "Madrid", 
      "IndoorOutdoor": "Indoor", 
      "agegroup": null, 
      "venueCountry": "ESP", 
      "rank": "1", 
      "event": "1500", 
      "result": "3:50.67", 
      "date": "2016-03-05", 
      "round": "h3", 
      "wind": null
    }, 
    {
      "competition_ID": "12870616", 
      "compName": null, 
      "roundstage": "Final", 
      "venue": "Madrid", 
      "IndoorOutdoor": "Indoor", 
      "agegroup": null, 
      "venueCountry": "ESP", 
      "rank": "4", 
      "event": "1500", 
      "result": "4:03.65", 
      "date": "2016-03-06", 
      "round": null, 
      "wind": null
    }, 
    {
      "competition_ID": "12873600", 
      "compName": null, 
      "roundstage": "Final", 
      "venue": "Ostrava", 
      "IndoorOutdoor": "Outdoor", 
      "agegroup": null, 
      "venueCountry": "CZE", 
      "rank": "5", 
      "event": "1500", 
      "result": "3:38.28", 
      "date": "2016-05-20", 
      "round": null, 
      "wind": null
    }, 
    {
      "competition_ID": "12873993", 
      "compName": "Meeting Internacional", 
      "roundstage": "Final", 
      "venue": "Palafrugell", 
      "IndoorOutdoor": "Outdoor", 
      "agegroup": null, 
      "venueCountry": "ESP", 
      "rank": "1", 
      "event": "1500", 
      "result": "3:43.89", 
      "date": "2016-05-28", 
      "round": null, 
      "wind": null
    }, 
    {
      "competition_ID": "12874194", 
      "compName": "12th Meeting Iberoamericano de Atletismo, Estadio Iberoamericano", 
      "roundstage": "Final", 
      "venue": "Huelva", 
      "IndoorOutdoor": "Outdoor", 
      "agegroup": null, 
      "venueCountry": "ESP", 
      "rank": "2", 
      "event": "1500", 
      "result": "3:36.14", 
      "date": "2016-06-03", 
      "round": null, 
      "wind": null
    }, 
    {
      "competition_ID": "12875879", 
      "compName": "34th Meeting Madrid, Centro Deportivo Municipal Moratalaz", 
      "roundstage": "Prelim", 
      "venue": "Madrid", 
      "IndoorOutdoor": "Outdoor", 
      "agegroup": null, 
      "venueCountry": "ESP", 
      "rank": null, 
      "event": "800", 
      "result": null, 
      "date": "2016-06-23", 
      "round": "rB", 
      "wind": null
    }, 
    {
      "competition_ID": "12876017", 
      "compName": "16th Reunion Internacional de Bilbao", 
      "roundstage": "Final", 
      "venue": "Bilbao", 
      "IndoorOutdoor": "Outdoor", 
      "agegroup": null, 
      "venueCountry": "ESP", 
      "rank": "2", 
      "event": "800", 
      "result": "1:47.19", 
      "date": "2016-06-25", 
      "round": null, 
      "wind": null
    }, 
    {
      "competition_ID": "12876245", 
      "compName": null, 
      "roundstage": "Prelim", 
      "venue": "Amsterdam", 
      "IndoorOutdoor": "Outdoor", 
      "agegroup": null, 
      "venueCountry": "NED", 
      "rank": "3", 
      "event": "1500", 
      "result": "3:40.60", 
      "date": "2016-07-07", 
      "round": "h1", 
      "wind": null
    }, 
    {
      "competition_ID": "12876245", 
      "compName": null, 
      "roundstage": "Final", 
      "venue": "Amsterdam", 
      "IndoorOutdoor": "Outdoor", 
      "agegroup": null, 
      "venueCountry": "NED", 
      "rank": "2", 
      "event": "1500", 
      "result": "3:46.90", 
      "date": "2016-07-09", 
      "round": null, 
      "wind": null
    }, 
    {
      "competition_ID": "12876704", 
      "compName": "KBC-Nacht Van De Atletiek, KBC Night of Athletics, Stadion De Veen", 
      "roundstage": "Final", 
      "venue": "Heusden", 
      "IndoorOutdoor": "Outdoor", 
      "agegroup": null, 
      "venueCountry": "BEL", 
      "rank": "10", 
      "event": "1500", 
      "result": "3:37.16", 
      "date": "2016-07-16", 
      "round": null, 
      "wind": null
    }, 
    {
      "competition_ID": "12876969", 
      "compName": "National Championships, Complejo Deportivo Las Mestas", 
      "roundstage": "Prelim", 
      "venue": "Gij\u00c3\u00b3n", 
      "IndoorOutdoor": "Outdoor", 
      "agegroup": null, 
      "venueCountry": "ESP", 
      "rank": "2", 
      "event": "800", 
      "result": "1:49.60", 
      "date": "2016-07-23", 
      "round": "h1", 
      "wind": null
    }, 
    {
      "competition_ID": "12876969", 
      "compName": "National Championships, Complejo Deportivo Las Mestas", 
      "roundstage": "Final", 
      "venue": "Gij\u00c3\u00b3n", 
      "IndoorOutdoor": "Outdoor", 
      "agegroup": null, 
      "venueCountry": "ESP", 
      "rank": "4", 
      "event": "800", 
      "result": "1:50.76", 
      "date": "2016-07-24", 
      "round": null, 
      "wind": null
    }, 
    {
      "competition_ID": "12877460", 
      "compName": null, 
      "roundstage": "Prelim", 
      "venue": "R\u00c3\u00ado de Janeiro", 
      "IndoorOutdoor": "Outdoor", 
      "agegroup": null, 
      "venueCountry": "BRA", 
      "rank": "7", 
      "event": "1500", 
      "result": "3:39.73", 
      "date": "2016-08-16", 
      "round": "h1", 
      "wind": null
    }, 
    {
      "competition_ID": "12877460", 
      "compName": null, 
      "roundstage": "Prelim", 
      "venue": "R\u00c3\u00ado de Janeiro", 
      "IndoorOutdoor": "Outdoor", 
      "agegroup": null, 
      "venueCountry": "BRA", 
      "rank": "11", 
      "event": "1500", 
      "result": "3:56.54", 
      "date": "2016-08-18", 
      "round": "s2", 
      "wind": null
    }, 
    {
      "competition_ID": "12877460", 
      "compName": null, 
      "roundstage": "Final", 
      "venue": "R\u00c3\u00ado de Janeiro", 
      "IndoorOutdoor": "Outdoor", 
      "agegroup": null, 
      "venueCountry": "BRA", 
      "rank": "7", 
      "event": "1500", 
      "result": "3:51.06", 
      "date": "2016-08-20", 
      "round": null, 
      "wind": null
    }
  ], 
  "athlete_id": "84298", 
  "birthdate": "25.08.1990", 
  "height": "182", 
  "birthyear": "1990", 
  "accomplishments": [
    {
      "description": "European Silver Medallist", 
      "details": {
        "details": null
      }
    }, 
    {
      "description": "European Bronze Medallist", 
      "details": {
        "details": null
      }
    }, 
    {
      "description": "7th at Olympic Games", 
      "details": {
        "details": null
      }
    }, 
    {
      "description": "European Junior Champion", 
      "details": {
        "details": null
      }
    }, 
    {
      "description": "European U23 Championships Bronze Medallist", 
      "details": {
        "details": null
      }
    }, 
    {
      "description": "4th at World Youth Championships", 
      "details": {
        "details": null
      }
    }
  ], 
  "gender": "M", 
  "nationality": "ESP"
}